Workbook

Sheet Resumen
A1: Resumen de pendientes
A2: Se actualiza solo a partir de la hoja Pendientes.
A4: Estado | B4: Cantidad | C4: % del total | E4: Plan | F4: Tema | G4: Abiertos | H4: Terminados | I4: Descartados | J4: Total
A5: No iniciado | B5: =COUNTIF(Pendientes!$F$5:$F$308,A5) | C5: =IF($B$12=0,0,B5/$B$12) | E5: 02 | F5: Roles y permisos del tendero | G5: =COUNTIFS(Pendientes!$B$5:$B$308,E5,Pendientes!$F$5:$F$308,"<>Terminado",Pendientes!$F$5:$F$308,"<>Descartado")-COUNTIFS(Pendientes!$B$5:$B$308,E5,Pendientes!$F$5:$F$308,"") | H5: =COUNTIFS(Pendientes!$B$5:$B$308,E5,Pendientes!$F$5:$F$308,"Terminado") | I5: =COUNTIFS(Pendientes!$B$5:$B$308,E5,Pendientes!$F$5:$F$308,"Descartado") | J5: =COUNTIF(Pendientes!$B$5:$B$308,E5)
A6: En progreso | B6: =COUNTIF(Pendientes!$F$5:$F$308,A6) | C6: =IF($B$12=0,0,B6/$B$12) | E6: 04 | F6: Posventa y facturación | G6: =COUNTIFS(Pendientes!$B$5:$B$308,E6,Pendientes!$F$5:$F$308,"<>Terminado",Pendientes!$F$5:$F$308,"<>Descartado")-COUNTIFS(Pendientes!$B$5:$B$308,E6,Pendientes!$F$5:$F$308,"") | H6: =COUNTIFS(Pendientes!$B$5:$B$308,E6,Pendientes!$F$5:$F$308,"Terminado") | I6: =COUNTIFS(Pendientes!$B$5:$B$308,E6,Pendientes!$F$5:$F$308,"Descartado") | J6: =COUNTIF(Pendientes!$B$5:$B$308,E6)
A7: Parcial | B7: =COUNTIF(Pendientes!$F$5:$F$308,A7) | C7: =IF($B$12=0,0,B7/$B$12) | E7: 05 | F7: Egresos de caja chica y Redis | G7: =COUNTIFS(Pendientes!$B$5:$B$308,E7,Pendientes!$F$5:$F$308,"<>Terminado",Pendientes!$F$5:$F$308,"<>Descartado")-COUNTIFS(Pendientes!$B$5:$B$308,E7,Pendientes!$F$5:$F$308,"") | H7: =COUNTIFS(Pendientes!$B$5:$B$308,E7,Pendientes!$F$5:$F$308,"Terminado") | I7: =COUNTIFS(Pendientes!$B$5:$B$308,E7,Pendientes!$F$5:$F$308,"Descartado") | J7: =COUNTIF(Pendientes!$B$5:$B$308,E7)
A8: Terminado | B8: =COUNTIF(Pendientes!$F$5:$F$308,A8) | C8: =IF($B$12=0,0,B8/$B$12) | E8: 06 | F8: Notificaciones avanzadas | G8: =COUNTIFS(Pendientes!$B$5:$B$308,E8,Pendientes!$F$5:$F$308,"<>Terminado",Pendientes!$F$5:$F$308,"<>Descartado")-COUNTIFS(Pendientes!$B$5:$B$308,E8,Pendientes!$F$5:$F$308,"") | H8: =COUNTIFS(Pendientes!$B$5:$B$308,E8,Pendientes!$F$5:$F$308,"Terminado") | I8: =COUNTIFS(Pendientes!$B$5:$B$308,E8,Pendientes!$F$5:$F$308,"Descartado") | J8: =COUNTIF(Pendientes!$B$5:$B$308,E8)
A9: Bloqueado | B9: =COUNTIF(Pendientes!$F$5:$F$308,A9) | C9: =IF($B$12=0,0,B9/$B$12) | E9: 07 | F9: App compañera Flutter | G9: =COUNTIFS(Pendientes!$B$5:$B$308,E9,Pendientes!$F$5:$F$308,"<>Terminado",Pendientes!$F$5:$F$308,"<>Descartado")-COUNTIFS(Pendientes!$B$5:$B$308,E9,Pendientes!$F$5:$F$308,"") | H9: =COUNTIFS(Pendientes!$B$5:$B$308,E9,Pendientes!$F$5:$F$308,"Terminado") | I9: =COUNTIFS(Pendientes!$B$5:$B$308,E9,Pendientes!$F$5:$F$308,"Descartado") | J9: =COUNTIF(Pendientes!$B$5:$B$308,E9)
A10: Descartado | B10: =COUNTIF(Pendientes!$F$5:$F$308,A10) | C10: =IF($B$12=0,0,B10/$B$12) | E10: 08 | F10: Funcionalidades faltantes | G10: =COUNTIFS(Pendientes!$B$5:$B$308,E10,Pendientes!$F$5:$F$308,"<>Terminado",Pendientes!$F$5:$F$308,"<>Descartado")-COUNTIFS(Pendientes!$B$5:$B$308,E10,Pendientes!$F$5:$F$308,"") | H10: =COUNTIFS(Pendientes!$B$5:$B$308,E10,Pendientes!$F$5:$F$308,"Terminado") | I10: =COUNTIFS(Pendientes!$B$5:$B$308,E10,Pendientes!$F$5:$F$308,"Descartado") | J10: =COUNTIF(Pendientes!$B$5:$B$308,E10)
A11: Por verificar | B11: =COUNTIF(Pendientes!$F$5:$F$308,A11) | C11: =IF($B$12=0,0,B11/$B$12) | E11: 09 | F11: Rediseño: paleta y tokens | G11: =COUNTIFS(Pendientes!$B$5:$B$308,E11,Pendientes!$F$5:$F$308,"<>Terminado",Pendientes!$F$5:$F$308,"<>Descartado")-COUNTIFS(Pendientes!$B$5:$B$308,E11,Pendientes!$F$5:$F$308,"") | H11: =COUNTIFS(Pendientes!$B$5:$B$308,E11,Pendientes!$F$5:$F$308,"Terminado") | I11: =COUNTIFS(Pendientes!$B$5:$B$308,E11,Pendientes!$F$5:$F$308,"Descartado") | J11: =COUNTIF(Pendientes!$B$5:$B$308,E11)
A12: Total | B12: =SUM(B5:B11) | E12: 10 | F12: Lint y calidad de código | G12: =COUNTIFS(Pendientes!$B$5:$B$308,E12,Pendientes!$F$5:$F$308,"<>Terminado",Pendientes!$F$5:$F$308,"<>Descartado")-COUNTIFS(Pendientes!$B$5:$B$308,E12,Pendientes!$F$5:$F$308,"") | H12: =COUNTIFS(Pendientes!$B$5:$B$308,E12,Pendientes!$F$5:$F$308,"Terminado") | I12: =COUNTIFS(Pendientes!$B$5:$B$308,E12,Pendientes!$F$5:$F$308,"Descartado") | J12: =COUNTIF(Pendientes!$B$5:$B$308,E12)
A13: Abiertos (sin terminar ni descartar) | B13: =B12-B8-B10 | E13: 11 | F13: Consejero IA "+0u" | G13: =COUNTIFS(Pendientes!$B$5:$B$308,E13,Pendientes!$F$5:$F$308,"<>Terminado",Pendientes!$F$5:$F$308,"<>Descartado")-COUNTIFS(Pendientes!$B$5:$B$308,E13,Pendientes!$F$5:$F$308,"") | H13: =COUNTIFS(Pendientes!$B$5:$B$308,E13,Pendientes!$F$5:$F$308,"Terminado") | I13: =COUNTIFS(Pendientes!$B$5:$B$308,E13,Pendientes!$F$5:$F$308,"Descartado") | J13: =COUNTIF(Pendientes!$B$5:$B$308,E13)
A14: Abiertos de prioridad Alta | B14: =COUNTIFS(Pendientes!$G$5:$G$308,"Alta",Pendientes!$F$5:$F$308,"<>Terminado",Pendientes!$F$5:$F$308,"<>Descartado") | E14: 12 | F14: Rediseño: tipografía y forma | G14: =COUNTIFS(Pendientes!$B$5:$B$308,E14,Pendientes!$F$5:$F$308,"<>Terminado",Pendientes!$F$5:$F$308,"<>Descartado")-COUNTIFS(Pendientes!$B$5:$B$308,E14,Pendientes!$F$5:$F$308,"") | H14: =COUNTIFS(Pendientes!$B$5:$B$308,E14,Pendientes!$F$5:$F$308,"Terminado") | I14: =COUNTIFS(Pendientes!$B$5:$B$308,E14,Pendientes!$F$5:$F$308,"Descartado") | J14: =COUNTIF(Pendientes!$B$5:$B$308,E14)
E15: 13 | F15: Consejero IA → borrador de orden | G15: =COUNTIFS(Pendientes!$B$5:$B$308,E15,Pendientes!$F$5:$F$308,"<>Terminado",Pendientes!$F$5:$F$308,"<>Descartado")-COUNTIFS(Pendientes!$B$5:$B$308,E15,Pendientes!$F$5:$F$308,"") | H15: =COUNTIFS(Pendientes!$B$5:$B$308,E15,Pendientes!$F$5:$F$308,"Terminado") | I15: =COUNTIFS(Pendientes!$B$5:$B$308,E15,Pendientes!$F$5:$F$308,"Descartado") | J15: =COUNTIF(Pendientes!$B$5:$B$308,E15)
A16: Planes 01 y 03: implementados y verificados, sin pendientes. | E16: 14 | F16: Rediseño: verificación | G16: =COUNTIFS(Pendientes!$B$5:$B$308,E16,Pendientes!$F$5:$F$308,"<>Terminado",Pendientes!$F$5:$F$308,"<>Descartado")-COUNTIFS(Pendientes!$B$5:$B$308,E16,Pendientes!$F$5:$F$308,"") | H16: =COUNTIFS(Pendientes!$B$5:$B$308,E16,Pendientes!$F$5:$F$308,"Terminado") | I16: =COUNTIFS(Pendientes!$B$5:$B$308,E16,Pendientes!$F$5:$F$308,"Descartado") | J16: =COUNTIF(Pendientes!$B$5:$B$308,E16)
E17: 15 | F17: Migración de Fiados en producción | G17: =COUNTIFS(Pendientes!$B$5:$B$308,E17,Pendientes!$F$5:$F$308,"<>Terminado",Pendientes!$F$5:$F$308,"<>Descartado")-COUNTIFS(Pendientes!$B$5:$B$308,E17,Pendientes!$F$5:$F$308,"") | H17: =COUNTIFS(Pendientes!$B$5:$B$308,E17,Pendientes!$F$5:$F$308,"Terminado") | I17: =COUNTIFS(Pendientes!$B$5:$B$308,E17,Pendientes!$F$5:$F$308,"Descartado") | J17: =COUNTIF(Pendientes!$B$5:$B$308,E17)
E18: 16 | F18: Recepción de mercancía | G18: =COUNTIFS(Pendientes!$B$5:$B$308,E18,Pendientes!$F$5:$F$308,"<>Terminado",Pendientes!$F$5:$F$308,"<>Descartado")-COUNTIFS(Pendientes!$B$5:$B$308,E18,Pendientes!$F$5:$F$308,"") | H18: =COUNTIFS(Pendientes!$B$5:$B$308,E18,Pendientes!$F$5:$F$308,"Terminado") | I18: =COUNTIFS(Pendientes!$B$5:$B$308,E18,Pendientes!$F$5:$F$308,"Descartado") | J18: =COUNTIF(Pendientes!$B$5:$B$308,E18)
E19: 17 | F19: Motor de riesgo unificado | G19: =COUNTIFS(Pendientes!$B$5:$B$308,E19,Pendientes!$F$5:$F$308,"<>Terminado",Pendientes!$F$5:$F$308,"<>Descartado")-COUNTIFS(Pendientes!$B$5:$B$308,E19,Pendientes!$F$5:$F$308,"") | H19: =COUNTIFS(Pendientes!$B$5:$B$308,E19,Pendientes!$F$5:$F$308,"Terminado") | I19: =COUNTIFS(Pendientes!$B$5:$B$308,E19,Pendientes!$F$5:$F$308,"Descartado") | J19: =COUNTIF(Pendientes!$B$5:$B$308,E19)
E20: 18 | F20: Simulador con motor único | G20: =COUNTIFS(Pendientes!$B$5:$B$308,E20,Pendientes!$F$5:$F$308,"<>Terminado",Pendientes!$F$5:$F$308,"<>Descartado")-COUNTIFS(Pendientes!$B$5:$B$308,E20,Pendientes!$F$5:$F$308,"") | H20: =COUNTIFS(Pendientes!$B$5:$B$308,E20,Pendientes!$F$5:$F$308,"Terminado") | I20: =COUNTIFS(Pendientes!$B$5:$B$308,E20,Pendientes!$F$5:$F$308,"Descartado") | J20: =COUNTIF(Pendientes!$B$5:$B$308,E20)
E21: 19 | F21: Requisitos de la intervención | G21: =COUNTIFS(Pendientes!$B$5:$B$308,E21,Pendientes!$F$5:$F$308,"<>Terminado",Pendientes!$F$5:$F$308,"<>Descartado")-COUNTIFS(Pendientes!$B$5:$B$308,E21,Pendientes!$F$5:$F$308,"") | H21: =COUNTIFS(Pendientes!$B$5:$B$308,E21,Pendientes!$F$5:$F$308,"Terminado") | I21: =COUNTIFS(Pendientes!$B$5:$B$308,E21,Pendientes!$F$5:$F$308,"Descartado") | J21: =COUNTIF(Pendientes!$B$5:$B$308,E21)
E22: 20 | F22: Cobertura real del backend | G22: =COUNTIFS(Pendientes!$B$5:$B$308,E22,Pendientes!$F$5:$F$308,"<>Terminado",Pendientes!$F$5:$F$308,"<>Descartado")-COUNTIFS(Pendientes!$B$5:$B$308,E22,Pendientes!$F$5:$F$308,"") | H22: =COUNTIFS(Pendientes!$B$5:$B$308,E22,Pendientes!$F$5:$F$308,"Terminado") | I22: =COUNTIFS(Pendientes!$B$5:$B$308,E22,Pendientes!$F$5:$F$308,"Descartado") | J22: =COUNTIF(Pendientes!$B$5:$B$308,E22)
E23: 21 | F23: Refactorización y tiempo real | G23: =COUNTIFS(Pendientes!$B$5:$B$308,E23,Pendientes!$F$5:$F$308,"<>Terminado",Pendientes!$F$5:$F$308,"<>Descartado")-COUNTIFS(Pendientes!$B$5:$B$308,E23,Pendientes!$F$5:$F$308,"") | H23: =COUNTIFS(Pendientes!$B$5:$B$308,E23,Pendientes!$F$5:$F$308,"Terminado") | I23: =COUNTIFS(Pendientes!$B$5:$B$308,E23,Pendientes!$F$5:$F$308,"Descartado") | J23: =COUNTIF(Pendientes!$B$5:$B$308,E23)
E24: 22 | F24: Panel interno y funciones por tienda | G24: =COUNTIFS(Pendientes!$B$5:$B$308,E24,Pendientes!$F$5:$F$308,"<>Terminado",Pendientes!$F$5:$F$308,"<>Descartado")-COUNTIFS(Pendientes!$B$5:$B$308,E24,Pendientes!$F$5:$F$308,"") | H24: =COUNTIFS(Pendientes!$B$5:$B$308,E24,Pendientes!$F$5:$F$308,"Terminado") | I24: =COUNTIFS(Pendientes!$B$5:$B$308,E24,Pendientes!$F$5:$F$308,"Descartado") | J24: =COUNTIF(Pendientes!$B$5:$B$308,E24)
E25: 23 | F25: IA con valor, medida y con privacidad | G25: =COUNTIFS(Pendientes!$B$5:$B$308,E25,Pendientes!$F$5:$F$308,"<>Terminado",Pendientes!$F$5:$F$308,"<>Descartado")-COUNTIFS(Pendientes!$B$5:$B$308,E25,Pendientes!$F$5:$F$308,"") | H25: =COUNTIFS(Pendientes!$B$5:$B$308,E25,Pendientes!$F$5:$F$308,"Terminado") | I25: =COUNTIFS(Pendientes!$B$5:$B$308,E25,Pendientes!$F$5:$F$308,"Descartado") | J25: =COUNTIF(Pendientes!$B$5:$B$308,E25)

Sheet Pendientes
A1: StockPilot · Seguimiento de pendientes de los planes 02 a 22
A2: Revisado contra el código de main el 27-09-2026. Cambie el Estado con la lista desplegable y anote la fecha, quién y qué en la Bitácora. Los planes 01 y 03 no tienen pendientes.
A4: ID | B4: Plan | C4: Área | D4: Pendiente | E4: Tipo | F4: Estado | G4: Prioridad | H4: Evidencia / dónde está | I4: Notas | J4: Responsable | K4: Última actualización | L4: Días sin actualizar
A5: P02-01 | B5: 02 | C5: Seguridad | D5: Un Tendero puede cambiar los datos de su tienda (incluido su propio límite de egresos) y desactivarla: PUT /api/tienda/update/:id y /api/tienda/estado/:id solo piden requireLogin | E5: Observación / defecto | F5: No iniciado | G5: Alta | H5: routes/storeRoutes.js; storeController verifica que la tienda sea la del usuario, pero no su rol. Verificado leyendo el código (28-sep). | I5: Plan 22, fase I0: agregar requireAdmin y una prueba de integración con sesión de Tendero que espere 403. | K5: 46293 | L5: =IF(K5="","",TODAY()-K5)
A6: P04-01 | B6: 04 | C6: Posventa | D6: Devolución de productos: reintegrar la cantidad al inventario y registrar la salida de dinero de la caja o un saldo a favor | E6: Pendiente del plan | F6: No iniciado | G6: Media | H6: Plan 04, vertiente A. No existe endpoint ni pantalla de devoluciones (búsqueda en controllers, routes y frontend: sin resultados). | K6: 46292 | L6: =IF(K6="","",TODAY()-K6)
A7: P04-02 | B7: 04 | C7: Posventa | D7: Anulación de ventas registradas por error, con motivo, usuario que anula y reajuste automático del arqueo esperado | E7: Pendiente del plan | F7: No iniciado | G7: Alta | H7: Plan 04, vertiente A. Sin implementación. | I7: Los errores de registro son la dificultad n.º 1 de la encuesta (53 %): anular bien una venta equivocada es parte de tener datos confiables. | K7: 46292 | L7: =IF(K7="","",TODAY()-K7)
A8: P04-03 | B8: 04 | C8: Posventa | D8: Reimpresión de comprobantes desde el historial de ventas | E8: Pendiente del plan | F8: No iniciado | G8: Media | H8: Plan 04, vertiente A. El diseño detallado está en el plan 19, sección 3.6 (recibo PDF y vista de factura). | I8: Se puede hacer junto con la fila del plan 19 sobre el recibo en PDF. | K8: 46292 | L8: =IF(K8="","",TODAY()-K8)
A9: P04-04 | B9: 04 | C9: Caja | D9: Egresos de caja chica con motivo, foto opcional y aprobación del administrador | E9: Pendiente del plan | F9: Terminado | G9: Media | H9: Implementado por el plan 05: ExpenseModal.jsx, HistorialEgresosTab.jsx, endpoints /api/caja/egreso. Cubierto por la prueba de integración caja.test.js. | K9: 46292 | L9: =IF(K9="","",TODAY()-K9)
A10: P04-05 | B10: 04 | C10: Fiscal | D10: Facturación electrónica oficial ante la DIAN (XML UBL 2.1, firma y QR) mediante un proveedor autorizado | E10: Trabajo futuro | F10: No iniciado | G10: Baja | H10: Plan 04, vertiente B. Acordado como trabajo futuro para la versión académica; el POS usa documento equivalente. | I10: Revisar si es obligatoria para los clientes objetivo antes del lanzamiento comercial. | K10: 46292 | L10: =IF(K10="","",TODAY()-K10)
A11: P05-01 | B11: 05 | C11: Infraestructura | D11: Activar Redis en producción (REDIS_URL) cuando haya varias instancias del servidor | E11: Pendiente del plan | F11: Por verificar | G11: Media | H11: Plan 05, sección 4. El código ya lo soporta con respaldo en PostgreSQL. No está confirmado si producción tiene REDIS_URL. | I11: Requisito para el Sprint 6 (2 réplicas) y para el tiempo real con varias réplicas (plan 21, T3). | K11: 46292 | L11: =IF(K11="","",TODAY()-K11)
A12: P06-01 | B12: 06 | C12: Notificaciones | D12: Notificaciones de fases 1 y 2: descuadre de caja, cambio de precio, comunicados, orden enviada y metas de ventas | E12: Pendiente del plan | F12: Terminado | G12: Media | H12: Tipos descuadre_caja, cambio_precio, anuncio_admin, orden_enviada y meta_ventas presentes en los controladores y en NotificationCenter.jsx. | K12: 46292 | L12: =IF(K12="","",TODAY()-K12)
A13: P06-02 | B13: 06 | C13: Notificaciones | D13: Umbrales de metas de ventas editables desde el panel del administrador (hoy fijos) | E13: Trabajo futuro | F13: No iniciado | G13: Baja | H13: Plan 06, punto 5 ("a futuro"). | K13: 46292 | L13: =IF(K13="","",TODAY()-K13)
A14: P07-01 | B14: 07 | C14: Móvil | D14: App nativa del Tendero en Flutter: vender (con fiado), caja con egresos, recibir mercancía, alertas y catálogo | E14: Pendiente del plan | F14: En progreso | G14: Alta | H14: Plan 07, sección 6 (3-oct). Repositorio aparte; la construye el equipo. | I14: Sigue en paralelo y sin fecha de piloto; se presenta en la sustentación (nov., día por confirmar). Desde el arranque del piloto: entorno aparte y sin versión nueva (plan 07, 6.1). Decisión del 6-oct. | K14: 46301 | L14: =IF(K14="","",TODAY()-K14)
A15: P07-02 | B15: 07 | C15: Backend | D15: Backend para la app: sesión por canal (web y app a la vez), Ventas.canal y docs/contrato_api_app_tendero.md con prueba por endpoint | E15: Pendiente del plan | F15: Terminado | G15: Alta | H15: Plan 07, sección 6.3; plan 22, sección 5 (A.1). Rama feat/backend-app-tendero. | I15: Mezclado en main (merge cb028d9). | K15: 46301 | L15: =IF(K15="","",TODAY()-K15)
A16: P07-03 | B16: 07 | C16: Visita | D16: Guion de la fase 4 (tareas, medidas, cuestionario), autorización de datos y formato de línea base para la visita | E16: Pendiente del plan | F16: No iniciado | G16: Alta | H16: Plan 22, sección 5 (A.2). | I16: Antes de la visita, ahora con la web en modo básico y una tienda de demostración (decisión del 6-oct). | K16: 46301 | L16: =IF(K16="","",TODAY()-K16)
A17: P07-04 | B17: 07 | C17: Infraestructura | D17: Decidir si se mantiene despierto Render en horario de tienda con un ping (plan gratuito: se duerme tras 15 min y tarda ~1 min en volver) | E17: Decisión pendiente | F17: No iniciado | G17: Media | H17: Plan 22, sección 5 (C.5). | I17: Mientras tanto, abrir la app unos minutos antes de entrar a cada tienda. | K17: 46292 | L17: =IF(K17="","",TODAY()-K17)
A18: P07-05 | B18: 07 | C18: Móvil | D18: Distribución en iPhone (requiere Mac y membresía de pago de Apple para TestFlight) | E18: Trabajo futuro | F18: No iniciado | G18: Baja | H18: Plan 07, sección 6.3. | I18: Después del piloto. | K18: 46292 | L18: =IF(K18="","",TODAY()-K18)
A19: P08-01 | B19: 08 | C19: Cartera | D19: Gestión de fiados con clientes, abonos y análisis de riesgo con IA | E19: Pendiente del plan | F19: Terminado | G19: Alta | H19: CarteraPage.jsx, clienteController.js, aiController.assessClientRisk. Cubierto por cartera.test.js (integración). | K19: 46292 | L19: =IF(K19="","",TODAY()-K19)
A20: P08-02 | B20: 08 | C20: Métodos de pago | D20: Registrar el método de pago de cada venta y usar solo el efectivo en el arqueo | E20: Pendiente del plan | F20: Terminado | G20: Media | H20: Implementado en el plan 01 (PaymentModal, Ventas.metodo_pago). | K20: 46292 | L20: =IF(K20="","",TODAY()-K20)
A21: P08-03 | B21: 08 | C21: Analítica | D21: Panel de rentabilidad por producto: margen × unidades, ranking y alerta de "producto trampa" (clase A con margen < 10 %) | E21: Pendiente del plan | F21: Parcial | G21: Media | H21: Hoy existe el margen promedio en el Dashboard y una columna de ganancia en el Excel de reportes; no hay vista por producto ni alertas. | K21: 46292 | L21: =IF(K21="","",TODAY()-K21)
A22: P08-04 | B22: 08 | C22: Inventario | D22: Conteo físico guiado: listar productos, capturar el conteo real, reporte de diferencias valorizado y ajuste masivo | E22: Pendiente del plan | F22: Parcial | G22: Media | H22: Existe el ajuste individual "por conteo físico" (inventoryController). No hay sesión de conteo ni tablas ConteoFisico/DetalleConteo. | I22: Sirve de instrumento para el indicador "exactitud de inventario" del piloto (fase 5). | K22: 46292 | L22: =IF(K22="","",TODAY()-K22)
A23: P08-05 | B23: 08 | C23: Proveedores | D23: Historial de precios de costo por producto y proveedor, con gráfica de evolución | E23: Pendiente del plan | F23: No iniciado | G23: Media | H23: Historial_Precios registra cambios del precio de venta hechos por estrategias de IA, no del costo. | K23: 46292 | L23: =IF(K23="","",TODAY()-K23)
A24: P08-06 | B24: 08 | C24: Notificaciones | D24: Notificaciones push en el celular (Web Push con service worker) | E24: Pendiente del plan | F24: No iniciado | G24: Media | H24: Plan 08, punto 6. Relacionado con las alertas en tiempo real del plan 21. | K24: 46292 | L24: =IF(K24="","",TODAY()-K24)
A25: P08-07 | B25: 08 | C25: Canales | D25: Integración con WhatsApp para alertas y pedidos | E25: Trabajo futuro | F25: No iniciado | G25: Media | H25: Plan 08, tier 3. | I25: Decisión previa de Luis: whatsapp-web.js detrás de una capa de abstracción para el MVP académico; API oficial de Meta para el lanzamiento comercial. | K25: 46292 | L25: =IF(K25="","",TODAY()-K25)
A26: P08-08 | B26: 08 | C26: Canales | D26: Catálogo público de la tienda ("vitrina digital") para los clientes del barrio | E26: Trabajo futuro | F26: No iniciado | G26: Baja | H26: Plan 08, tier 3. | K26: 46292 | L26: =IF(K26="","",TODAY()-K26)
A27: P08-09 | B27: 08 | C27: Multi-tienda | D27: Vista consolidada de varias tiendas para un mismo administrador | E27: Trabajo futuro | F27: Por verificar | G27: Baja | H27: Plan 08, tier 3. Hay soporte de varias tiendas (TiendasPage, scripts/migrate_multistore.js); falta confirmar si existe una vista consolidada. | K27: 46292 | L27: =IF(K27="","",TODAY()-K27)
A28: P09-01 | B28: 09 | C28: UX | D28: La barra lateral queda por encima del fondo de los modales y se puede navegar con un cobro a medias | E28: Observación / defecto | F28: Parcial | G28: Media | H28: En escritorio ya está resuelto (Sidebar z-40 frente a modales z-50/z-100). En móvil el menú abierto usa z-[200]: verificar a 390 px con un modal abierto. | I28: Reportado también en el plan 14, observación 1. | K28: 46292 | L28: =IF(K28="","",TODAY()-K28)
A29: P09-02 | B29: 09 | C29: UX | D29: Auditoría: 5 tarjetas en una grilla de 4 columnas deja la última sola | E29: Observación / defecto | F29: Por verificar | G29: Baja | H29: AuditoriaPage.jsx sigue con lg:grid-cols-4. | K29: 46292 | L29: =IF(K29="","",TODAY()-K29)
A30: P09-03 | B30: 09 | C30: POS | D30: Historial de ventas sin paginación: cargarMasVentas existe pero no está conectado a ningún botón | E30: Observación / defecto | F30: No iniciado | G30: Media | H30: TODO en frontend/src/components/puntoventa/HistorialVentasTab.jsx, línea 70. | I30: Solo se ve la primera página de ventas. | K30: 46292 | L30: =IF(K30="","",TODAY()-K30)
A31: P09-04 | B31: 09 | C31: Dependencias | D31: react-router-dom y axios están en devDependencies siendo dependencias de ejecución | E31: Observación / defecto | F31: No iniciado | G31: Baja | H31: frontend/package.json. | I31: Puede romper un build que instale solo dependencias de producción. | K31: 46292 | L31: =IF(K31="","",TODAY()-K31)
A32: P09-05 | B32: 09 | C32: Rendimiento | D32: Chunks del frontend mayores a 500 kB; cargar recharts y las rutas de forma diferida | E32: Observación / defecto | F32: No iniciado | G32: Media | H32: Plan 09, sección 6. Solo 2 de 23 páginas usan lazy(). | I32: Incluido en el plan 21, R3 punto 4. | K32: 46292 | L32: =IF(K32="","",TODAY()-K32)
A33: P09-06 | B33: 09 | C33: Diseño | D33: Tokens de @theme que solo usa JS (ToastContext) pueden dejar de emitirse si ninguna clase los usa | E33: Observación / defecto | F33: No iniciado | G33: Baja | H33: Plan 09, sección 6. | K33: 46292 | L33: =IF(K33="","",TODAY()-K33)
A34: P10-01 | B34: 10 | C34: Calidad | D34: Agregar eslint.config.js y la dependencia eslint al backend para que el lint corra en CI | E34: Pendiente del plan | F34: No iniciado | G34: Media | H34: Plan 10, secciones 2 y 4. No existe eslint.config.* en la raíz. | K34: 46292 | L34: =IF(K34="","",TODAY()-K34)
A35: P10-02 | B35: 10 | C35: Pruebas | D35: Plantilla de generar_reporte.js: versión de Vitest corregida (v4), pero sigue diciendo "Certificado Oficial" y "Production-Ready" | E35: Observación / defecto | F35: Parcial | G35: Media | H35: generar_reporte.js, líneas 68-108. | I35: Corregir el tono antes de anexar el reporte a un entregable. | K35: 46292 | L35: =IF(K35="","",TODAY()-K35)
A36: P10-03 | B36: 10 | C36: Seguridad | D36: test_disable_2fa.js en la raíz inserta datos en la base real | E36: Observación / defecto | F36: No iniciado | G36: Baja | H36: Plan 10, sección 3.2. | I36: Moverlo a scripts/ con la protección de base de pruebas o eliminarlo. | K36: 46292 | L36: =IF(K36="","",TODAY()-K36)
A37: P10-04 | B37: 10 | C37: Datos | D37: seed_test_data.js hace TRUNCATE de todas las tablas sin verificar a qué base apunta | E37: Observación / defecto | F37: No iniciado | G37: Media | H37: Plan 10, sección 3.1. | I37: Agregar la misma protección de setupTestDb.js (nombre terminado en _test y host local). | K37: 46292 | L37: =IF(K37="","",TODAY()-K37)
A38: P11-01 | B38: 11 | C38: Motor | D38: Acotar la tendencia (0,5× a 2×) y exigir un mínimo de ventas | E38: Observación / defecto | F38: Terminado | G38: Media | H38: utils/reposicion.js: TENDENCIA_MIN/MAX y MIN_VENTAS_PARA_TENDENCIA. | K38: 46292 | L38: =IF(K38="","",TODAY()-K38)
A39: P11-02 | B39: 11 | C39: IA | D39: Confianza 50 %/20 % en todas las tarjetas mientras no haya historial en Feedback_IA | E39: Observación / defecto | F39: No iniciado | G39: Baja | H39: Plan 11, sección 5. | I39: Ya no se resuelve con los datos del piloto: el modo básico no muestra la IA y el piloto no la evalúa (plan 23). Con el evaluador corregido (P23-01) se podrá medir en el modo avanzado. | K39: 46301 | L39: =IF(K39="","",TODAY()-K39)
A40: P12-01 | B40: 12 | C40: UX | D40: Tabla de Movimientos: la columna Observaciones queda fuera de vista | E40: Observación / defecto | F40: No iniciado | G40: Baja | H40: Plan 12, sección 5. | K40: 46292 | L40: =IF(K40="","",TODAY()-K40)
A41: P12-02 | B41: 12 | C41: UX | D41: Columna de producto estrecha en Productos y Movimientos (nombres largos en 3 líneas) | E41: Observación / defecto | F41: No iniciado | G41: Baja | H41: Plan 12, sección 5, y plan 14, observación 6. | K41: 46292 | L41: =IF(K41="","",TODAY()-K41)
A42: P12-03 | B42: 12 | C42: Motor | D42: Productos con unidades marcados como "AGOTADO" | E42: Observación / defecto | F42: Terminado | G42: Media | H42: Resuelto con los niveles agotado/crítico/reponer/ok del plan 17. | K42: 46292 | L42: =IF(K42="","",TODAY()-K42)
A43: P12-04 | B43: 12 | C43: Diseño | D43: La utilidad titular fija line-height 1 y junta los títulos de dos líneas | E43: Observación / defecto | F43: No iniciado | G43: Baja | H43: Plan 12, sección 5. | I43: Subir a 1,05 si molesta. | K43: 46292 | L43: =IF(K43="","",TODAY()-K43)
A44: P13-01 | B44: 13 | C44: Proveedores | D44: Máquina de estados formal en PATCH /api/ordenes/:id/estado (hoy solo rechaza "Completada" y acepta cualquier otro texto) | E44: Pendiente del plan | F44: Parcial | G44: Media | H44: Plan 13, secciones 10 y 13; suppliersController.updateOrderStatus. | K44: 46292 | L44: =IF(K44="","",TODAY()-K44)
A45: P14-01 | B45: 14 | C45: UX | D45: Los avisos (toasts) tapan los botones de la esquina superior derecha durante unos 5 segundos | E45: Observación / defecto | F45: No iniciado | G45: Baja | H45: ToastContext.jsx: top 20 px, right 20 px. | K45: 46292 | L45: =IF(K45="","",TODAY()-K45)
A46: P14-02 | B46: 14 | C46: Caja | D46: Si falla la consulta de la caja, el modal ofrece "Abrir caja" aunque haya un turno abierto | E46: Observación / defecto | F46: No iniciado | G46: Media | H46: Plan 14, observación 4. | I46: Distinguir "sin turno" de "no se pudo consultar". | K46: 46292 | L46: =IF(K46="","",TODAY()-K46)
A47: P14-03 | B47: 14 | C47: UX | D47: Avisos de error duplicados en desarrollo (React StrictMode) | E47: Observación / defecto | F47: Descartado | G47: Baja | H47: Solo pasa en desarrollo; en producción sale uno. | K47: 46292 | L47: =IF(K47="","",TODAY()-K47)
A48: P14-04 | B48: 14 | C48: Git | D48: Subir a main las ramas del rediseño (fases 2 a 4) | E48: Pendiente del plan | F48: Terminado | G48: Media | H48: Merges en el historial de Git (feature/rediseno-visual, feature/rediseno-fase4, etc.). | K48: 46292 | L48: =IF(K48="","",TODAY()-K48)
A49: P15-01 | B49: 15 | C49: Base de datos | D49: El esquema vive en dos lugares (init_pg.sql y la auto-migración de config/database.js), lo que produce brechas como la de Fiados | E49: Observación / defecto | F49: No iniciado | G49: Media | H49: Plan 15, sección 6. | I49: Incluido en el plan 21, R4. | K49: 46292 | L49: =IF(K49="","",TODAY()-K49)
A50: P15-02 | B50: 15 | C50: Base de datos | D50: init_pg.sql no podía crear una base nueva (dependencia circular Tienda ↔ Usuarios) | E50: Observación / defecto | F50: Terminado | G50: Media | H50: Corregido en el plan 20, sección 8.1. | K50: 46292 | L50: =IF(K50="","",TODAY()-K50)
A51: P16-01 | B51: 16 | C51: IA | D51: "Aprendizaje de la IA" como lo proponía el documento original | E51: Pendiente del plan | F51: Descartado | G51: Baja | H51: Ya existe por otra vía: feedbackController + runDailyAIEvaluation (plan 16, sección 1). | K51: 46292 | L51: =IF(K51="","",TODAY()-K51)
A52: P16-02 | B52: 16 | C52: Pruebas | D52: Pruebas de la recepción de mercancía: cantidad recibida igual, menor y mayor a la pedida | E52: Pendiente del plan | F52: No iniciado | G52: Media | H52: Plan 16, sección 6. No está entre los 7 flujos de integración del plan 20. | I52: Incluido en el plan 21, R0. | K52: 46292 | L52: =IF(K52="","",TODAY()-K52)
A53: P17-01 | B53: 17 | C53: Motor | D53: Consolidar las consultas de velocidad restantes | E53: Pendiente del plan | F53: Descartado | G53: Baja | H53: Plan 17, sección 8.7, fase 6: descartado por bajo beneficio. | K53: 46292 | L53: =IF(K53="","",TODAY()-K53)
A54: P17-02 | B54: 17 | C54: Productos | D54: El código de barras es obligatorio en ProductFormModal y bloquea en silencio la edición de productos sin código | E54: Observación / defecto | F54: No iniciado | G54: Alta | H54: ProductFormModal.jsx, línea 344 (required). Plan 17, sección 8.8. | I54: Si hay productos reales sin código, no se pueden editar desde la interfaz. | K54: 46292 | L54: =IF(K54="","",TODAY()-K54)
A55: P17-03 | B55: 17 | C55: Git | D55: Probar manualmente y subir a main la unificación del motor de riesgo | E55: Pendiente del plan | F55: Terminado | G55: Alta | H55: Merge de feature/unificacion-motor-riesgo en el historial de Git. | K55: 46292 | L55: =IF(K55="","",TODAY()-K55)
A56: P18-01 | B56: 18 | C56: Simulador | D56: Simulador de escenarios con el motor único de reposición (fases 1 a 4) | E56: Pendiente del plan | F56: Terminado | G56: Media | H56: calcularReposicion acepta diasCoberturaOverride, /api/ia/snapshot recibe ?dias=N, SimuladorPage.jsx usa cantidad_recomendada y la respuesta incluye categoria. | K56: 46292 | L56: =IF(K56="","",TODAY()-K56)
A57: P18-02 | B57: 18 | C57: Documentación | D57: Actualizar el encabezado del plan 18: todavía dice "Propuesto, pendiente de confirmación" | E57: Mantenimiento de docs | F57: No iniciado | G57: Baja | H57: docs/planes/18_unificacion_simulador_motor_reposicion.md, línea 3. | K57: 46292 | L57: =IF(K57="","",TODAY()-K57)
A58: P19-01 | B58: 19 | C58: Respaldos | D58: Respaldo diario con pg_dump (conserva 14) | E58: Pendiente del plan | F58: Parcial | G58: Alta | H58: utils/backup.js y cron de las 2:00 en schedulerService.js. | I58: Solo sirve en local: en Render gratuito el disco es temporal y el servidor se duerme. Desde el 3-oct no se programa en producción; lo reemplaza el workflow de GitHub Actions. | K58: 46292 | L58: =IF(K58="","",TODAY()-K58)
A59: P19-02 | B59: 19 | C59: Respaldos | D59: Copia de los respaldos en almacenamiento externo, verificar que pg_dump exista en Render y probar una restauración | E59: Pendiente del plan | F59: Terminado | G59: Alta | H59: .github/workflows/respaldo-neon.yml (diario, cifrado con gpg, 14 días de retención, postgres:18) y docs/restaurar_respaldo.md. | I59: Restauración verificada el 3-oct, según Luis. | K59: 46292 | L59: =IF(K59="","",TODAY()-K59)
A60: P19-03 | B60: 19 | C60: Legal | D60: Política de tratamiento de datos con aceptación obligatoria en el registro | E60: Pendiente del plan | F60: Por verificar | G60: Alta | H60: Implementada en código (PoliticaDatosPage.jsx, /politica-datos, fecha_aceptacion_politica_datos). Falta confirmar que esté desplegada en Render. | K60: 46292 | L60: =IF(K60="","",TODAY()-K60)
A61: P19-04 | B61: 19 | C61: Legal | D61: Re-consentimiento si cambia la política y formulario de autoservicio para ejercer los derechos del titular | E61: Pendiente del plan | F61: No iniciado | G61: Baja | H61: Plan 19, sección 3.2 ("fuera de esta ronda"). | K61: 46292 | L61: =IF(K61="","",TODAY()-K61)
A62: P19-05 | B62: 19 | C62: Métricas | D62: Métrica de activación de la prueba gratuita (≥ 20 productos y ventas durante 7 días) con endpoint interno | E62: Pendiente del plan | F62: No iniciado | G62: Media | H62: Plan 19, sección 3.3. Diseño SQL listo. | I62: Construir cuando se prepare la convocatoria pública. | K62: 46292 | L62: =IF(K62="","",TODAY()-K62)
A63: P19-06 | B63: 19 | C63: Modo básico | D63: Modo básico, fases A a C: preferencia de modo, menú reducido y pantalla "¿Qué pido?" con recepción | E63: Pendiente del plan | F63: En progreso | G63: Alta | H63: Plan 19, sección 3.4; rama feat/modo-basico-web (subida al remoto, commits ce91ec7, e2e238a, 6aa9be3). | I63: Fases A, B y C implementadas y verificadas (pruebas, mutaciones y navegador). Falta: mezclar a main (la migración de modo_interfaz corre sola al desplegar), probar en celular y con un Administrador con 2FA. | K63: 46301 | L63: =IF(K63="","",TODAY()-K63)
A64: P19-07 | B64: 19 | C64: Modo básico | D64: Modo básico, fases D y E: permisos del colaborador sobre órdenes y catálogo simplificado | E64: Pendiente del plan | F64: No iniciado | G64: Baja | H64: Plan 19, sección 3.4. | I64: Después de la visita; solo si el piloto muestra que hacen falta. La fase C no las necesita (/pedir va solo para el Administrador). | K64: 46301 | L64: =IF(K64="","",TODAY()-K64)
A65: P19-08 | B65: 19 | C65: Convocatoria | D65: Pregunta de experiencia digital en el registro, invitación a compartir y encuesta corta de satisfacción | E65: Pendiente del plan | F65: No iniciado | G65: Media | H65: Plan 19, sección 3.5. | I65: Depende de la convocatoria pública. | K65: 46292 | L65: =IF(K65="","",TODAY()-K65)
A66: P19-09 | B66: 19 | C66: POS | D66: Botón "Descargar recibo (PDF)" y vista de factura individual desde el historial | E66: Pendiente del plan | F66: No iniciado | G66: Media | H66: Plan 19, sección 3.6. Reutiliza pdfkit. | K66: 46292 | L66: =IF(K66="","",TODAY()-K66)
A67: P19-10 | B67: 19 | C67: Métricas | D67: El SQL de la métrica de activación usa Tienda.fecha_creacion, una columna que no existe | E67: Observación / defecto | F67: No iniciado | G67: Media | H67: Plan 19, sección 3.3, frente a database/init_pg.sql (Tienda no tiene ninguna fecha). | I67: Se corrige en el plan 22, fase I1 (columna nueva y relleno con la fecha de registro más antigua de sus usuarios). | K67: 46293 | L67: =IF(K67="","",TODAY()-K67)
A68: P20-01 | B68: 20 | C68: Base de datos | D68: La auto-migración de config/database.js corre en cada require contra cualquier DATABASE_URL, sin protección | E68: Observación / defecto | F68: No iniciado | G68: Alta | H68: Plan 20, sección 8.3. | I68: Incluido en el plan 21, R4. | K68: 46292 | L68: =IF(K68="","",TODAY()-K68)
A69: P20-02 | B69: 20 | C69: Caja | D69: La apertura de caja hace SELECT y después INSERT sin transacción (carrera posible, no reproducida) | E69: Observación / defecto | F69: No iniciado | G69: Media | H69: Plan 20, sección 8.8. | I69: Incluido en el plan 21, R2 (services/caja.js). | K69: 46292 | L69: =IF(K69="","",TODAY()-K69)
A70: P20-03 | B70: 20 | C70: Pruebas | D70: Pruebas para los bloques que siguen excluidos de la cobertura: evaluación de órdenes de la IA, dryRun/resolve/getStats de alertas y validateRegister/validateReport | E70: Pendiente del plan | F70: No iniciado | G70: Media | H70: Bloques /* v8 ignore */ en feedbackController.js, models/Alert.js y middleware/validation.js, cada uno con su justificación. | K70: 46292 | L70: =IF(K70="","",TODAY()-K70)
A71: P20-04 | B71: 20 | C71: Pruebas | D71: Subir los thresholds de cobertura a medida que se agreguen pruebas | E71: Pendiente del plan | F71: No iniciado | G71: Baja | H71: vitest.config.js (hoy 10/15/19/9). | I71: Tarea continua. | K71: 46292 | L71: =IF(K71="","",TODAY()-K71)
A72: P20-05 | B72: 20 | C72: Pruebas | D72: Prueba del límite de fuerza bruta del login (10 intentos fallidos en 15 minutos) | E72: Observación / defecto | F72: No iniciado | G72: Baja | H72: Plan 20, sección 8.6. | K72: 46292 | L72: =IF(K72="","",TODAY()-K72)
A73: P20-06 | B73: 20 | C73: Documentación | D73: Actualizar la sección 6 del plan 20: todavía dice que la rama no se ha subido ni mezclado a main | E73: Mantenimiento de docs | F73: No iniciado | G73: Baja | H73: docs/planes/20_cobertura_real_backend.md, sección 6. | K73: 46292 | L73: =IF(K73="","",TODAY()-K73)
A74: P21-01 | B74: 21 | C74: Refactorización | D74: R0: pruebas de caracterización de IA, proveedores, autenticación y productos | E74: Pendiente del plan | F74: Terminado | G74: Alta | H74: Mezclada en main y subida el 28-sep (merge 2e523dc): 48 pruebas de caracterización y 2 de guardia. Cobertura combinada ≈35 % → ≈56 % (npm run test:coverage:combinada). | K74: 46292 | L74: =IF(K74="","",TODAY()-K74)
A75: P21-02 | B75: 21 | C75: Refactorización | D75: R1: services/ia/ y cliente único de OpenAI (base del ia-service del Sprint 6.3) | E75: Pendiente del plan | F75: Terminado | G75: Alta | H75: Rama refactor/R1-servicios-ia (subida) y merge --no-ff a main local el 8-oct. aiController 901 → 152 líneas; cliente único de OpenAI; services/ia/ con 14 módulos. 365 unitarias + 431 de integración en verde; cobertura combinada 73,5 %. Plan 21, «R1 — Resultados». | I75: Aprobada por Luis el 8-oct. origin/main NO se actualizó: main local tiene 5 commits previos sin subir (incluye el 2FA en CRUD) y subirlo podría desplegar durante el congelamiento. Se despliega después del piloto. | J75: Agente (Claude Code) | K75: 46303 | L75: =IF(K75="","",TODAY()-K75)
A76: P21-03 | B76: 21 | C76: Refactorización | D76: R2: eventos de inventario y servicios de dominio (proveedores, auth, productos, caja) | E76: Pendiente del plan | F76: No iniciado | G76: Media | H76: Plan 21, sección 4. | I76: Antes de R2, caracterizar también las ramas de error de cada endpoint (lección de R1). suppliersController es hoy el controlador más grande (632 líneas) y conserva el prompt de generateSmartOrder. | K76: 46303 | L76: =IF(K76="","",TODAY()-K76)
A77: P21-04 | B77: 21 | C77: Refactorización | D77: R3: hooks y descomposición del frontend, empezando por DashboardPage | E77: Pendiente del plan | F77: No iniciado | G77: Media | H77: Plan 21, sección 4. | I77: Después del piloto. El modo básico (plan 19, fases A a C) no depende de R3.1. | K77: 46301 | L77: =IF(K77="","",TODAY()-K77)
A78: P21-05 | B78: 21 | C78: Refactorización | D78: R4: limpieza (migración explícita, estilo de controladores, console.* → logger) | E78: Pendiente del plan | F78: No iniciado | G78: Baja | H78: Plan 21, sección 4. | I78: Al 8-oct quedan 164 console.* en el backend (authController 24, schedulerService 15, saleController 12, productController 12, app.js 12…). R1 limpió aiController, services/ia, services/inventory y suppliersController. Incluir mover ai_audit.log de la raíz a logs/. | K78: 46303 | L78: =IF(K78="","",TODAY()-K78)
A79: P21-06 | B79: 21 | C79: Tiempo real | D79: Decidir el transporte de las alertas en tiempo real: SSE (recomendado) o Socket.io | E79: Decisión pendiente | F79: No iniciado | G79: Alta | H79: Plan 21, secciones 5.2 y 8. | I79: Replantear después del piloto: para la app nativa, notificaciones push; SSE para la web. | K79: 46292 | L79: =IF(K79="","",TODAY()-K79)
A80: P21-07 | B80: 21 | C80: Tiempo real | D80: T1 y T2: canal interno, endpoint /api/eventos y hook del frontend que reemplaza las consultas periódicas | E80: Pendiente del plan | F80: No iniciado | G80: Media | H80: Plan 21, sección 5.3. | I80: Después del piloto, replanteado (ver la fila de la decisión de transporte). | K80: 46292 | L80: =IF(K80="","",TODAY()-K80)
A81: P21-08 | B81: 21 | C81: Tiempo real | D81: T3: Redis pub/sub (o LISTEN/NOTIFY) y Nginx para varias réplicas | E81: Pendiente del plan | F81: No iniciado | G81: Media | H81: Plan 21, sección 5.3. | I81: Junto con el Sprint 6 de Bases de Datos Avanzadas. | K81: 46292 | L81: =IF(K81="","",TODAY()-K81)
A82: P21-09 | B82: 21 | C82: Seguridad | D82: /api/verify-reset-code no tiene limitador propio: el código de 6 dígitos solo queda cubierto por el límite global (600 cada 15 min) | E82: Observación / defecto | F82: Terminado | G82: Alta | H82: routes/authRoutes.js:25; app.js solo limita forgot-password y reset-password. Caracterizado en autenticacion_flujos.test.js (R0). | I82: Mezclado en main (commit c0a65c3, merge cb028d9). | K82: 46301 | L82: =IF(K82="","",TODAY()-K82)
A83: P21-10 | B83: 21 | C83: Proveedores | D83: Recepción de mercancía sin tope: completarRecepcion acepta más unidades de las pedidas, y recibir menos cierra la orden sin dejar el faltante pendiente | E83: Observación / defecto | F83: No iniciado | G83: Media | H83: controllers/suppliersController.js (completarRecepcion). Caracterizado en proveedores_flujo.test.js (R0). | I83: Decidir si se bloquea, se pide confirmación o se deja registro del faltante. | K83: 46292 | L83: =IF(K83="","",TODAY()-K83)
A84: P21-11 | B84: 21 | C84: Pruebas | D84: Los limitadores de peticiones comparten contador entre archivos de prueba: TRUNCATE … RESTART IDENTITY reutiliza user_1 y todas las peticiones sin sesión salen de la misma IP; con la suite creciendo puede aparecer un 429 intermitente | E84: Observación / defecto | F84: Terminado | G84: Baja | H84: Medido sin reinicio: global 242/600 sobre user_1, auth 7/10. tests/integration/helpers/limitadores.js reinicia los MemoryStore al comienzo de cada archivo (pico por archivo: 48/600 y 5/10); guardia limitadores_reinicio.test.js. | I84: Mezclado en main con R0 el 28-sep. | K84: 46292 | L84: =IF(K84="","",TODAY()-K84)
A85: P21-12 | B85: 21 | C85: Refactorización | D85: Código muerto: el chequeo !req.file de bulkUpload nunca se alcanza por esa ruta (validateFileType responde antes) | E85: Observación / defecto | F85: No iniciado | G85: Baja | H85: Caracterizado en productos_carga_masiva.test.js (R0). | I85: Entra en R4. | K85: 46292 | L85: =IF(K85="","",TODAY()-K85)
A86: P21-13 | B86: 21 | C86: Seguridad | D86: El skip de globalLimiter es código muerto: al montarse en /api/, req.path llega sin ese prefijo, así que login, registro y 2fa/verify sí gastan el presupuesto global | E86: Observación / defecto | F86: Terminado | G86: Baja | H86: middleware/rateLimiter.js (skip con req.path.startsWith('/api/login')…); comprobado con una prueba temporal del agente. | I86: Mezclado en main (commit c0a65c3, merge cb028d9). | K86: 46301 | L86: =IF(K86="","",TODAY()-K86)
A87: P21-14 | B87: 21 | C87: Caja | D87: Apertura de caja con transacción y bloqueo (punto 2.4), adelantada de R2 para antes del piloto | E87: Pendiente del plan | F87: Terminado | G87: Media | H87: Plan 21, punto 2.4 y sección 6; plan 22, sección 5 (A.3). | I87: Mezclado en main (commit 75a1861, merge cb028d9). | K87: 46301 | L87: =IF(K87="","",TODAY()-K87)
... A100: P22-11 | B100: 22 | C100: Seguridad | D100: POST /api/admin/seed vaciaba todas las tablas de todas las tiendas y creaba admin/admin123; cualquier persona registrada podía llamarla | E100: Observación / defecto | F100: Terminado | G100: Alta | H100: Corregido el 28-sep (fix/seed-produccion): ruta eliminada; la semilla solo corre como comando con guardia de base local. | I100: Plan 22, sección 1.4. | K100: 46293 | L100: =IF(K100="","",TODAY()-K100)
A101: P22-12 | B101: 22 | C101: Seguridad | D101: C1: reportes editables y borrables entre tiendas (Report.update/delete filtraban solo por id) | E101: Observación / defecto | F101: Terminado | G101: Alta | H101: Corregido el 28-sep (fix/aislamiento-reportes-feedback). | K101: 46293 | L101: =IF(K101="","",TODAY()-K101)
A102: P22-13 | B102: 22 | C102: Seguridad | D102: C2: evaluación de IA de órdenes de otra tienda, con fuga de nombres y ventas de productos | E102: Observación / defecto | F102: Terminado | G102: Alta | H102: Corregido el 28-sep (fix/aislamiento-reportes-feedback); evaluateOrder caracterizado antes del cambio. | K102: 46293 | L102: =IF(K102="","",TODAY()-K102)
A103: P22-14 | B103: 22 | C103: Seguridad | D103: C3: POST /api/alertas/test-summary enviaba correos sin requireAdmin | E103: Observación / defecto | F103: Terminado | G103: Media | H103: Corregido el 28-sep. | K103: 46293 | L103: =IF(K103="","",TODAY()-K103)
A104: P22-15 | B104: 22 | C104: Seguridad | D104: C4: un token CSRF inválido responde 500 en vez de 403 (el manejador global ignora err.status) | E104: Observación / defecto | F104: No iniciado | G104: Baja | H104: app.js, manejador global de errores. | I104: Revisar antes cómo reacciona la interfaz. | K104: 46293 | L104: =IF(K104="","",TODAY()-K104)
A105: P22-16 | B105: 22 | C105: Seguridad | D105: C5: clienteRoutes aplica requireLogin a todo /api (rutas inexistentes responden 401 en vez de 404) | E105: Observación / defecto | F105: No iniciado | G105: Baja | H105: routes/clienteRoutes.js. | I105: Entra en R4. | K105: 46293 | L105: =IF(K105="","",TODAY()-K105)
A106: P22-17 | B106: 22 | C106: Seguridad | D106: C6: la carpeta exports/ era compartida; cualquier usuario listaba y descargaba exportaciones de otras tiendas | E106: Observación / defecto | F106: Terminado | G106: Alta | H106: Corregido el 3-oct (fix/exports-por-tienda): tienda en el nombre, verificación al descargar, borrado tras descarga, sin listado. | K106: 46293 | L106: =IF(K106="","",TODAY()-K106)
A107: P22-18 | B107: 22 | C107: Seguridad | D107: C7: PUT /api/productos/agregar/:id sumaba o restaba stock sin movimiento en el Kardex | E107: Observación / defecto | F107: Terminado | G107: Alta | H107: Ruta eliminada el 3-oct (fix/i0-matriz-roles). | K107: 46293 | L107: =IF(K107="","",TODAY()-K107)
A108: P22-19 | B108: 22 | C108: Métricas | D108: Excluir las tiendas de prueba del equipo de las métricas del piloto (propuesta: Tienda.es_prueba) | E108: Pendiente del plan | F108: No iniciado | G108: Alta | H108: Plan 22, sección 3.3. | I108: Antes del arranque del piloto, junto con I2. | K108: 46293 | L108: =IF(K108="","",TODAY()-K108)
A109: P23-01 | B109: 23 | C109: Evaluador | D109: El evaluador de Feedback_IA compara un número equivocado: sugerencia_ia guarda el % de ajuste de la IA y feedbackController.js:99 lo usa como cantidad. Corregirlo y decidir qué cantidad(es) se evalúan (propuesta: motor, IA ajustada y lo que pidió el dueño) | E109: Observación / defecto | F109: No iniciado | G109: Alta | H109: Plan 23, secciones 1 y 3.A. controllers/feedbackController.js:99; ordenBorradorController.js:102. | I109: Antes del arranque del piloto. Decisión 1 de Luis. Probablemente requiere migración (columnas nuevas en Feedback_IA). Cambia el factor que usan alertas y Proveedores. | J109: Luis | K109: 46301 | L109: =IF(K109="","",TODAY()-K109)
A110: P23-02 | B110: 23 | C110: Medición | D110: Reporte comparativo: error del motor, de la IA y del dueño frente a las ventas reales, por tienda y producto | E110: Pendiente del plan | F110: No iniciado | G110: Media | H110: Plan 23, sección 3.A3. | I110: En rama durante el piloto. Depende de P23-01. Sirve también para el documento académico. | K110: 46301 | L110: =IF(K110="","",TODAY()-K110)
A111: P23-03 | B111: 23 | C111: Motor adaptativo | D111: Estadística sin IA: tiempo real de entrega por proveedor, variabilidad de la demanda, efecto del día de la semana o la quincena | E111: Pendiente del plan | F111: No iniciado | G111: Media | H111: Plan 23, sección 3.A4. | I111: Opcional. En rama durante el piloto. Es lo más honesto para decir que el motor «se adapta». | K111: 46301 | L111: =IF(K111="","",TODAY()-K111)
A112: P23-04 | B112: 23 | C112: IA | D112: Darle contexto real al ajuste de la IA (calendario, quincena, festivos, vencimientos) y registrar el contexto en Auditoria_IA | E112: Pendiente del plan | F112: No iniciado | G112: Media | H112: Plan 23, sección 3.B. | I112: Depende de P23-01 y P23-02: sin medición no se sabe si mejora algo. | K112: 46301 | L112: =IF(K112="","",TODAY()-K112)
A113: P23-05 | B113: 23 | C113: IA | D113: Leer fotos de facturas del proveedor para dar entrada a mercancía o alta de catálogo, mandando a la IA solo las líneas y sin guardar la imagen | E113: Pendiente del plan | F113: No iniciado | G113: Media | H113: Plan 23, sección 3.C. | I113: Es el frente más grande. Depende de P23-06 y P23-07 (privacidad). Nunca fotos del cuaderno de fiados. | K113: 46301 | L113: =IF(K113="","",TODAY()-K113)
...

Sheet Bitácora
A1: Bitácora de cambios
A2: Una fila por cada cambio de estado. Así queda el rastro de quién movió qué y por qué.
A4: Fecha | B4: ID | C4: Estado anterior | D4: Estado nuevo | E4: Quién | F4: Comentario / evidencia (commit, PR, captura)
A5: 46292 | B5: — | C5: — | D5: — | E5: Agente (Claude Code) | F5: Creación del seguimiento: revisión de los planes 01 a 21 contra el código de main.
A6: 46293 | B6: P02-01, P19, P22 | C6: — | D6: No iniciado | E6: Agente (Claude Code) | F6: Plan 22 (panel interno y funciones por tienda): se agregan sus fases, dos decisiones de métricas, el hallazgo de seguridad de las rutas de tienda y el error de la columna fecha_creacion en la métrica de activación.
A7: 46293 | B7: P22-06, P22-07 | C7: No iniciado | D7: Terminado | E7: Luis | F7: Decisiones de métricas: activación = al menos 20 productos y ventas en 5 de los primeros 7 días; los días de apertura se preguntan en el registro.
A8: 46293 | B8: P21-01, P22-01, P21-09 a P21-13, P22-09, P22-10 | C8: No iniciado | D8: Por verificar | E8: Agente (Claude Code) | F8: R0 del plan 21 terminado en la rama test/plan21-r0-caracterizacion (48 pruebas, sin cambios de producción, sin merge). I0 pasa a En progreso y se amplía a auditoría de autorización. Se agregan los hallazgos de R0: egresos entre tiendas, verify-reset-code sin limitador, recepción sin tope, contadores compartidos en las pruebas (resuelto en la rama), código muerto en bulkUpload y skip inerte de globalLimiter.
A9: 46293 | B9: P21-01, P21-11, P22-09, P22-10 y hallazgos de I0 | C9: Por verificar / No iniciado | D9: Terminado | E9: Agente (Claude Code) | F9: Mezclados y subidos el 28-sep: R0, P22-09 con regla de estados, rutas de tienda, eliminación de la semilla en producción y C1 a C3. Matriz de roles decidida (D1 a D4 = solo Administrador).
A10: 46298 | B10: P22-01, C6, C7, P19 (respaldos) | C10: En progreso / No iniciado | D10: Terminado | E10: Agente (Claude Code) | F10: Mezclados y subidos el 3-oct: C6, I0 completo (incluye C7) y respaldo externo en GitHub Actions (postgres:18). Restauración verificada, según Luis.
A11: 46298 | B11: P07, P19 (modo básico), P21-R1/R3/T, P22-I3 | C11: — | D11: — | E11: Luis | F11: La app nativa del Tendero se adelanta para la visita a las tiendas piloto (semana del 5-oct). Repositorio aparte, Android primero. Nuevo orden en el plan 22, sección 5.
A12: 46301 | B12: P07-01, P07-02, P07-03, P19-06, P19-07, P21-04, P21-09, P21-13, P21-14, P22-04, P22-05 | C12: — | D12: — | E12: Luis | F12: Cambio de rumbo (6-oct): el piloto y la visita van con la web en modo básico (plan 19, 3.4, fases A, B y C; /pedir solo Administrador); la app nativa sigue en paralelo y se presenta en la sustentación (nov.). Panel (I1, I2, I4) antes del piloto, con encuesta de satisfacción. Revierte la decisión del 3-oct. Además, P07-02, P21-09, P21-13 y P21-14 pasan a Terminado: ya están en main (merge cb028d9, verificado con git log).
A13: 46301 | B13: P19-06, P11-02, P23-01 a P23-09 | C13: — | D13: — | E13: Luis | F13: Decisiones del 6-oct: la IA va disponible pero opcional (oculta en el modo básico); se invertirá en corregir el evaluador y medir, contexto real al ajuste y lectura de facturas (plan 23); privacidad primero. Modo básico A, B y C implementado en la rama feat/modo-basico-web (subida). Arreglo de privacidad de Cartera (afddd1d) terminado. Rama del backend y 4 ramas de la app subidas; main sin tocar.
A14: 46301 | B14: P23-08 | C14: No iniciado | D14: En progreso | E14: Agente (Claude Code) | F14: Borrador de las secciones corregidas sobre el alcance de la IA, con el formato del documento «Secciones corregidas v2»: Documentacion/StockPilot_Secciones_corregidas_sobre_la_IA.docx (21 recuadros de instrucción, 4 tablas). Pendiente de que Luis lo aplique.
A15: 46301 | B15: P23-08 | C15: En progreso | D15: En progreso | E15: Agente (Claude Code) | F15: Se consolidó todo en Documentacion/Revision_Documento_Practica_5_v2.docx (24 páginas en Word, 10 tablas): revisión del 26-sep actualizada al 6-oct (pruebas 287 + 407, 28,2 KLOC, escáner, rol «Colaborador»), reglas de alertas, textos de la IA, novedades y correcciones a Plan de Negocio, Intervención y Herramientas. Se retira el borrador anterior «Secciones corregidas sobre la IA».
A16: 46303 | B16: P21-02, P21-17 a P21-22 | C16: No iniciado / — | D16: Por verificar / No iniciado | E16: Agente (Claude Code) | F16: R1 del plan 21 hecha en la rama refactor/R1-servicios-ia (6 commits, sin mezclar a main): aiController 901 → 152 líneas, cliente único de OpenAI, services/ia con 14 módulos. 365 unitarias + 431 de integración en verde (796 en el reporte); cobertura combinada 73,5 %. Hallazgos nuevos P21-17 a P21-22: reporte de pruebas en carpeta inexistente (corregido en la rama), ruta vieja en CLAUDE.md, umbrales de cobertura por subir (decisión de Luis), zonas con poca cobertura.
A17: 46303 | B17: P21-02, P21-17, P21-18, P21-20 | C17: Por verificar / No iniciado | D17: Terminado | E17: Luis | F17: Luis aprueba R1 y manda mezclarla (8-oct): merge --no-ff a main local; la rama refactor/R1-servicios-ia se sube como evidencia. Aprueba también subir los umbrales de cobertura (17/23/32/15) y corregir la ruta vieja del CLAUDE.md. origin/main no se actualiza todavía: main local lleva 5 commits previos sin subir (incluido el 2FA en CRUD, ec4d48c) y no se sabe si subir main despliega durante el congelamiento. Regla de Luis: cada plan nuevo debe quedar subido, es la evidencia del desarrollo.

Sheet Leyenda
A1: Cómo usar este archivo
A3: Estado | B3: No iniciado | C3: Nadie ha empezado.
B4: En progreso | C4: Alguien está trabajando en esto ahora (anote el responsable).
B5: Parcial | C5: Existe una parte; la fila explica qué falta.
B6: Terminado | C6: Hecho y verificado. Anote la evidencia en la Bitácora.
B7: Bloqueado | C7: No se puede avanzar hasta que se resuelva otra cosa (anótela en Notas).
B8: Descartado | C8: Se decidió no hacerlo; la fila dice por qué.
B9: Por verificar | C9: Puede estar hecho, pero hay que comprobarlo (por ejemplo, en producción).
A10: Tipo | B10: Pendiente del plan | C10: Algo que el plan proponía hacer.
B11: Observación / defecto | C11: Un problema que el plan encontró de pasada, sin corregir.
B12: Trabajo futuro | C12: Idea para después del lanzamiento o de la entrega académica.
B13: Decisión pendiente | C13: Hace falta que el equipo decida antes de implementar.
B14: Mantenimiento de docs | C14: El documento del plan quedó desactualizado frente al código.
A15: ID | B15: P19-03 | C15: Plan 19, tercer pendiente. Las filas nuevas pueden seguir la misma regla.
A16: Días sin actualizar | B16: Fórmula | C16: Días desde la última actualización; sirve para ver lo que quedó olvidado.
