Workbook

Sheet Instrucciones
A1: StockPilot — Modelo financiero a 5 años
A2: Práctica de Ingeniería V · Formato de las preguntas 21 a 26 de la guía del Fondo Emprender
A4: Cómo usar el modelo
A5: 1. Todos los supuestos están en la hoja "Supuestos". Solo se editan las celdas en azul; las de fondo amarillo son los supuestos clave.
A6: 2. Las hojas "Pesimista", "Base" y "Optimista" calculan mes a mes (60 meses) y resumen por año. No se editan: todo son fórmulas.
A7: 3. La hoja "Resumen" muestra el escenario elegido en Supuestos!C5 (1 = Pesimista, 2 = Base, 3 = Optimista) con la estructura del Fondo Emprender.
A8: 4. La hoja "Comparación" pone los tres escenarios lado a lado.
A9: 5. Supuestos!C8 define cómo crece el equipo: 1 = según la carga de trabajo (recomendado); 2 = calendario de contratación del plan de negocio original.
A11: Convenciones de color
A12: Azul: dato de entrada editable · Negro: fórmula · Verde: vínculo a otra hoja · Fondo amarillo: supuesto clave.
A14: Cómo se calcula la nómina
A15: Costo mensual de un empleado = salario × (1 + aportes del empleador + prestaciones) + auxilio de transporte × (1 + prestaciones que lo incluyen), si el salario es ≤ 2 SMMLV.
... A30: Trabajo desde casa y equipos (v2): mientras los fundadores no cobran, el proyecto les reembolsa la energía y la parte del internet del hogar que usan para trabajar; además reserva cada mes el costo de reponer sus portátiles (vida útil de 5 años) y compra un portátil por cada colaborador nuevo. Desde el mes con salario, el auxilio de conectividad (mismo valor que el de transporte ya incluido en la nómina) cubre la energía y el internet. Supuestos en Supuestos!A82:F89.

Sheet Supuestos
A1: Supuestos del modelo
A2: Editar solo las celdas en azul. Cada supuesto tiene su fuente o justificación en la columna F.
A4: Controles
A5: Escenario que muestra la hoja Resumen | C5: 2 | F5: 1 = Pesimista, 2 = Base, 3 = Optimista
A8: Modo de crecimiento del equipo | C8: 1 | F8: 1 = según carga de trabajo (recomendado); 2 = calendario del plan de negocio original
A10: Supuestos por escenario | C10: Pesimista | D10: Base | E10: Optimista
A11: Clientes activos al cierre del año 1 | C11: 60 | D11: 120 | E11: 150 | F11: Base: meta del Plan de Negocio
A12: Clientes activos al cierre del año 2 | C12: 150 | D12: 300 | E12: 400 | F12: Base: SOM año 2 del Plan de Negocio
A13: Clientes activos al cierre del año 3 | C13: 300 | D13: 600 | E13: 800 | F13: Base: SOM año 3 del Plan de Negocio
A14: Clientes activos al cierre del año 4 | C14: 450 | D14: 900 | E14: 1200 | F14: Supuesto: inicio de expansión a otras ciudades
A15: Clientes activos al cierre del año 5 | C15: 600 | D15: 1200 | E15: 1600 | F15: Supuesto: ≈ 2,7 % de las tiendas de Bogotá en el escenario base
A16: Abandono mensual de clientes (churn) | C16: 0.05 | D16: 0.03 | E16: 0.02 | F16: El plan usa 5 % mensual y 90 % anual en secciones distintas; 3 % es un punto intermedio
A17: Marketing por cliente nuevo (CAC sin salarios) | C17: 100000 | D17: 65000 | E17: 50000 | F17: Base calibrada para que el año 1 cueste ≈ $9M, como en el Plan de Negocio (tabla 17.3)
A18: Mes en que los fundadores empiezan a recibir salario | C18: 37 | D18: 25 | E18: 25 | F18: Mes 25 = inicio del año 3
A20: Rampa de clientes del año 1 (fracción de la meta del año 1 al cierre de cada mes)
A21: Mes | C21: 1 | D21: 2 | E21: 3 | F21: 4 | G21: 5 | H21: 6 | I21: 7 | J21: 8 | K21: 9 | L21: 10 | M21: 11 | N21: 12
A22: Fracción de la meta del año 1 | C22: 0.0833 | D22: 0.125 | E22: 0.2083 | F22: 0.2917 | G22: 0.375 | H22: 0.4583 | I22: 0.5417 | J22: 0.6667 | K22: 0.75 | L22: 0.8333 | M22: 0.9167 | N22: 1
A23: Fuente: tabla 8.2 del Plan de Negocio (10 clientes en el mes 1 hasta 120 en el mes 12).
A25: Ingresos
A26: Precio mensual por tienda (año 1, sin IVA) | B26: COP/mes | C26: 39900 | F26: Plan de Negocio; igual al plan Esencial de Treinta
A27: Ajuste anual del precio | B27: % | C27: 0.05 | F27: Supuesto: ajuste cercano a la inflación
A28: Costos variables
A29: Costo de IA (OpenAI) por cliente activo | B29: COP/mes | C29: 1250 | F29: Plan de Negocio: $150.000/mes para 120 clientes
A30: Comisión de pasarela de pagos | B30: % ingreso | C30: 0.03 | F30: Supuesto (Wompi/PayU); no estaba en el plan
A31: Infraestructura en la nube hasta el umbral 1 | B31: COP/mes | C31: 220000 | F31: Plan de Negocio: Render + Neon
A32: Umbral 1 de clientes | B32: clientes | C32: 300 | F32: Supuesto
A33: Infraestructura en la nube hasta el umbral 2 | B33: COP/mes | C33: 450000 | F33: Supuesto: plan superior de base de datos y servidor
A34: Umbral 2 de clientes | B34: clientes | C34: 700 | F34: Supuesto
A35: Infraestructura en la nube por encima del umbral 2 | B35: COP/mes | C35: 800000 | F35: Supuesto
A36: Nómina
A37: SMMLV 2026 | B37: COP/mes | C37: 1750905 | F37: Infobae, 14-abr-2026 (decreto en litigio; actualizar si cambia)
A38: Auxilio de transporte 2026 | B38: COP/mes | C38: 249095 | F38: Infobae, 14-abr-2026. Aplica a salarios ≤ 2 SMMLV
A39: Ajuste anual de salarios, SMMLV y gastos | B39: % | C39: 0.05 | F39: Supuesto: ajuste cercano a la inflación
A40: Aporte a pensión (empleador) | B40: % salario | C40: 0.12 | F40: Ley 100 de 1993
A41: ARL riesgo I | B41: % salario | C41: 0.00522 | F41: Decreto 1772 de 1994
A42: Caja de compensación | B42: % salario | C42: 0.04 | F42: Ley 21 de 1982
A43: Salud, SENA e ICBF (empleador) | B43: % salario | C43: 0 | F43: Exoneración art. 114-1 ET para SAS con salarios < 10 SMMLV; verificar con contador
A44: Cesantías | B44: % salario | C44: 0.0833 | F44: Código Sustantivo del Trabajo
A45: Intereses sobre cesantías | B45: % salario | C45: 0.01 | F45: 12 % anual sobre las cesantías
A46: Prima de servicios | B46: % salario | C46: 0.0833 | F46: Código Sustantivo del Trabajo
A47: Vacaciones | B47: % salario | C47: 0.0417 | F47: 15 días hábiles al año
A48: Factor prestacional total sobre el salario | B48: % salario | C48: =$C$40+$C$41+$C$42+$C$43+$C$44+$C$45+$C$46+$C$47 -> 0.38352 | F48: Fórmula: suma de los ocho conceptos anteriores
A49: Factor sobre el auxilio de transporte | B49: % auxilio | C49: =$C$44+$C$45+$C$46 -> 0.1766 | F49: Cesantías, intereses y prima incluyen el auxilio
A50: Salario de un colaborador (soporte, ventas o desarrollo) | B50: COP/mes | C50: 2000000 | F50: Plan de Negocio: comercial $2.000.000 y desarrollador $1.800.000
A51: Número de fundadores | B51: personas | C51: 3 | F51: Equipo fundador
A52: Salario de cada fundador cuando empieza a cobrar | B52: COP/mes | C52: 3000000 | F52: Supuesto: salario de ingeniero junior en Bogotá
A53: Capacidad de trabajo
A54: Horas al mes de cada fundador, año 1 | B54: horas | C54: 80 | F54: Supuesto: medio tiempo mientras terminan la carrera
A55: Horas al mes de cada fundador, año 2 | B55: horas | C55: 120 | F55: Supuesto
A56: Horas al mes de cada fundador, años 3 a 5 | B56: horas | C56: 160 | F56: Supuesto: tiempo completo
A57: Horas productivas al mes de un colaborador | B57: horas | C57: 160 | F57: Jornada completa descontando reuniones y ausencias
A58: Minutos de soporte por cliente activo al mes | B58: minutos | C58: 20 | F58: Supuesto: consultas por WhatsApp y ajustes
A59: Horas de incorporación por cliente nuevo | B59: horas | C59: 1.7 | F59: Plan de Negocio, sección 13 (activación ≈ 1,7 h)
A60: Horas de venta por cliente nuevo | B60: horas | C60: 4 | F60: Supuesto: demostraciones y visitas con tasa de cierre de 25 %
A61: Horas de desarrollo y mantenimiento base al mes | B61: horas | C61: 80 | F61: Supuesto: correcciones, seguridad, respaldos y mejoras
A62: Horas de desarrollo adicionales por cada 100 clientes | B62: horas | C62: 5 | F62: Supuesto
A63: Gastos fijos
A64: Arriendo de coworking | B64: COP/mes | C64: 500000 | F64: Plan de Negocio (tabla 17.3)
A65: Mes en que empieza el coworking | B65: mes | C65: 25 | F65: Supuesto: trabajo remoto los dos primeros años
A66: Gastos administrativos y legales, año 1 | B66: COP/mes | C66: 200000 | F66: Plan de Negocio (tabla 17.3)
A67: Gastos administrativos y legales desde el año 2 | B67: COP/mes | C67: 400000 | F67: Supuesto: contador externo
A68: Software y herramientas | B68: COP/mes | C68: 100000 | F68: Plan de Negocio (tabla 17.3)
A69: Dominio y SSL | B69: COP/mes | C69: 10000 | F69: Plan de Negocio (tabla 17.2)
A70: Inversión, impuestos y evaluación
A71: Gastos preoperativos (constitución SAS, registros, dominio) | B71: COP | C71: 500000 | F71: Plan de Negocio (tabla 17.5)
A72: Marketing inicial (landing page y material) | B72: COP | C72: 1000000 | F72: Plan de Negocio (tabla 17.5)
A73: Equipos de cómputo (aporte en especie de los fundadores) | B73: COP | C73: 0 | F73: Plan de Negocio: equipos preexistentes
A74: Tarifa de impuesto de renta | B74: % | C74: 0.35 | F74: Tarifa general de personas jurídicas
A75: Tasa de descuento (TIO) para el VPN | B75: % | C75: 0.2 | F75: Supuesto: rentabilidad mínima exigida por los socios
A77: Fuentes de financiación (se comparan con la necesidad de caja del escenario elegido en la hoja Resumen)
A78: Recursos propios (fundadores) | C78: 4000000 | F78: Plan de Negocio, resumen ejecutivo
A79: Fondo Emprender (capital semilla, sujeto a aprobación) | C79: 6000000 | F79: Plan de Negocio, resumen ejecutivo
A80: Otras fuentes (familiares, inversionista ángel) | C80: 5850000 | F80: Plan de Negocio, resumen ejecutivo
A82: Trabajo desde casa y equipos
A83: Tarifa de energía residencial | B83: COP/kWh | C83: 863.61 | F83: Enel Colombia, tarifa plena de agosto de 2026 (estrato 4). El estrato 3 paga esa misma tarifa por encima del consumo de subsistencia (130 kWh/mes), así que el consumo adicional del puesto de trabajo cuesta lo mismo en ambos estratos
A84: Consumo eléctrico del puesto de trabajo | B84: W | C84: 75 | F84: Supuesto: portátil ≈ 45 W en uso de desarrollo + monitor ≈ 20 W + iluminación LED ≈ 10 W
A85: Plan de internet hogar | B85: COP/mes | C85: 60000 | F85: Referencia: planes de 200 a 500 Mb en Bogotá entre $46.990 y $79.900 con IVA (comparadorinternet.co, jul-2026). Los planes de 100 Mb casi ya no se ofrecen
A86: Horas de uso del internet en el hogar | B86: horas/mes | C86: 480 | F86: Supuesto: 16 horas al día. La parte que asume el proyecto es horas de trabajo ÷ 480
A87: Precio de un portátil con los requisitos mínimos | B87: COP | C87: 2500000 | F87: Referencia: Lenovo IdeaPad Slim 3 (Ryzen 5 7520U, 16 GB, 512 GB SSD) a $2.299.900 en Homecenter, sept-2026. Requisitos en el Plan de Negocio, sección 12
A88: Vida útil de un portátil | B88: meses | C88: 60 | F88: Tasa máxima de depreciación de equipos de cómputo: 20 % anual (Decreto 1625 de 2016, art. 1.2.1.18.4)
A89: Desde el mes en que los fundadores cobran salario, el auxilio de transporte que ya incluye la nómina se paga como auxilio de conectividad digital (mismo valor; Ley 2088 de 2021 y Ley 2121 de 2021) y cubre estos gastos, por eso se reembolsan solo mientras trabajan sin salario.

Sheet Resumen
A1: Proyección financiera a 5 años — escenario seleccionado
A2: ="Escenario: "&CHOOSE(Supuestos!$C$5,"Pesimista","Base","Optimista")&" · Modo de equipo: "&IF(Supuestos!$C$8=1,"según carga de trabajo","calendario del plan original") -> Escenario: Base · Modo de equipo: según carga de trabajo
A3: Millones de COP salvo indicación. Cambie el escenario en Supuestos!C5.
A5: 21. Proyección de ingresos
A6: Concepto | B6: Año 0 | C6: Año 1 | D6: Año 2 | E6: Año 3 | F6: Año 4 | G6: Año 5
A7: Clientes activos al cierre | C7: =CHOOSE(Supuestos!$C$5,Pesimista!C53,Base!C53,Optimista!C53) -> 120 | D7: =CHOOSE(Supuestos!$C$5,Pesimista!D53,Base!D53,Optimista!D53) -> 300 | E7: =CHOOSE(Supuestos!$C$5,Pesimista!E53,Base!E53,Optimista!E53) -> 600 | F7: =CHOOSE(Supuestos!$C$5,Pesimista!F53,Base!F53,Optimista!F53) -> 900 | G7: =CHOOSE(Supuestos!$C$5,Pesimista!G53,Base!G53,Optimista!G53) -> 1200
A8: Clientes nuevos | C8: =CHOOSE(Supuestos!$C$5,Pesimista!C54,Base!C54,Optimista!C54) -> 138.9 | D8: =CHOOSE(Supuestos!$C$5,Pesimista!D54,Base!D54,Optimista!D54) -> 252.9 | E8: =CHOOSE(Supuestos!$C$5,Pesimista!E54,Base!E54,Optimista!E54) -> 457.5 | F8: =CHOOSE(Supuestos!$C$5,Pesimista!F54,Base!F54,Optimista!F54) -> 565.5 | G8: =CHOOSE(Supuestos!$C$5,Pesimista!G54,Base!G54,Optimista!G54) -> 673.5
A9: Clientes retirados | C9: =CHOOSE(Supuestos!$C$5,Pesimista!C55,Base!C55,Optimista!C55) -> 18.9 | D9: =CHOOSE(Supuestos!$C$5,Pesimista!D55,Base!D55,Optimista!D55) -> 72.9 | E9: =CHOOSE(Supuestos!$C$5,Pesimista!E55,Base!E55,Optimista!E55) -> 157.5 | F9: =CHOOSE(Supuestos!$C$5,Pesimista!F55,Base!F55,Optimista!F55) -> 265.5 | G9: =CHOOSE(Supuestos!$C$5,Pesimista!G55,Base!G55,Optimista!G55) -> 373.5
A10: Precio mensual (COP) | C10: =CHOOSE(Supuestos!$C$5,Pesimista!C56,Base!C56,Optimista!C56) -> 39900 | D10: =CHOOSE(Supuestos!$C$5,Pesimista!D56,Base!D56,Optimista!D56) -> 41895 | E10: =CHOOSE(Supuestos!$C$5,Pesimista!E56,Base!E56,Optimista!E56) -> 43989.75 | F10: =CHOOSE(Supuestos!$C$5,Pesimista!F56,Base!F56,Optimista!F56) -> 46189.238 | G10: =CHOOSE(Supuestos!$C$5,Pesimista!G56,Base!G56,Optimista!G56) -> 48498.699
A11: Ingresos | C11: =CHOOSE(Supuestos!$C$5,Pesimista!C57,Base!C57,Optimista!C57) -> 29.925 | D11: =CHOOSE(Supuestos!$C$5,Pesimista!D57,Base!D57,Optimista!D57) -> 109.34595 | E11: =CHOOSE(Supuestos!$C$5,Pesimista!E57,Base!E57,Optimista!E57) -> 244.14311 | F11: =CHOOSE(Supuestos!$C$5,Pesimista!F57,Base!F57,Optimista!F57) -> 422.63152 | G11: =CHOOSE(Supuestos!$C$5,Pesimista!G57,Base!G57,Optimista!G57) -> 618.35842
A13: 22. Proyección de costos
A14: Concepto | B14: Año 0 | C14: Año 1 | D14: Año 2 | E14: Año 3 | F14: Año 4 | G14: Año 5
A15: Costos de operación del servicio (IA, pasarela, nube) | C15: =CHOOSE(Supuestos!$C$5,Pesimista!C58,Base!C58,Optimista!C58) -> 4.47525 | D15: =CHOOSE(Supuestos!$C$5,Pesimista!D58,Base!D58,Optimista!D58) -> 9.3460035 | E15: =CHOOSE(Supuestos!$C$5,Pesimista!E58,Base!E58,Optimista!E58) -> 20.372887 | F15: =CHOOSE(Supuestos!$C$5,Pesimista!F58,Base!F58,Optimista!F58) -> 34.119282 | G15: =CHOOSE(Supuestos!$C$5,Pesimista!G58,Base!G58,Optimista!G58) -> 47.522883
A16: Margen bruto | C16: =CHOOSE(Supuestos!$C$5,Pesimista!C59,Base!C59,Optimista!C59) -> 25.44975 | D16: =CHOOSE(Supuestos!$C$5,Pesimista!D59,Base!D59,Optimista!D59) -> 99.999946 | E16: =CHOOSE(Supuestos!$C$5,Pesimista!E59,Base!E59,Optimista!E59) -> 223.77023 | F16: =CHOOSE(Supuestos!$C$5,Pesimista!F59,Base!F59,Optimista!F59) -> 388.51224 | G16: =CHOOSE(Supuestos!$C$5,Pesimista!G59,Base!G59,Optimista!G59) -> 570.83553
A17: Margen bruto (%) | C17: =CHOOSE(Supuestos!$C$5,Pesimista!C60,Base!C60,Optimista!C60) -> 0.85045113 | D17: =CHOOSE(Supuestos!$C$5,Pesimista!D60,Base!D60,Optimista!D60) -> 0.91452812 | E17: =CHOOSE(Supuestos!$C$5,Pesimista!E60,Base!E60,Optimista!E60) -> 0.9165535 | F17: =CHOOSE(Supuestos!$C$5,Pesimista!F60,Base!F60,Optimista!F60) -> 0.91926944 | G17: =CHOOSE(Supuestos!$C$5,Pesimista!G60,Base!G60,Optimista!G60) -> 0.9231467
A19: 23. Proyección de gastos
A20: Concepto | B20: Año 0 | C20: Año 1 | D20: Año 2 | E20: Año 3 | F20: Año 4 | G20: Año 5
A21: Nómina de colaboradores | C21: =CHOOSE(Supuestos!$C$5,Pesimista!C61,Base!C61,Optimista!C61) -> 0 | D21: =CHOOSE(Supuestos!$C$5,Pesimista!D61,Base!D61,Optimista!D61) -> 0 | E21: =CHOOSE(Supuestos!$C$5,Pesimista!E61,Base!E61,Optimista!E61) -> 20.242728 | F21: =CHOOSE(Supuestos!$C$5,Pesimista!F61,Base!F61,Optimista!F61) -> 63.764593 | G21: =CHOOSE(Supuestos!$C$5,Pesimista!G61,Base!G61,Optimista!G61) -> 115.30764
A22: Nómina de fundadores | C22: =CHOOSE(Supuestos!$C$5,Pesimista!C62,Base!C62,Optimista!C62) -> 0 | D22: =CHOOSE(Supuestos!$C$5,Pesimista!D62,Base!D62,Optimista!D62) -> 0 | E22: =CHOOSE(Supuestos!$C$5,Pesimista!E62,Base!E62,Optimista!E62) -> 176.36828 | F22: =CHOOSE(Supuestos!$C$5,Pesimista!F62,Base!F62,Optimista!F62) -> 185.18669 | G22: =CHOOSE(Supuestos!$C$5,Pesimista!G62,Base!G62,Optimista!G62) -> 194.44603
A23: Marketing y adquisición | C23: =CHOOSE(Supuestos!$C$5,Pesimista!C63,Base!C63,Optimista!C63) -> 9.0285 | D23: =CHOOSE(Supuestos!$C$5,Pesimista!D63,Base!D63,Optimista!D63) -> 17.260425 | E23: =CHOOSE(Supuestos!$C$5,Pesimista!E63,Base!E63,Optimista!E63) -> 32.785594 | F23: =CHOOSE(Supuestos!$C$5,Pesimista!F63,Base!F63,Optimista!F63) -> 42.551401 | G23: =CHOOSE(Supuestos!$C$5,Pesimista!G63,Base!G63,Optimista!G63) -> 53.211825
A24: Arriendo, administración, software, equipos y trabajo desde casa | C24: =CHOOSE(Supuestos!$C$5,Pesimista!C64,Base!C64,Optimista!C64) -> 5.7665398 | D24: =CHOOSE(Supuestos!$C$5,Pesimista!D64,Base!D64,Optimista!D64) -> 8.6218001 | E24: =CHOOSE(Supuestos!$C$5,Pesimista!E64,Base!E64,Optimista!E64) -> 17.5203 | F24: =CHOOSE(Supuestos!$C$5,Pesimista!F64,Base!F64,Optimista!F64) -> 18.396315 | G24: =CHOOSE(Supuestos!$C$5,Pesimista!G64,Base!G64,Optimista!G64) -> 19.316131
A25: Total gastos operativos | C25: =CHOOSE(Supuestos!$C$5,Pesimista!C65,Base!C65,Optimista!C65) -> 14.79504 | D25: =CHOOSE(Supuestos!$C$5,Pesimista!D65,Base!D65,Optimista!D65) -> 25.882225 | E25: =CHOOSE(Supuestos!$C$5,Pesimista!E65,Base!E65,Optimista!E65) -> 246.9169 | F25: =CHOOSE(Supuestos!$C$5,Pesimista!F65,Base!F65,Optimista!F65) -> 309.899 | G25: =CHOOSE(Supuestos!$C$5,Pesimista!G65,Base!G65,Optimista!G65) -> 382.28162
A26: Resultado operativo (EBITDA) | C26: =CHOOSE(Supuestos!$C$5,Pesimista!C66,Base!C66,Optimista!C66) -> 10.65471 | D26: =CHOOSE(Supuestos!$C$5,Pesimista!D66,Base!D66,Optimista!D66) -> 74.117721 | E26: =CHOOSE(Supuestos!$C$5,Pesimista!E66,Base!E66,Optimista!E66) -> -23.146673 | F26: =CHOOSE(Supuestos!$C$5,Pesimista!F66,Base!F66,Optimista!F66) -> 78.613241 | G26: =CHOOSE(Supuestos!$C$5,Pesimista!G66,Base!G66,Optimista!G66) -> 188.55391
A27: Impuesto de renta | C27: =CHOOSE(Supuestos!$C$5,Pesimista!C69,Base!C69,Optimista!C69) -> 3.7291486 | D27: =CHOOSE(Supuestos!$C$5,Pesimista!D69,Base!D69,Optimista!D69) -> 25.941202 | E27: =CHOOSE(Supuestos!$C$5,Pesimista!E69,Base!E69,Optimista!E69) -> 0 | F27: =CHOOSE(Supuestos!$C$5,Pesimista!F69,Base!F69,Optimista!F69) -> 19.413299 | G27: =CHOOSE(Supuestos!$C$5,Pesimista!G69,Base!G69,Optimista!G69) -> 65.99387
A28: Utilidad neta | C28: =CHOOSE(Supuestos!$C$5,Pesimista!C70,Base!C70,Optimista!C70) -> 6.9255617 | D28: =CHOOSE(Supuestos!$C$5,Pesimista!D70,Base!D70,Optimista!D70) -> 48.176519 | E28: =CHOOSE(Supuestos!$C$5,Pesimista!E70,Base!E70,Optimista!E70) -> -23.146673 | F28: =CHOOSE(Supuestos!$C$5,Pesimista!F70,Base!F70,Optimista!F70) -> 59.199943 | G28: =CHOOSE(Supuestos!$C$5,Pesimista!G70,Base!G70,Optimista!G70) -> 122.56004
A29: Flujo de caja neto | B29: =CHOOSE(Supuestos!$C$5,Pesimista!B71,Base!B71,Optimista!B71) -> -1.5 | C29: =CHOOSE(Supuestos!$C$5,Pesimista!C71,Base!C71,Optimista!C71) -> 6.9255617 | D29: =CHOOSE(Supuestos!$C$5,Pesimista!D71,Base!D71,Optimista!D71) -> 48.176519 | E29: =CHOOSE(Supuestos!$C$5,Pesimista!E71,Base!E71,Optimista!E71) -> -23.146673 | F29: =CHOOSE(Supuestos!$C$5,Pesimista!F71,Base!F71,Optimista!F71) -> 59.199943 | G29: =CHOOSE(Supuestos!$C$5,Pesimista!G71,Base!G71,Optimista!G71) -> 122.56004
A30: Flujo de caja acumulado | B30: =CHOOSE(Supuestos!$C$5,Pesimista!B72,Base!B72,Optimista!B72) -> -1.5 | C30: =CHOOSE(Supuestos!$C$5,Pesimista!C72,Base!C72,Optimista!C72) -> 5.4255617 | D30: =CHOOSE(Supuestos!$C$5,Pesimista!D72,Base!D72,Optimista!D72) -> 53.602081 | E30: =CHOOSE(Supuestos!$C$5,Pesimista!E72,Base!E72,Optimista!E72) -> 30.455407 | F30: =CHOOSE(Supuestos!$C$5,Pesimista!F72,Base!F72,Optimista!F72) -> 89.65535 | G30: =CHOOSE(Supuestos!$C$5,Pesimista!G72,Base!G72,Optimista!G72) -> 212.21539
A31: Memo: trabajo no remunerado de los fundadores (aporte en especie) | C31: =CHOOSE(Supuestos!$C$5,Pesimista!C74,Base!C74,Optimista!C74) -> 79.985613 | D31: =CHOOSE(Supuestos!$C$5,Pesimista!D74,Base!D74,Optimista!D74) -> 125.97734 | E31: =CHOOSE(Supuestos!$C$5,Pesimista!E74,Base!E74,Optimista!E74) -> 0 | F31: =CHOOSE(Supuestos!$C$5,Pesimista!F74,Base!F74,Optimista!F74) -> 0 | G31: =CHOOSE(Supuestos!$C$5,Pesimista!G74,Base!G74,Optimista!G74) -> 0
A32: Personas en el equipo al cierre | C32: =CHOOSE(Supuestos!$C$5,Pesimista!C75,Base!C75,Optimista!C75) -> 3 | D32: =CHOOSE(Supuestos!$C$5,Pesimista!D75,Base!D75,Optimista!D75) -> 3 | E32: =CHOOSE(Supuestos!$C$5,Pesimista!E75,Base!E75,Optimista!E75) -> 4 | F32: =CHOOSE(Supuestos!$C$5,Pesimista!F75,Base!F75,Optimista!F75) -> 5 | G32: =CHOOSE(Supuestos!$C$5,Pesimista!G75,Base!G75,Optimista!G75) -> 6
A33: Punto de equilibrio (clientes activos) | C33: =CHOOSE(Supuestos!$C$5,Pesimista!C77,Base!C77,Optimista!C77) -> 39 | D33: =CHOOSE(Supuestos!$C$5,Pesimista!D77,Base!D77,Optimista!D77) -> 61 | E33: =CHOOSE(Supuestos!$C$5,Pesimista!E77,Base!E77,Optimista!E77) -> 510 | F33: =CHOOSE(Supuestos!$C$5,Pesimista!F77,Base!F77,Optimista!F77) -> 612 | G33: =CHOOSE(Supuestos!$C$5,Pesimista!G77,Base!G77,Optimista!G77) -> 718
A35: 24. Inversiones (COP)
A36: Gastos preoperativos | B36: =Supuestos!$C$71 -> 500000
A37: Marketing inicial | B37: =Supuestos!$C$72 -> 1000000
A38: Equipos de cómputo (aporte en especie) | B38: =Supuestos!$C$73 -> 0
A39: Total inversión inicial | B39: =SUM(B36:B38) -> 1500000
A41: 25. Capital de trabajo e indicadores
A42: VPN a la TIO (millones COP) | B42: =CHOOSE(Supuestos!$C$5,Pesimista!C80,Base!C80,Optimista!C80) -> 102.13564
A43: TIR | B43: =CHOOSE(Supuestos!$C$5,Pesimista!C81,Base!C81,Optimista!C81) -> 7.333862
A44: Año de recuperación de la inversión | B44: =CHOOSE(Supuestos!$C$5,Pesimista!C82,Base!C82,Optimista!C82) -> 1
A45: Necesidad máxima de caja (millones COP) | B45: =CHOOSE(Supuestos!$C$5,Pesimista!C83,Base!C83,Optimista!C83) -> 3.4915691
A46: Primer mes con resultado operativo positivo | B46: =CHOOSE(Supuestos!$C$5,Pesimista!C84,Base!C84,Optimista!C84) -> 5
A47: Capital de trabajo requerido (necesidad máxima de caja − inversión inicial, COP) | B47: =MAX(0,B45*1000000-B39) -> 1991569.1
A49: 26. Resumen de fuentes de financiación (COP)
A50: Recursos propios (fundadores) | B50: =Supuestos!$C$78 -> 4000000
A51: Fondo Emprender | B51: =Supuestos!$C$79 -> 6000000
A52: Otras fuentes | B52: =Supuestos!$C$80 -> 5850000
A53: Total fuentes identificadas | B53: =SUM(B50:B52) -> 15850000
A54: Financiación requerida (necesidad máxima de caja) | B54: =B45*1000000 -> 3491569.1
A55: Brecha de financiación (negativo = faltan recursos) | B55: =B53-B54 -> 12358431

Sheet Comparación
A1: Comparación de escenarios
A2: ="Modo de equipo: "&IF(Supuestos!$C$8=1,"según carga de trabajo","calendario del plan original") -> Modo de equipo: según carga de trabajo
A4: Indicador | B4: Pesimista | C4: Base | D4: Optimista
A5: Clientes activos al cierre del año 5 | B5: =Pesimista!G53 -> 600 | C5: =Base!G53 -> 1200 | D5: =Optimista!G53 -> 1600
A6: Ingresos año 1 (millones COP) | B6: =Pesimista!C57 -> 14.9625 | C6: =Base!C57 -> 29.925 | D6: =Optimista!C57 -> 37.40625
A7: Ingresos año 5 (millones COP) | B7: =Pesimista!G57 -> 309.17921 | C7: =Base!G57 -> 618.35842 | D7: =Optimista!G57 -> 824.47789
A8: Utilidad neta año 1 (millones COP) | B8: =Pesimista!C70 -> -1.9366648 | C8: =Base!C70 -> 6.9255617 | D8: =Optimista!C70 -> 11.971796
A9: Utilidad neta año 5 (millones COP) | B9: =Pesimista!G70 -> -18.486027 | C9: =Base!G70 -> 122.56004 | D9: =Optimista!G70 -> 224.97898
A10: Trabajo no remunerado de fundadores, 5 años (millones COP) | B10: =SUM(Pesimista!C74:G74) -> 382.33123 | C10: =SUM(Base!C74:G74) -> 205.96295 | D10: =SUM(Optimista!C74:G74) -> 205.96295
A11: Personas en el equipo al cierre del año 5 | B11: =Pesimista!G75 -> 4 | C11: =Base!G75 -> 6 | D11: =Optimista!G75 -> 7
A12: VPN a la TIO (millones COP) | B12: =Pesimista!C80 -> 0.84796043 | C12: =Base!C80 -> 102.13564 | D12: =Optimista!C80 -> 206.6355
A13: TIR | B13: =Pesimista!C81 -> 0.17689002 | C13: =Base!C81 -> 7.333862 | D13: =Optimista!C81 -> 10.528371
A14: Año de recuperación de la inversión | B14: =Pesimista!C82 -> 2 | C14: =Base!C82 -> 1 | D14: =Optimista!C82 -> 1
A15: Necesidad máxima de caja (millones COP) | B15: =Pesimista!C83 -> 5.5498048 | C15: =Base!C83 -> 3.4915691 | D15: =Optimista!C83 -> 2.854692
A16: Primer mes con resultado operativo positivo | B16: =Pesimista!C84 -> 9 | C16: =Base!C84 -> 5 | D16: =Optimista!C84 -> 4

Sheet Pesimista
A1: Escenario Pesimista — proyección mensual (60 meses) y anual
A2: Índice del escenario | B2: 1
A3: Todo en esta hoja es fórmula. Para cambiar resultados, edite la hoja Supuestos.
A5: Mes | C5: 1 | D5: 2 | E5: 3 | F5: 4 | G5: 5 | H5: 6 | I5: 7 | J5: 8 | K5: 9 | L5: 10 | M5: 11 | N5: 12 | O5: 13 | P5: 14 | Q5: 15 | R5: 16 | S5: 17 | T5: 18 | U5: 19 | V5: 20 | W5: 21 | X5: 22 | Y5: 23 | Z5: 24 | AA5: 25 | AB5: 26 | AC5: 27 | AD5: 28 | AE5: 29 | AF5: 30 | AG5: 31 | AH5: 32 | AI5: 33 | AJ5: 34 | AK5: 35 | AL5: 36 | AM5: 37 | AN5: 38 | AO5: 39 | AP5: 40 | AQ5: 41 | AR5: 42 | AS5: 43 | AT5: 44 | AU5: 45 | AV5: 46 | AW5: 47 | AX5: 48 | AY5: 49 | AZ5: 50 | BA5: 51 | BB5: 52 | BC5: 53 | BD5: 54 | BE5: 55 | BF5: 56 | BG5: 57 | BH5: 58 | BI5: 59 | BJ5: 60
A6: Año | C6: =ROUNDUP(C5/12,0) -> 1 | D6: =ROUNDUP(D5/12,0) -> 1 | E6: =ROUNDUP(E5/12,0) -> 1 | F6: =ROUNDUP(F5/12,0) -> 1 | G6: =ROUNDUP(G5/12,0) -> 1 | H6: =ROUNDUP(H5/12,0) -> 1 | I6: =ROUNDUP(I5/12,0) -> 1 | J6: =ROUNDUP(J5/12,0) -> 1 | ... BJ6: =ROUNDUP(BJ5/12,0) -> 5
A7: Mes del año | C7: =C5-(C6-1)*12 -> 1 | D7: =D5-(D6-1)*12 -> 2 | E7: =E5-(E6-1)*12 -> 3 | F7: =F5-(F6-1)*12 -> 4 | G7: =G5-(G6-1)*12 -> 5 | H7: =H5-(H6-1)*12 -> 6 | I7: =I5-(I6-1)*12 -> 7 | J7: =J5-(J6-1)*12 -> 8 | ... BJ7: =BJ5-(BJ6-1)*12 -> 12
A9: Clientes
A10: Meta de clientes activos al cierre del mes | B10: clientes | C10: =IF(C6=1,INDEX(Supuestos!$C$22:$N$22,1,C7)*INDEX(Supuestos!$C$11:$E$11,1,$B$2),IF(C6=2,INDEX(Supuestos!$C$11:$E$11,1,$B$2),IF(C6=3,INDEX(Supuestos!$C$12:$E$12,1,$B$2),IF(C6=4,INDEX(Supuestos!$C$13:$E$13,1,$B$2),INDEX(Supuestos!$C$14:$E$14,1,$B$2))))+(IF(C6=2,INDEX(Supuestos!$C$12:$E$12,1,$B$2),IF(C6=3,INDEX(Supuestos!$C$13:$E$13,1,$B$2),IF(C6=4,INDEX(Supuestos!$C$14:$E$14,1,$B$2),INDEX(Supuestos!$C$15:$E$15,1,$B$2))))-IF(C6=2,INDEX(Supuestos!$C$11:$E$11,1,$B$2),IF(C6=3,INDEX(Supuestos!$C$12:$E$12,1,$B$2),IF(C6=4,INDEX(Supuestos!$C$13:$E$13,1,$B$2),INDEX(Supuestos!$C$14:$E$14,1,$B$2)))))*C7/12) -> 4.998 | D10: =IF(D6=1,INDEX(Supuestos!$C$22:$N$22,1,D7)*INDEX(Supuestos!$C$11:$E$11,1,$B$2),IF(D6=2,INDEX(Supuestos!$C$11:$E$11,1,$B$2),IF(D6=3,INDEX(Supuestos!$C$12:$E$12,1,$B$2),IF(D6=4,INDEX(Supuestos!$C$13:$E$13,1,$B$2),INDEX(Supuestos!$C$14:$E$14,1,$B$2))))+(IF(D6=2,INDEX(Supuestos!$C$12:$E$12,1,$B$2),IF(D6=3,INDEX(Supuestos!$C$13:$E$13,1,$B$2),IF(D6=4,INDEX(Supuestos!$C$14:$E$14,1,$B$2),INDEX(Supuestos!$C$15:$E$15,1,$B$2))))-IF(D6=2,INDEX(Supuestos!$C$11:$E$11,1,$B$2),IF(D6=3,INDEX(Supuestos!$C$12:$E$12,1,$B$2),IF(D6=4,INDEX(Supuestos!$C$13:$E$13,1,$B$2),INDEX(Supuestos!$C$14:$E$14,1,$B$2)))))*D7/12) -> 7.5 | E10: =IF(E6=1,INDEX(Supuestos!$C$22:$N$22,1,E7)*INDEX(Supuestos!$C$11:$E$11,1,$B$2),IF(E6=2,INDEX(Supuestos!$C$11:$E$11,1,$B$2),IF(E6=3,INDEX(Supuestos!$C$12:$E$12,1,$B$2),IF(E6=4,INDEX(Supuestos!$C$13:$E$13,1,$B$2),INDEX(Supuestos!$C$14:$E$14,1,$B$2))))+(IF(E6=2,INDEX(Supuestos!$C$12:$E$12,1,$B$2),IF(E6=3,INDEX(Supuestos!$C$13:$E$13,1,$B$2),IF(E6=4,INDEX(Supuestos!$C$14:$E$14,1,$B$2),INDEX(Supuestos!$C$15:$E$15,1,$B$2))))-IF(E6=2,INDEX(Supuestos!$C$11:$E$11,1,$B$2),IF(E6=3,INDEX(Supuestos!$C$12:$E$12,1,$B$2),IF(E6=4,INDEX(Supuestos!$C$13:$E$13,1,$B$2),INDEX(Supuestos!$C$14:$E$14,1,$B$2)))))*E7/12) -> 12.498 | F10: =IF(F6=1,INDEX(Supuestos!$C$22:$N$22,1,F7)*INDEX(Supuestos!$C$11:$E$11,1,$B$2),IF(F6=2,INDEX(Supuestos!$C$11:$E$11,1,$B$2),IF(F6=3,INDEX(Supuestos!$C$12:$E$12,1,$B$2),IF(F6=4,INDEX(Supuestos!$C$13:$E$13,1,$B$2),INDEX(Supuestos!$C$14:$E$14,1,$B$2))))+(IF(F6=2,INDEX(Supuestos!$C$12:$E$12,1,$B$2),IF(F6=3,INDEX(Supuestos!$C$13:$E$13,1,$B$2),IF(F6=4,INDEX(Supuestos!$C$14:$E$14,1,$B$2),INDEX(Supuestos!$C$15:$E$15,1,$B$2))))-IF(F6=2,INDEX(Supuestos!$C$11:$E$11,1,$B$2),IF(F6=3,INDEX(Supuestos!$C$12:$E$12,1,$B$2),IF(F6=4,INDEX(Supuestos!$C$13:$E$13,1,$B$2),INDEX(Supuestos!$C$14:$E$14,1,$B$2)))))*F7/12) -> 17.502 | G10: =IF(G6=1,INDEX(Supuestos!$C$22:$N$22,1,G7)*INDEX(Supuestos!$C$11:$E$11,1,$B$2),IF(G6=2,INDEX(Supuestos!$C$11:$E$11,1,$B$2),IF(G6=3,INDEX(Supuestos!$C$12:$E$12,1,$B$2),IF(G6=4,INDEX(Supuestos!$C$13:$E$13,1,$B$2),INDEX(Supuestos!$C$14:$E$14,1,$B$2))))+(IF(G6=2,INDEX(Supuestos!$C$12:$E$12,1,$B$2),IF(G6=3,INDEX(Supuestos!$C$13:$E$13,1,$B$2),IF(G6=4,INDEX(Supuestos!$C$14:$E$14,1,$B$2),INDEX(Supuestos!$C$15:$E$15,1,$B$2))))-IF(G6=2,INDEX(Supuestos!$C$11:$E$11,1,$B$2),IF(G6=3,INDEX(Supuestos!$C$12:$E$12,1,$B$2),IF(G6=4,INDEX(Supuestos!$C$13:$E$13,1,$B$2),INDEX(Supuestos!$C$14:$E$14,1,$B$2)))))*G7/12) -> 22.5 | H10: =IF(H6=1,INDEX(Supuestos!$C$22:$N$22,1,H7)*INDEX(Supuestos!$C$11:$E$11,1,$B$2),IF(H6=2,INDEX(Supuestos!$C$11:$E$11,1,$B$2),IF(H6=3,INDEX(Supuestos!$C$12:$E$12,1,$B$2),IF(H6=4,INDEX(Supuestos!$C$13:$E$13,1,$B$2),INDEX(Supuestos!$C$14:$E$14,1,$B$2))))+(IF(H6=2,INDEX(Supuestos!$C$12:$E$12,1,$B$2),IF(H6=3,INDEX(Supuestos!$C$13:$E$13,1,$B$2),IF(H6=4,INDEX(Supuestos!$C$14:$E$14,1,$B$2),INDEX(Supuestos!$C$15:$E$15,1,$B$2))))-IF(H6=2,INDEX(Supuestos!$C$11:$E$11,1,$B$2),IF(H6=3,INDEX(Supuestos!$C$12:$E$12,1,$B$2),IF(H6=4,INDEX(Supuestos!$C$13:$E$13,1,$B$2),INDEX(Supuestos!$C$14:$E$14,1,$B$2)))))*H7/12) -> 27.498 | I10: =IF(I6=1,INDEX(Supuestos!$C$22:$N$22,1,I7)*INDEX(Supuestos!$C$11:$E$11,1,$B$2),IF(I6=2,INDEX(Supuestos!$C$11:$E$11,1,$B$2),IF(I6=3,INDEX(Supuestos!$C$12:$E$12,1,$B$2),IF(I6=4,INDEX(Supuestos!$C$13:$E$13,1,$B$2),INDEX(Supuestos!$C$14:$E$14,1,$B$2))))+(IF(I6=2,INDEX(Supuestos!$C$12:$E$12,1,$B$2),IF(I6=3,INDEX(Supuestos!$C$13:$E$13,1,$B$2),IF(I6=4,INDEX(Supuestos!$C$14:$E$14,1,$B$2),INDEX(Supuestos!$C$15:$E$15,1,$B$2))))-IF(I6=2,INDEX(Supuestos!$C$11:$E$11,1,$B$2),IF(I6=3,INDEX(Supuestos!$C$12:$E$12,1,$B$2),IF(I6=4,INDEX(Supuestos!$C$13:$E$13,1,$B$2),INDEX(Supuestos!$C$14:$E$14,1,$B$2)))))*I7/12) -> 32.502 | J10: =IF(J6=1,INDEX(Supuestos!$C$22:$N$22,1,J7)*INDEX(Supuestos!$C$11:$E$11,1,$B$2),IF(J6=2,INDEX(Supuestos!$C$11:$E$11,1,$B$2),IF(J6=3,INDEX(Supuestos!$C$12:$E$12,1,$B$2),IF(J6=4,INDEX(Supuestos!$C$13:$E$13,1,$B$2),INDEX(Supuestos!$C$14:$E$14,1,$B$2))))+(IF(J6=2,INDEX(Supuestos!$C$12:$E$12,1,$B$2),IF(J6=3,INDEX(Supuestos!$C$13:$E$13,1,$B$2),IF(J6=4,INDEX(Supuestos!$C$14:$E$14,1,$B$2),INDEX(Supuestos!$C$15:$E$15,1,$B$2))))-IF(J6=2,INDEX(Supuestos!$C$11:$E$11,1,$B$2),IF(J6=3,INDEX(Supuestos!$C$12:$E$12,1,$B$2),IF(J6=4,INDEX(Supuestos!$C$13:$E$13,1,$B$2),INDEX(Supuestos!$C$14:$E$14,1,$B$2)))))*J7/12) -> 40.002 | ... BJ10: =IF(BJ6=1,INDEX(Supuestos!$C$22:$N$22,1,BJ7)*INDEX(Supuestos!$C$11:$E$11,1,$B$2),IF(BJ6=2,INDEX(Supuestos!$C$11:$E$11,1,$B$2),IF(BJ6=3,INDEX(Supuestos!$C$12:$E$12,1,$B$2),IF(BJ6=4,INDEX(Supuestos!$C$13:$E$13,1,$B$2),INDEX(Supuestos!$C$14:$E$14,1,$B$2))))+(IF(BJ6=2,INDEX(Supuestos!$C$12:$E$12,1,$B$2),IF(BJ6=3,INDEX(Supuestos!$C$13:$E$13,1,$B$2),IF(BJ6=4,INDEX(Supuestos!$C$14:$E$14,1,$B$2),INDEX(Supuestos!$C$15:$E$15,1,$B$2))))-IF(BJ6=2,INDEX(Supuestos!$C$11:$E$11,1,$B$2),IF(BJ6=3,INDEX(Supuestos!$C$12:$E$12,1,$B$2),IF(BJ6=4,INDEX(Supuestos!$C$13:$E$13,1,$B$2),INDEX(Supuestos!$C$14:$E$14,1,$B$2)))))*BJ7/12) -> 600
A11: Clientes al inicio del mes | B11: clientes | C11: 0 | D11: =C14 -> 4.998 | E11: =D14 -> 7.5 | F11: =E14 -> 12.498 | G11: =F14 -> 17.502 | H11: =G14 -> 22.5 | I11: =H14 -> 27.498 | J11: =I14 -> 32.502 | K11: =J14 -> 40.002 | ... BJ11: =BI14 -> 587.5
A12: Clientes que se retiran | B12: clientes | C12: =C11*INDEX(Supuestos!$C$16:$E$16,1,$B$2) -> 0 | D12: =D11*INDEX(Supuestos!$C$16:$E$16,1,$B$2) -> 0.2499 | E12: =E11*INDEX(Supuestos!$C$16:$E$16,1,$B$2) -> 0.375 | F12: =F11*INDEX(Supuestos!$C$16:$E$16,1,$B$2) -> 0.6249 | G12: =G11*INDEX(Supuestos!$C$16:$E$16,1,$B$2) -> 0.8751 | H12: =H11*INDEX(Supuestos!$C$16:$E$16,1,$B$2) -> 1.125 | I12: =I11*INDEX(Supuestos!$C$16:$E$16,1,$B$2) -> 1.3749 | J12: =J11*INDEX(Supuestos!$C$16:$E$16,1,$B$2) -> 1.6251 | ... BJ12: =BJ11*INDEX(Supuestos!$C$16:$E$16,1,$B$2) -> 29.375
A13: Clientes nuevos | B13: clientes | C13: =MAX(0,C10-(C11-C12)) -> 4.998 | D13: =MAX(0,D10-(D11-D12)) -> 2.7519 | E13: =MAX(0,E10-(E11-E12)) -> 5.373 | F13: =MAX(0,F10-(F11-F12)) -> 5.6289 | G13: =MAX(0,G10-(G11-G12)) -> 5.8731 | H13: =MAX(0,H10-(H11-H12)) -> 6.123 | I13: =MAX(0,I10-(I11-I12)) -> 6.3789 | J13: =MAX(0,J10-(J11-J12)) -> 9.1251 | ... BJ13: =MAX(0,BJ10-(BJ11-BJ12)) -> 41.875
A14: Clientes activos al cierre del mes | B14: clientes | C14: =C11-C12+C13 -> 4.998 | D14: =D11-D12+D13 -> 7.5 | E14: =E11-E12+E13 -> 12.498 | F14: =F11-F12+F13 -> 17.502 | G14: =G11-G12+G13 -> 22.5 | H14: =H11-H12+H13 -> 27.498 | I14: =I11-I12+I13 -> 32.502 | J14: =J11-J12+J13 -> 40.002 | ... BJ14: =BJ11-BJ12+BJ13 -> 600
A16: Ingresos y costos variables
A17: Precio mensual por tienda | B17: COP | C17: =Supuestos!$C$26*(1+Supuestos!$C$27)^(C6-1) -> 39900 | D17: =Supuestos!$C$26*(1+Supuestos!$C$27)^(D6-1) -> 39900 | E17: =Supuestos!$C$26*(1+Supuestos!$C$27)^(E6-1) -> 39900 | F17: =Supuestos!$C$26*(1+Supuestos!$C$27)^(F6-1) -> 39900 | G17: =Supuestos!$C$26*(1+Supuestos!$C$27)^(G6-1) -> 39900 | H17: =Supuestos!$C$26*(1+Supuestos!$C$27)^(H6-1) -> 39900 | I17: =Supuestos!$C$26*(1+Supuestos!$C$27)^(I6-1) -> 39900 | J17: =Supuestos!$C$26*(1+Supuestos!$C$27)^(J6-1) -> 39900 | ... BJ17: =Supuestos!$C$26*(1+Supuestos!$C$27)^(BJ6-1) -> 48498.699
A18: Ingresos | B18: COP | C18: =C14*C17 -> 199420.2 | D18: =D14*D17 -> 299250 | E18: =E14*E17 -> 498670.2 | F18: =F14*F17 -> 698329.8 | G18: =G14*G17 -> 897750 | H18: =H14*H17 -> 1097170.2 | I18: =I14*I17 -> 1296829.8 | J18: =J14*J17 -> 1596079.8 | ... BJ18: =BJ14*BJ17 -> 29099220
A19: Costo de IA | B19: COP | C19: =C14*Supuestos!$C$29*(1+Supuestos!$C$39)^(C6-1) -> 6247.5 | D19: =D14*Supuestos!$C$29*(1+Supuestos!$C$39)^(D6-1) -> 9375 | E19: =E14*Supuestos!$C$29*(1+Supuestos!$C$39)^(E6-1) -> 15622.5 | F19: =F14*Supuestos!$C$29*(1+Supuestos!$C$39)^(F6-1) -> 21877.5 | G19: =G14*Supuestos!$C$29*(1+Supuestos!$C$39)^(G6-1) -> 28125 | H19: =H14*Supuestos!$C$29*(1+Supuestos!$C$39)^(H6-1) -> 34372.5 | I19: =I14*Supuestos!$C$29*(1+Supuestos!$C$39)^(I6-1) -> 40627.5 | J19: =J14*Supuestos!$C$29*(1+Supuestos!$C$39)^(J6-1) -> 50002.5 | ... BJ19: =BJ14*Supuestos!$C$29*(1+Supuestos!$C$39)^(BJ6-1) -> 911629.69
A20: Comisión de pasarela de pagos | B20: COP | C20: =C18*Supuestos!$C$30 -> 5982.606 | D20: =D18*Supuestos!$C$30 -> 8977.5 | E20: =E18*Supuestos!$C$30 -> 14960.106 | F20: =F18*Supuestos!$C$30 -> 20949.894 | G20: =G18*Supuestos!$C$30 -> 26932.5 | H20: =H18*Supuestos!$C$30 -> 32915.106 | I20: =I18*Supuestos!$C$30 -> 38904.894 | J20: =J18*Supuestos!$C$30 -> 47882.394 | ... BJ20: =BJ18*Supuestos!$C$30 -> 872976.59
A21: Infraestructura en la nube | B21: COP | C21: =IF(C14<=Supuestos!$C$32,Supuestos!$C$31,IF(C14<=Supuestos!$C$34,Supuestos!$C$33,Supuestos!$C$35)) -> 220000 | D21: =IF(D14<=Supuestos!$C$32,Supuestos!$C$31,IF(D14<=Supuestos!$C$34,Supuestos!$C$33,Supuestos!$C$35)) -> 220000 | E21: =IF(E14<=Supuestos!$C$32,Supuestos!$C$31,IF(E14<=Supuestos!$C$34,Supuestos!$C$33,Supuestos!$C$35)) -> 220000 | F21: =IF(F14<=Supuestos!$C$32,Supuestos!$C$31,IF(F14<=Supuestos!$C$34,Supuestos!$C$33,Supuestos!$C$35)) -> 220000 | G21: =IF(G14<=Supuestos!$C$32,Supuestos!$C$31,IF(G14<=Supuestos!$C$34,Supuestos!$C$33,Supuestos!$C$35)) -> 220000 | H21: =IF(H14<=Supuestos!$C$32,Supuestos!$C$31,IF(H14<=Supuestos!$C$34,Supuestos!$C$33,Supuestos!$C$35)) -> 220000 | I21: =IF(I14<=Supuestos!$C$32,Supuestos!$C$31,IF(I14<=Supuestos!$C$34,Supuestos!$C$33,Supuestos!$C$35)) -> 220000 | J21: =IF(J14<=Supuestos!$C$32,Supuestos!$C$31,IF(J14<=Supuestos!$C$34,Supuestos!$C$33,Supuestos!$C$35)) -> 220000 | ... BJ21: =IF(BJ14<=Supuestos!$C$32,Supuestos!$C$31,IF(BJ14<=Supuestos!$C$34,Supuestos!$C$33,Supuestos!$C$35)) -> 450000
A22: Total costos de operación del servicio | B22: COP | C22: =SUM(C19:C21) -> 232230.11 | D22: =SUM(D19:D21) -> 238352.5 | E22: =SUM(E19:E21) -> 250582.61 | F22: =SUM(F19:F21) -> 262827.39 | G22: =SUM(G19:G21) -> 275057.5 | H22: =SUM(H19:H21) -> 287287.61 | I22: =SUM(I19:I21) -> 299532.39 | J22: =SUM(J19:J21) -> 317884.89 | ... BJ22: =SUM(BJ19:BJ21) -> 2234606.3
A23: Margen bruto | B23: COP | C23: =C18-C22 -> -32809.906 | D23: =D18-D22 -> 60897.5 | E23: =E18-E22 -> 248087.59 | F23: =F18-F22 -> 435502.41 | G23: =G18-G22 -> 622692.5 | H23: =H18-H22 -> 809882.59 | I23: =I18-I22 -> 997297.41 | J23: =J18-J22 -> 1278194.9 | ... BJ23: =BJ18-BJ22 -> 26864613
A25: Carga de trabajo y equipo
A26: Horas de soporte | B26: horas | C26: =C14*Supuestos!$C$58/60 -> 1.666 | D26: =D14*Supuestos!$C$58/60 -> 2.5 | E26: =E14*Supuestos!$C$58/60 -> 4.166 | F26: =F14*Supuestos!$C$58/60 -> 5.834 | G26: =G14*Supuestos!$C$58/60 -> 7.5 | H26: =H14*Supuestos!$C$58/60 -> 9.166 | I26: =I14*Supuestos!$C$58/60 -> 10.834 | J26: =J14*Supuestos!$C$58/60 -> 13.334 | ... BJ26: =BJ14*Supuestos!$C$58/60 -> 200
A27: Horas de incorporación de clientes nuevos | B27: horas | C27: =C13*Supuestos!$C$59 -> 8.4966 | D27: =D13*Supuestos!$C$59 -> 4.67823 | E27: =E13*Supuestos!$C$59 -> 9.1341 | F27: =F13*Supuestos!$C$59 -> 9.56913 | G27: =G13*Supuestos!$C$59 -> 9.98427 | H27: =H13*Supuestos!$C$59 -> 10.4091 | I27: =I13*Supuestos!$C$59 -> 10.84413 | J27: =J13*Supuestos!$C$59 -> 15.51267 | ... BJ27: =BJ13*Supuestos!$C$59 -> 71.1875
A28: Horas de ventas | B28: horas | C28: =C13*Supuestos!$C$60 -> 19.992 | D28: =D13*Supuestos!$C$60 -> 11.0076 | E28: =E13*Supuestos!$C$60 -> 21.492 | F28: =F13*Supuestos!$C$60 -> 22.5156 | G28: =G13*Supuestos!$C$60 -> 23.4924 | H28: =H13*Supuestos!$C$60 -> 24.492 | I28: =I13*Supuestos!$C$60 -> 25.5156 | J28: =J13*Supuestos!$C$60 -> 36.5004 | ... BJ28: =BJ13*Supuestos!$C$60 -> 167.5
A29: Horas de desarrollo y mantenimiento | B29: horas | C29: =Supuestos!$C$61+C14/100*Supuestos!$C$62 -> 80.2499 | D29: =Supuestos!$C$61+D14/100*Supuestos!$C$62 -> 80.375 | E29: =Supuestos!$C$61+E14/100*Supuestos!$C$62 -> 80.6249 | F29: =Supuestos!$C$61+F14/100*Supuestos!$C$62 -> 80.8751 | G29: =Supuestos!$C$61+G14/100*Supuestos!$C$62 -> 81.125 | H29: =Supuestos!$C$61+H14/100*Supuestos!$C$62 -> 81.3749 | I29: =Supuestos!$C$61+I14/100*Supuestos!$C$62 -> 81.6251 | J29: =Supuestos!$C$61+J14/100*Supuestos!$C$62 -> 82.0001 | ... BJ29: =Supuestos!$C$61+BJ14/100*Supuestos!$C$62 -> 110
A30: Horas requeridas | B30: horas | C30: =SUM(C26:C29) -> 110.4045 | D30: =SUM(D26:D29) -> 98.56083 | E30: =SUM(E26:E29) -> 115.417 | F30: =SUM(F26:F29) -> 118.79383 | G30: =SUM(G26:G29) -> 122.10167 | H30: =SUM(H26:H29) -> 125.442 | I30: =SUM(I26:I29) -> 128.81883 | J30: =SUM(J26:J29) -> 147.34717 | ... BJ30: =SUM(BJ26:BJ29) -> 548.6875
A31: Capacidad de los fundadores | B31: horas | C31: =Supuestos!$C$51*IF(C6=1,Supuestos!$C$54,IF(C6=2,Supuestos!$C$55,Supuestos!$C$56)) -> 240 | D31: =Supuestos!$C$51*IF(D6=1,Supuestos!$C$54,IF(D6=2,Supuestos!$C$55,Supuestos!$C$56)) -> 240 | E31: =Supuestos!$C$51*IF(E6=1,Supuestos!$C$54,IF(E6=2,Supuestos!$C$55,Supuestos!$C$56)) -> 240 | F31: =Supuestos!$C$51*IF(F6=1,Supuestos!$C$54,IF(F6=2,Supuestos!$C$55,Supuestos!$C$56)) -> 240 | G31: =Supuestos!$C$51*IF(G6=1,Supuestos!$C$54,IF(G6=2,Supuestos!$C$55,Supuestos!$C$56)) -> 240 | H31: =Supuestos!$C$51*IF(H6=1,Supuestos!$C$54,IF(H6=2,Supuestos!$C$55,Supuestos!$C$56)) -> 240 | I31: =Supuestos!$C$51*IF(I6=1,Supuestos!$C$54,IF(I6=2,Supuestos!$C$55,Supuestos!$C$56)) -> 240 | J31: =Supuestos!$C$51*IF(J6=1,Supuestos!$C$54,IF(J6=2,Supuestos!$C$55,Supuestos!$C$56)) -> 240 | ... BJ31: =Supuestos!$C$51*IF(BJ6=1,Supuestos!$C$54,IF(BJ6=2,Supuestos!$C$55,Supuestos!$C$56)) -> 480
A32: Colaboradores contratados | B32: personas | C32: =IF(Supuestos!$C$8=1,MAX(0,ROUNDUP((C30-C31)/Supuestos!$C$57,0)),IF(C5=1,1,IF(C6=1,2,IF(C6=2,3,IF(C6=3,4,5))))) -> 0 | D32: =IF(Supuestos!$C$8=1,MAX(0,ROUNDUP((D30-D31)/Supuestos!$C$57,0)),IF(D5=1,1,IF(D6=1,2,IF(D6=2,3,IF(D6=3,4,5))))) -> 0 | E32: =IF(Supuestos!$C$8=1,MAX(0,ROUNDUP((E30-E31)/Supuestos!$C$57,0)),IF(E5=1,1,IF(E6=1,2,IF(E6=2,3,IF(E6=3,4,5))))) -> 0 | F32: =IF(Supuestos!$C$8=1,MAX(0,ROUNDUP((F30-F31)/Supuestos!$C$57,0)),IF(F5=1,1,IF(F6=1,2,IF(F6=2,3,IF(F6=3,4,5))))) -> 0 | G32: =IF(Supuestos!$C$8=1,MAX(0,ROUNDUP((G30-G31)/Supuestos!$C$57,0)),IF(G5=1,1,IF(G6=1,2,IF(G6=2,3,IF(G6=3,4,5))))) -> 0 | H32: =IF(Supuestos!$C$8=1,MAX(0,ROUNDUP((H30-H31)/Supuestos!$C$57,0)),IF(H5=1,1,IF(H6=1,2,IF(H6=2,3,IF(H6=3,4,5))))) -> 0 | I32: =IF(Supuestos!$C$8=1,MAX(0,ROUNDUP((I30-I31)/Supuestos!$C$57,0)),IF(I5=1,1,IF(I6=1,2,IF(I6=2,3,IF(I6=3,4,5))))) -> 0 | J32: =IF(Supuestos!$C$8=1,MAX(0,ROUNDUP((J30-J31)/Supuestos!$C$57,0)),IF(J5=1,1,IF(J6=1,2,IF(J6=2,3,IF(J6=3,4,5))))) -> 0 | ... BJ32: =IF(Supuestos!$C$8=1,MAX(0,ROUNDUP((BJ30-BJ31)/Supuestos!$C$57,0)),IF(BJ5=1,1,IF(BJ6=1,2,IF(BJ6=2,3,IF(BJ6=3,4,5))))) -> 1
A33: Costo total mensual por colaborador | B33: COP | C33: =Supuestos!$C$50*(1+Supuestos!$C$39)^(C6-1)*(1+Supuestos!$C$48)+IF(Supuestos!$C$50*(1+Supuestos!$C$39)^(C6-1)<=2*Supuestos!$C$37*(1+Supuestos!$C$39)^(C6-1),Supuestos!$C$38*(1+Supuestos!$C$39)^(C6-1)*(1+Supuestos!$C$49),0) -> 3060125.2 | D33: =Supuestos!$C$50*(1+Supuestos!$C$39)^(D6-1)*(1+Supuestos!$C$48)+IF(Supuestos!$C$50*(1+Supuestos!$C$39)^(D6-1)<=2*Supuestos!$C$37*(1+Supuestos!$C$39)^(D6-1),Supuestos!$C$38*(1+Supuestos!$C$39)^(D6-1)*(1+Supuestos!$C$49),0) -> 3060125.2 | E33: =Supuestos!$C$50*(1+Supuestos!$C$39)^(E6-1)*(1+Supuestos!$C$48)+IF(Supuestos!$C$50*(1+Supuestos!$C$39)^(E6-1)<=2*Supuestos!$C$37*(1+Supuestos!$C$39)^(E6-1),Supuestos!$C$38*(1+Supuestos!$C$39)^(E6-1)*(1+Supuestos!$C$49),0) -> 3060125.2 | F33: =Supuestos!$C$50*(1+Supuestos!$C$39)^(F6-1)*(1+Supuestos!$C$48)+IF(Supuestos!$C$50*(1+Supuestos!$C$39)^(F6-1)<=2*Supuestos!$C$37*(1+Supuestos!$C$39)^(F6-1),Supuestos!$C$38*(1+Supuestos!$C$39)^(F6-1)*(1+Supuestos!$C$49),0) -> 3060125.2 | G33: =Supuestos!$C$50*(1+Supuestos!$C$39)^(G6-1)*(1+Supuestos!$C$48)+IF(Supuestos!$C$50*(1+Supuestos!$C$39)^(G6-1)<=2*Supuestos!$C$37*(1+Supuestos!$C$39)^(G6-1),Supuestos!$C$38*(1+Supuestos!$C$39)^(G6-1)*(1+Supuestos!$C$49),0) -> 3060125.2 | H33: =Supuestos!$C$50*(1+Supuestos!$C$39)^(H6-1)*(1+Supuestos!$C$48)+IF(Supuestos!$C$50*(1+Supuestos!$C$39)^(H6-1)<=2*Supuestos!$C$37*(1+Supuestos!$C$39)^(H6-1),Supuestos!$C$38*(1+Supuestos!$C$39)^(H6-1)*(1+Supuestos!$C$49),0) -> 3060125.2 | I33: =Supuestos!$C$50*(1+Supuestos!$C$39)^(I6-1)*(1+Supuestos!$C$48)+IF(Supuestos!$C$50*(1+Supuestos!$C$39)^(I6-1)<=2*Supuestos!$C$37*(1+Supuestos!$C$39)^(I6-1),Supuestos!$C$38*(1+Supuestos!$C$39)^(I6-1)*(1+Supuestos!$C$49),0) -> 3060125.2 | J33: =Supuestos!$C$50*(1+Supuestos!$C$39)^(J6-1)*(1+Supuestos!$C$48)+IF(Supuestos!$C$50*(1+Supuestos!$C$39)^(J6-1)<=2*Supuestos!$C$37*(1+Supuestos!$C$39)^(J6-1),Supuestos!$C$38*(1+Supuestos!$C$39)^(J6-1)*(1+Supuestos!$C$49),0) -> 3060125.2 | ... BJ33: =Supuestos!$C$50*(1+Supuestos!$C$39)^(BJ6-1)*(1+Supuestos!$C$48)+IF(Supuestos!$C$50*(1+Supuestos!$C$39)^(BJ6-1)<=2*Supuestos!$C$37*(1+Supuestos!$C$39)^(BJ6-1),Supuestos!$C$38*(1+Supuestos!$C$39)^(BJ6-1)*(1+Supuestos!$C$49),0) -> 3719601.3
A34: Nómina de colaboradores | B34: COP | C34: =C32*C33 -> 0 | D34: =D32*D33 -> 0 | E34: =E32*E33 -> 0 | F34: =F32*F33 -> 0 | G34: =G32*G33 -> 0 | H34: =H32*H33 -> 0 | I34: =I32*I33 -> 0 | J34: =J32*J33 -> 0 | ... BJ34: =BJ32*BJ33 -> 3719601.3
A35: Fundadores con salario | B35: personas | C35: =IF(C5>=INDEX(Supuestos!$C$18:$E$18,1,$B$2),Supuestos!$C$51,0) -> 0 | D35: =IF(D5>=INDEX(Supuestos!$C$18:$E$18,1,$B$2),Supuestos!$C$51,0) -> 0 | E35: =IF(E5>=INDEX(Supuestos!$C$18:$E$18,1,$B$2),Supuestos!$C$51,0) -> 0 | F35: =IF(F5>=INDEX(Supuestos!$C$18:$E$18,1,$B$2),Supuestos!$C$51,0) -> 0 | G35: =IF(G5>=INDEX(Supuestos!$C$18:$E$18,1,$B$2),Supuestos!$C$51,0) -> 0 | H35: =IF(H5>=INDEX(Supuestos!$C$18:$E$18,1,$B$2),Supuestos!$C$51,0) -> 0 | I35: =IF(I5>=INDEX(Supuestos!$C$18:$E$18,1,$B$2),Supuestos!$C$51,0) -> 0 | J35: =IF(J5>=INDEX(Supuestos!$C$18:$E$18,1,$B$2),Supuestos!$C$51,0) -> 0 | ... BJ35: =IF(BJ5>=INDEX(Supuestos!$C$18:$E$18,1,$B$2),Supuestos!$C$51,0) -> 3
A36: Costo total mensual por fundador | B36: COP | C36: =Supuestos!$C$52*(1+Supuestos!$C$39)^(C6-1)*(1+Supuestos!$C$48)+IF(Supuestos!$C$52*(1+Supuestos!$C$39)^(C6-1)<=2*Supuestos!$C$37*(1+Supuestos!$C$39)^(C6-1),Supuestos!$C$38*(1+Supuestos!$C$39)^(C6-1)*(1+Supuestos!$C$49),0) -> 4443645.2 | D36: =Supuestos!$C$52*(1+Supuestos!$C$39)^(D6-1)*(1+Supuestos!$C$48)+IF(Supuestos!$C$52*(1+Supuestos!$C$39)^(D6-1)<=2*Supuestos!$C$37*(1+Supuestos!$C$39)^(D6-1),Supuestos!$C$38*(1+Supuestos!$C$39)^(D6-1)*(1+Supuestos!$C$49),0) -> 4443645.2 | E36: =Supuestos!$C$52*(1+Supuestos!$C$39)^(E6-1)*(1+Supuestos!$C$48)+IF(Supuestos!$C$52*(1+Supuestos!$C$39)^(E6-1)<=2*Supuestos!$C$37*(1+Supuestos!$C$39)^(E6-1),Supuestos!$C$38*(1+Supuestos!$C$39)^(E6-1)*(1+Supuestos!$C$49),0) -> 4443645.2 | F36: =Supuestos!$C$52*(1+Supuestos!$C$39)^(F6-1)*(1+Supuestos!$C$48)+IF(Supuestos!$C$52*(1+Supuestos!$C$39)^(F6-1)<=2*Supuestos!$C$37*(1+Supuestos!$C$39)^(F6-1),Supuestos!$C$38*(1+Supuestos!$C$39)^(F6-1)*(1+Supuestos!$C$49),0) -> 4443645.2 | G36: =Supuestos!$C$52*(1+Supuestos!$C$39)^(G6-1)*(1+Supuestos!$C$48)+IF(Supuestos!$C$52*(1+Supuestos!$C$39)^(G6-1)<=2*Supuestos!$C$37*(1+Supuestos!$C$39)^(G6-1),Supuestos!$C$38*(1+Supuestos!$C$39)^(G6-1)*(1+Supuestos!$C$49),0) -> 4443645.2 | H36: =Supuestos!$C$52*(1+Supuestos!$C$39)^(H6-1)*(1+Supuestos!$C$48)+IF(Supuestos!$C$52*(1+Supuestos!$C$39)^(H6-1)<=2*Supuestos!$C$37*(1+Supuestos!$C$39)^(H6-1),Supuestos!$C$38*(1+Supuestos!$C$39)^(H6-1)*(1+Supuestos!$C$49),0) -> 4443645.2 | I36: =Supuestos!$C$52*(1+Supuestos!$C$39)^(I6-1)*(1+Supuestos!$C$48)+IF(Supuestos!$C$52*(1+Supuestos!$C$39)^(I6-1)<=2*Supuestos!$C$37*(1+Supuestos!$C$39)^(I6-1),Supuestos!$C$38*(1+Supuestos!$C$39)^(I6-1)*(1+Supuestos!$C$49),0) -> 4443645.2 | J36: =Supuestos!$C$52*(1+Supuestos!$C$39)^(J6-1)*(1+Supuestos!$C$48)+IF(Supuestos!$C$52*(1+Supuestos!$C$39)^(J6-1)<=2*Supuestos!$C$37*(1+Supuestos!$C$39)^(J6-1),Supuestos!$C$38*(1+Supuestos!$C$39)^(J6-1)*(1+Supuestos!$C$49),0) -> 4443645.2 | ... BJ36: =Supuestos!$C$52*(1+Supuestos!$C$39)^(BJ6-1)*(1+Supuestos!$C$48)+IF(Supuestos!$C$52*(1+Supuestos!$C$39)^(BJ6-1)<=2*Supuestos!$C$37*(1+Supuestos!$C$39)^(BJ6-1),Supuestos!$C$38*(1+Supuestos!$C$39)^(BJ6-1)*(1+Supuestos!$C$49),0) -> 5401278.5
A37: Nómina de fundadores | B37: COP | C37: =C35*C36 -> 0 | D37: =D35*D36 -> 0 | E37: =E35*E36 -> 0 | F37: =F35*F36 -> 0 | G37: =G35*G36 -> 0 | H37: =H35*H36 -> 0 | I37: =I35*I36 -> 0 | J37: =J35*J36 -> 0 | ... BJ37: =BJ35*BJ36 -> 16203835
A38: Personas en el equipo (fundadores + colaboradores) | B38: personas | C38: =Supuestos!$C$51+C32 -> 3 | D38: =Supuestos!$C$51+D32 -> 3 | E38: =Supuestos!$C$51+E32 -> 3 | F38: =Supuestos!$C$51+F32 -> 3 | G38: =Supuestos!$C$51+G32 -> 3 | H38: =Supuestos!$C$51+H32 -> 3 | I38: =Supuestos!$C$51+I32 -> 3 | J38: =Supuestos!$C$51+J32 -> 3 | ... BJ38: =Supuestos!$C$51+BJ32 -> 4
A40: Gastos operativos
A41: Nómina total | B41: COP | C41: =C34+C37 -> 0 | D41: =D34+D37 -> 0 | E41: =E34+E37 -> 0 | F41: =F34+F37 -> 0 | G41: =G34+G37 -> 0 | H41: =H34+H37 -> 0 | I41: =I34+I37 -> 0 | J41: =J34+J37 -> 0 | ... BJ41: =BJ34+BJ37 -> 19923437
A42: Marketing y adquisición de clientes | B42: COP | C42: =C13*INDEX(Supuestos!$C$17:$E$17,1,$B$2)*(1+Supuestos!$C$39)^(C6-1) -> 499800 | D42: =D13*INDEX(Supuestos!$C$17:$E$17,1,$B$2)*(1+Supuestos!$C$39)^(D6-1) -> 275190 | E42: =E13*INDEX(Supuestos!$C$17:$E$17,1,$B$2)*(1+Supuestos!$C$39)^(E6-1) -> 537300 | F42: =F13*INDEX(Supuestos!$C$17:$E$17,1,$B$2)*(1+Supuestos!$C$39)^(F6-1) -> 562890 | G42: =G13*INDEX(Supuestos!$C$17:$E$17,1,$B$2)*(1+Supuestos!$C$39)^(G6-1) -> 587310 | H42: =H13*INDEX(Supuestos!$C$17:$E$17,1,$B$2)*(1+Supuestos!$C$39)^(H6-1) -> 612300 | I42: =I13*INDEX(Supuestos!$C$17:$E$17,1,$B$2)*(1+Supuestos!$C$39)^(I6-1) -> 637890 | J42: =J13*INDEX(Supuestos!$C$17:$E$17,1,$B$2)*(1+Supuestos!$C$39)^(J6-1) -> 912510 | ... BJ42: =BJ13*INDEX(Supuestos!$C$17:$E$17,1,$B$2)*(1+Supuestos!$C$39)^(BJ6-1) -> 5089932.4
A43: Arriendo de coworking | B43: COP | C43: =IF(C5>=Supuestos!$C$65,Supuestos!$C$64*(1+Supuestos!$C$39)^(C6-1),0) -> 0 | D43: =IF(D5>=Supuestos!$C$65,Supuestos!$C$64*(1+Supuestos!$C$39)^(D6-1),0) -> 0 | E43: =IF(E5>=Supuestos!$C$65,Supuestos!$C$64*(1+Supuestos!$C$39)^(E6-1),0) -> 0 | F43: =IF(F5>=Supuestos!$C$65,Supuestos!$C$64*(1+Supuestos!$C$39)^(F6-1),0) -> 0 | G43: =IF(G5>=Supuestos!$C$65,Supuestos!$C$64*(1+Supuestos!$C$39)^(G6-1),0) -> 0 | H43: =IF(H5>=Supuestos!$C$65,Supuestos!$C$64*(1+Supuestos!$C$39)^(H6-1),0) -> 0 | I43: =IF(I5>=Supuestos!$C$65,Supuestos!$C$64*(1+Supuestos!$C$39)^(I6-1),0) -> 0 | J43: =IF(J5>=Supuestos!$C$65,Supuestos!$C$64*(1+Supuestos!$C$39)^(J6-1),0) -> 0 | ... BJ43: =IF(BJ5>=Supuestos!$C$65,Supuestos!$C$64*(1+Supuestos!$C$39)^(BJ6-1),0) -> 607753.12
A44: Gastos administrativos y legales | B44: COP | C44: =IF(C6=1,Supuestos!$C$66,Supuestos!$C$67*(1+Supuestos!$C$39)^(C6-2)) -> 200000 | D44: =IF(D6=1,Supuestos!$C$66,Supuestos!$C$67*(1+Supuestos!$C$39)^(D6-2)) -> 200000 | E44: =IF(E6=1,Supuestos!$C$66,Supuestos!$C$67*(1+Supuestos!$C$39)^(E6-2)) -> 200000 | F44: =IF(F6=1,Supuestos!$C$66,Supuestos!$C$67*(1+Supuestos!$C$39)^(F6-2)) -> 200000 | G44: =IF(G6=1,Supuestos!$C$66,Supuestos!$C$67*(1+Supuestos!$C$39)^(G6-2)) -> 200000 | H44: =IF(H6=1,Supuestos!$C$66,Supuestos!$C$67*(1+Supuestos!$C$39)^(H6-2)) -> 200000 | I44: =IF(I6=1,Supuestos!$C$66,Supuestos!$C$67*(1+Supuestos!$C$39)^(I6-2)) -> 200000 | J44: =IF(J6=1,Supuestos!$C$66,Supuestos!$C$67*(1+Supuestos!$C$39)^(J6-2)) -> 200000 | ... BJ44: =IF(BJ6=1,Supuestos!$C$66,Supuestos!$C$67*(1+Supuestos!$C$39)^(BJ6-2)) -> 463050
A45: Software, herramientas, dominio y SSL | B45: COP | C45: =(Supuestos!$C$68+Supuestos!$C$69)*(1+Supuestos!$C$39)^(C6-1) -> 110000 | D45: =(Supuestos!$C$68+Supuestos!$C$69)*(1+Supuestos!$C$39)^(D6-1) -> 110000 | E45: =(Supuestos!$C$68+Supuestos!$C$69)*(1+Supuestos!$C$39)^(E6-1) -> 110000 | F45: =(Supuestos!$C$68+Supuestos!$C$69)*(1+Supuestos!$C$39)^(F6-1) -> 110000 | G45: =(Supuestos!$C$68+Supuestos!$C$69)*(1+Supuestos!$C$39)^(G6-1) -> 110000 | H45: =(Supuestos!$C$68+Supuestos!$C$69)*(1+Supuestos!$C$39)^(H6-1) -> 110000 | I45: =(Supuestos!$C$68+Supuestos!$C$69)*(1+Supuestos!$C$39)^(I6-1) -> 110000 | J45: =(Supuestos!$C$68+Supuestos!$C$69)*(1+Supuestos!$C$39)^(J6-1) -> 110000 | ... BJ45: =(Supuestos!$C$68+Supuestos!$C$69)*(1+Supuestos!$C$39)^(BJ6-1) -> 133705.69
A46: Total gastos operativos | B46: COP | C46: =SUM(C41:C45)+C91 -> 980344.98 | D46: =SUM(D41:D45)+D91 -> 755734.98 | E46: =SUM(E41:E45)+E91 -> 1017845 | F46: =SUM(F41:F45)+F91 -> 1043435 | G46: =SUM(G41:G45)+G91 -> 1067855 | H46: =SUM(H41:H45)+H91 -> 1092845 | I46: =SUM(I41:I45)+I91 -> 1118435 | J46: =SUM(J41:J45)+J91 -> 1393055 | ... BJ46: =SUM(BJ41:BJ45)+BJ91 -> 26369816
A47: Resultado operativo (EBITDA) | B47: COP | C47: =C23-C46 -> -1013154.9 | D47: =D23-D46 -> -694837.48 | E47: =E23-E46 -> -769757.39 | F47: =F23-F46 -> -607932.57 | G47: =G23-G46 -> -445162.48 | H47: =H23-H46 -> -282962.39 | I47: =I23-I46 -> -121137.57 | J47: =J23-J46 -> -114860.07 | ... BJ47: =BJ23-BJ46 -> 494797.1
A48: Caja acumulada antes de impuestos (incluye inversión inicial) | B48: COP | C48: =-(Supuestos!$C$71+Supuestos!$C$72+Supuestos!$C$73)+C47 -> -2513154.9 | D48: =C48+D47 -> -3207992.4 | E48: =D48+E47 -> -3977749.8 | F48: =E48+F47 -> -4585682.3 | G48: =F48+G47 -> -5030844.8 | H48: =G48+H47 -> -5313807.2 | I48: =H48+I47 -> -5434944.8 | J48: =I48+J47 -> -5549804.8 | K48: =J48+K47 -> -5264774.8 | ... BJ48: =BI48+BJ47 -> 16565211
A49: Memo: valor del trabajo no remunerado de los fundadores | B49: COP | C49: =(Supuestos!$C$51-C35)*C36*C31/Supuestos!$C$51/160 -> 6665467.8 | D49: =(Supuestos!$C$51-D35)*D36*D31/Supuestos!$C$51/160 -> 6665467.8 | E49: =(Supuestos!$C$51-E35)*E36*E31/Supuestos!$C$51/160 -> 6665467.8 | F49: =(Supuestos!$C$51-F35)*F36*F31/Supuestos!$C$51/160 -> 6665467.8 | G49: =(Supuestos!$C$51-G35)*G36*G31/Supuestos!$C$51/160 -> 6665467.8 | H49: =(Supuestos!$C$51-H35)*H36*H31/Supuestos!$C$51/160 -> 6665467.8 | I49: =(Supuestos!$C$51-I35)*I36*I31/Supuestos!$C$51/160 -> 6665467.8 | J49: =(Supuestos!$C$51-J35)*J36*J31/Supuestos!$C$51/160 -> 6665467.8 | ... BJ49: =(Supuestos!$C$51-BJ35)*BJ36*BJ31/Supuestos!$C$51/160 -> 0
A51: Resumen anual (millones de COP salvo indicación)
A52: Concepto | B52: Año 0 | C52: Año 1 | D52: Año 2 | E52: Año 3 | F52: Año 4 | G52: Año 5
A53: Clientes activos al cierre (número) | C53: =INDEX($C$14:$BJ$14,1,12) -> 60 | D53: =INDEX($C$14:$BJ$14,1,24) -> 150 | E53: =INDEX($C$14:$BJ$14,1,36) -> 300 | F53: =INDEX($C$14:$BJ$14,1,48) -> 450 | G53: =INDEX($C$14:$BJ$14,1,60) -> 600
A54: Clientes nuevos en el año (número) | C54: =SUMIF($C$6:$BJ$6,1,$C$13:$BJ$13) -> 75.75 | D54: =SUMIF($C$6:$BJ$6,2,$C$13:$BJ$13) -> 150.75 | E54: =SUMIF($C$6:$BJ$6,3,$C$13:$BJ$13) -> 281.25 | F54: =SUMIF($C$6:$BJ$6,4,$C$13:$BJ$13) -> 371.25 | G54: =SUMIF($C$6:$BJ$6,5,$C$13:$BJ$13) -> 461.25
A55: Clientes retirados en el año (número) | C55: =SUMIF($C$6:$BJ$6,1,$C$12:$BJ$12) -> 15.75 | D55: =SUMIF($C$6:$BJ$6,2,$C$12:$BJ$12) -> 60.75 | E55: =SUMIF($C$6:$BJ$6,3,$C$12:$BJ$12) -> 131.25 | F55: =SUMIF($C$6:$BJ$6,4,$C$12:$BJ$12) -> 221.25 | G55: =SUMIF($C$6:$BJ$6,5,$C$12:$BJ$12) -> 311.25
A56: Precio mensual (COP) | C56: =INDEX($C$17:$BJ$17,1,12) -> 39900 | D56: =INDEX($C$17:$BJ$17,1,24) -> 41895 | E56: =INDEX($C$17:$BJ$17,1,36) -> 43989.75 | F56: =INDEX($C$17:$BJ$17,1,48) -> 46189.238 | G56: =INDEX($C$17:$BJ$17,1,60) -> 48498.699
A57: Ingresos | C57: =SUMIF($C$6:$BJ$6,1,$C$18:$BJ$18)/1000000 -> 14.9625 | D57: =SUMIF($C$6:$BJ$6,2,$C$18:$BJ$18)/1000000 -> 54.672975 | E57: =SUMIF($C$6:$BJ$6,3,$C$18:$BJ$18)/1000000 -> 122.07156 | F57: =SUMIF($C$6:$BJ$6,4,$C$18:$BJ$18)/1000000 -> 211.31576 | G57: =SUMIF($C$6:$BJ$6,5,$C$18:$BJ$18)/1000000 -> 309.17921
A58: Costos de operación del servicio (IA, pasarela, nube) | C58: =SUMIF($C$6:$BJ$6,1,$C$22:$BJ$22)/1000000 -> 3.557625 | D58: =SUMIF($C$6:$BJ$6,2,$C$22:$BJ$22)/1000000 -> 5.9930018 | E58: =SUMIF($C$6:$BJ$6,3,$C$22:$BJ$22)/1000000 -> 10.126444 | F58: =SUMIF($C$6:$BJ$6,4,$C$22:$BJ$22)/1000000 -> 18.359641 | G58: =SUMIF($C$6:$BJ$6,5,$C$22:$BJ$22)/1000000 -> 24.361442
A59: Margen bruto | C59: =C57-C58 -> 11.404875 | D59: =D57-D58 -> 48.679973 | E59: =E57-E58 -> 111.94511 | F59: =F57-F58 -> 192.95612 | G59: =G57-G58 -> 284.81777
A60: Margen bruto (%) | C60: =IF(C57=0,0,C59/C57) -> 0.76223058 | D60: =IF(D57=0,0,D59/D57) -> 0.89038457 | E60: =IF(E57=0,0,E59/E57) -> 0.91704502 | F60: =IF(F57=0,0,F59/F57) -> 0.9131175 | G60: =IF(G57=0,0,G59/G57) -> 0.92120608
A61: Nómina de colaboradores | C61: =SUMIF($C$6:$BJ$6,1,$C$34:$BJ$34)/1000000 -> 0 | D61: =SUMIF($C$6:$BJ$6,2,$C$34:$BJ$34)/1000000 -> 0 | E61: =SUMIF($C$6:$BJ$6,3,$C$34:$BJ$34)/1000000 -> 0 | F61: =SUMIF($C$6:$BJ$6,4,$C$34:$BJ$34)/1000000 -> 0 | G61: =SUMIF($C$6:$BJ$6,5,$C$34:$BJ$34)/1000000 -> 33.476412
A62: Nómina de fundadores | C62: =SUMIF($C$6:$BJ$6,1,$C$37:$BJ$37)/1000000 -> 0 | D62: =SUMIF($C$6:$BJ$6,2,$C$37:$BJ$37)/1000000 -> 0 | E62: =SUMIF($C$6:$BJ$6,3,$C$37:$BJ$37)/1000000 -> 0 | F62: =SUMIF($C$6:$BJ$6,4,$C$37:$BJ$37)/1000000 -> 185.18669 | G62: =SUMIF($C$6:$BJ$6,5,$C$37:$BJ$37)/1000000 -> 194.44603
A63: Marketing y adquisición | C63: =SUMIF($C$6:$BJ$6,1,$C$42:$BJ$42)/1000000 -> 7.575 | D63: =SUMIF($C$6:$BJ$6,2,$C$42:$BJ$42)/1000000 -> 15.82875 | E63: =SUMIF($C$6:$BJ$6,3,$C$42:$BJ$42)/1000000 -> 31.007812 | F63: =SUMIF($C$6:$BJ$6,4,$C$42:$BJ$42)/1000000 -> 42.976828 | G63: =SUMIF($C$6:$BJ$6,5,$C$42:$BJ$42)/1000000 -> 56.065226
A64: Arriendo, administración, software, equipos y trabajo desde casa | C64: =(SUMIF($C$6:$BJ$6,1,$C$43:$BJ$43)+SUMIF($C$6:$BJ$6,1,$C$44:$BJ$44)+SUMIF($C$6:$BJ$6,1,$C$45:$BJ$45)+SUMIF($C$6:$BJ$6,1,$C$91:$BJ$91))/1000000 -> 5.7665398 | D64: =(SUMIF($C$6:$BJ$6,2,$C$43:$BJ$43)+SUMIF($C$6:$BJ$6,2,$C$44:$BJ$44)+SUMIF($C$6:$BJ$6,2,$C$45:$BJ$45)+SUMIF($C$6:$BJ$6,2,$C$91:$BJ$91))/1000000 -> 8.6218001 | E64: =(SUMIF($C$6:$BJ$6,3,$C$43:$BJ$43)+SUMIF($C$6:$BJ$6,3,$C$44:$BJ$44)+SUMIF($C$6:$BJ$6,3,$C$45:$BJ$45)+SUMIF($C$6:$BJ$6,3,$C$91:$BJ$91))/1000000 -> 15.96917 | F64: =(SUMIF($C$6:$BJ$6,4,$C$43:$BJ$43)+SUMIF($C$6:$BJ$6,4,$C$44:$BJ$44)+SUMIF($C$6:$BJ$6,4,$C$45:$BJ$45)+SUMIF($C$6:$BJ$6,4,$C$91:$BJ$91))/1000000 -> 15.502253 | G64: =(SUMIF($C$6:$BJ$6,5,$C$43:$BJ$43)+SUMIF($C$6:$BJ$6,5,$C$44:$BJ$44)+SUMIF($C$6:$BJ$6,5,$C$45:$BJ$45)+SUMIF($C$6:$BJ$6,5,$C$91:$BJ$91))/1000000 -> 19.316131
A65: Total gastos operativos | C65: =SUMIF($C$6:$BJ$6,1,$C$46:$BJ$46)/1000000 -> 13.34154 | D65: =SUMIF($C$6:$BJ$6,2,$C$46:$BJ$46)/1000000 -> 24.45055 | E65: =SUMIF($C$6:$BJ$6,3,$C$46:$BJ$46)/1000000 -> 46.976983 | F65: =SUMIF($C$6:$BJ$6,4,$C$46:$BJ$46)/1000000 -> 243.66577 | G65: =SUMIF($C$6:$BJ$6,5,$C$46:$BJ$46)/1000000 -> 303.30379
A66: Resultado operativo (EBITDA) | C66: =C59-C65 -> -1.9366648 | D66: =D59-D65 -> 24.229423 | E66: =E59-E65 -> 64.96813 | F66: =F59-F65 -> -50.709651 | G66: =G59-G65 -> -18.486027
A67: Pérdidas acumuladas por compensar al inicio | C67: =0 -> 0 | D67: =MIN(0,C67+C66) -> -1.9366648 | E67: =MIN(0,D67+D66) -> 0 | F67: =MIN(0,E67+E66) -> 0 | G67: =MIN(0,F67+F66) -> -50.709651
A68: Base gravable | C68: =MAX(0,C66+C67) -> 0 | D68: =MAX(0,D66+D67) -> 22.292758 | E68: =MAX(0,E66+E67) -> 64.96813 | F68: =MAX(0,F66+F67) -> 0 | G68: =MAX(0,G66+G67) -> 0
A69: Impuesto de renta | C69: =C68*Supuestos!$C$74 -> 0 | D69: =D68*Supuestos!$C$74 -> 7.8024654 | E69: =E68*Supuestos!$C$74 -> 22.738846 | F69: =F68*Supuestos!$C$74 -> 0 | G69: =G68*Supuestos!$C$74 -> 0
A70: Utilidad neta | C70: =C66-C69 -> -1.9366648 | D70: =D66-D69 -> 16.426958 | E70: =E66-E69 -> 42.229285 | F70: =F66-F69 -> -50.709651 | G70: =G66-G69 -> -18.486027
A71: Flujo de caja neto | B71: =-(Supuestos!$C$71+Supuestos!$C$72+Supuestos!$C$73)/1000000 -> -1.5 | C71: =C70 -> -1.9366648 | D71: =D70 -> 16.426958 | E71: =E70 -> 42.229285 | F71: =F70 -> -50.709651 | G71: =G70 -> -18.486027
A72: Flujo de caja acumulado | B72: =B71 -> -1.5 | C72: =B72+C71 -> -3.4366648 | D72: =C72+D71 -> 12.990293 | E72: =D72+E71 -> 55.219577 | F72: =E72+F71 -> 4.5099266 | G72: =F72+G71 -> -13.9761
A73: ¿Recuperó la inversión? (1 = sí) | C73: =IF(C72>=0,1,0) -> 0 | D73: =IF(D72>=0,1,0) -> 1 | E73: =IF(E72>=0,1,0) -> 1 | F73: =IF(F72>=0,1,0) -> 1 | G73: =IF(G72>=0,1,0) -> 0
A74: Memo: trabajo no remunerado de los fundadores (aporte en especie) | C74: =SUMIF($C$6:$BJ$6,1,$C$49:$BJ$49)/1000000 -> 79.985613 | D74: =SUMIF($C$6:$BJ$6,2,$C$49:$BJ$49)/1000000 -> 125.97734 | E74: =SUMIF($C$6:$BJ$6,3,$C$49:$BJ$49)/1000000 -> 176.36828 | F74: =SUMIF($C$6:$BJ$6,4,$C$49:$BJ$49)/1000000 -> 0 | G74: =SUMIF($C$6:$BJ$6,5,$C$49:$BJ$49)/1000000 -> 0
A75: Personas en el equipo al cierre | C75: =INDEX($C$38:$BJ$38,1,12) -> 3 | D75: =INDEX($C$38:$BJ$38,1,24) -> 3 | E75: =INDEX($C$38:$BJ$38,1,36) -> 3 | F75: =INDEX($C$38:$BJ$38,1,48) -> 3 | G75: =INDEX($C$38:$BJ$38,1,60) -> 4
A76: Ingreso anual por persona del equipo | C76: =IF(C75=0,0,C57/C75) -> 4.9875 | D76: =IF(D75=0,0,D57/D75) -> 18.224325 | E76: =IF(E75=0,0,E57/E75) -> 40.690519 | F76: =IF(F75=0,0,F57/F75) -> 70.438587 | G76: =IF(G75=0,0,G57/G75) -> 77.294802
A77: Punto de equilibrio (clientes activos necesarios, promedio mensual del año) | C77: =ROUNDUP((SUMIF($C$6:$BJ$6,1,$C$46:$BJ$46)+SUMIF($C$6:$BJ$6,1,$C$21:$BJ$21))/12/(INDEX($C$17:$BJ$17,1,12)*(1-Supuestos!$C$30)-Supuestos!$C$29*(1+Supuestos!$C$39)^(1-1)),0) -> 36 | D77: =ROUNDUP((SUMIF($C$6:$BJ$6,2,$C$46:$BJ$46)+SUMIF($C$6:$BJ$6,2,$C$21:$BJ$21))/12/(INDEX($C$17:$BJ$17,1,24)*(1-Supuestos!$C$30)-Supuestos!$C$29*(1+Supuestos!$C$39)^(2-1)),0) -> 58 | E77: =ROUNDUP((SUMIF($C$6:$BJ$6,3,$C$46:$BJ$46)+SUMIF($C$6:$BJ$6,3,$C$21:$BJ$21))/12/(INDEX($C$17:$BJ$17,1,36)*(1-Supuestos!$C$30)-Supuestos!$C$29*(1+Supuestos!$C$39)^(3-1)),0) -> 101 | F77: =ROUNDUP((SUMIF($C$6:$BJ$6,4,$C$46:$BJ$46)+SUMIF($C$6:$BJ$6,4,$C$21:$BJ$21))/12/(INDEX($C$17:$BJ$17,1,48)*(1-Supuestos!$C$30)-Supuestos!$C$29*(1+Supuestos!$C$39)^(4-1)),0) -> 479 | G77: =ROUNDUP((SUMIF($C$6:$BJ$6,5,$C$46:$BJ$46)+SUMIF($C$6:$BJ$6,5,$C$21:$BJ$21))/12/(INDEX($C$17:$BJ$17,1,60)*(1-Supuestos!$C$30)-Supuestos!$C$29*(1+Supuestos!$C$39)^(5-1)),0) -> 566
A79: Indicadores de evaluación
A80: VPN a la TIO (millones COP) | C80: =B71+NPV(Supuestos!$C$75,C71:G71) -> 0.84796043
A81: TIR | C81: =IFERROR(IRR(B71:G71),"No existe") -> 0.17689002
A82: Año de recuperación de la inversión | C82: =IFERROR(MATCH(1,C73:G73,0),"Más de 5 años") -> 2
A83: Necesidad máxima de caja (millones COP) | C83: =-MIN(0,MIN($C$48:$BJ$48))/1000000 -> 5.5498048
A84: Primer mes con resultado operativo positivo | C84: =IFERROR(MATCH(TRUE(),INDEX($C$47:$BJ$47>0,0),0),"No ocurre en 5 años") -> 9
A86: Trabajo desde casa y equipos
A87: Fundadores trabajando sin salario desde casa | B87: personas | C87: =Supuestos!$C$51-C35 -> 3 | D87: =Supuestos!$C$51-D35 -> 3 | E87: =Supuestos!$C$51-E35 -> 3 | F87: =Supuestos!$C$51-F35 -> 3 | G87: =Supuestos!$C$51-G35 -> 3 | H87: =Supuestos!$C$51-H35 -> 3 | I87: =Supuestos!$C$51-I35 -> 3 | J87: =Supuestos!$C$51-J35 -> 3 | ... BJ87: =Supuestos!$C$51-BJ35 -> 0
A88: Energía e internet del hogar (se reembolsan mientras no hay salario) | B88: COP | C88: =C87*(Supuestos!$C$84/1000*(C31/Supuestos!$C$51)*Supuestos!$C$83+Supuestos!$C$85*MIN(1,(C31/Supuestos!$C$51)/Supuestos!$C$86))*(1+Supuestos!$C$39)^(C6-1) -> 45544.98 | D88: =D87*(Supuestos!$C$84/1000*(D31/Supuestos!$C$51)*Supuestos!$C$83+Supuestos!$C$85*MIN(1,(D31/Supuestos!$C$51)/Supuestos!$C$86))*(1+Supuestos!$C$39)^(D6-1) -> 45544.98 | E88: =E87*(Supuestos!$C$84/1000*(E31/Supuestos!$C$51)*Supuestos!$C$83+Supuestos!$C$85*MIN(1,(E31/Supuestos!$C$51)/Supuestos!$C$86))*(1+Supuestos!$C$39)^(E6-1) -> 45544.98 | F88: =F87*(Supuestos!$C$84/1000*(F31/Supuestos!$C$51)*Supuestos!$C$83+Supuestos!$C$85*MIN(1,(F31/Supuestos!$C$51)/Supuestos!$C$86))*(1+Supuestos!$C$39)^(F6-1) -> 45544.98 | G88: =G87*(Supuestos!$C$84/1000*(G31/Supuestos!$C$51)*Supuestos!$C$83+Supuestos!$C$85*MIN(1,(G31/Supuestos!$C$51)/Supuestos!$C$86))*(1+Supuestos!$C$39)^(G6-1) -> 45544.98 | H88: =H87*(Supuestos!$C$84/1000*(H31/Supuestos!$C$51)*Supuestos!$C$83+Supuestos!$C$85*MIN(1,(H31/Supuestos!$C$51)/Supuestos!$C$86))*(1+Supuestos!$C$39)^(H6-1) -> 45544.98 | I88: =I87*(Supuestos!$C$84/1000*(I31/Supuestos!$C$51)*Supuestos!$C$83+Supuestos!$C$85*MIN(1,(I31/Supuestos!$C$51)/Supuestos!$C$86))*(1+Supuestos!$C$39)^(I6-1) -> 45544.98 | J88: =J87*(Supuestos!$C$84/1000*(J31/Supuestos!$C$51)*Supuestos!$C$83+Supuestos!$C$85*MIN(1,(J31/Supuestos!$C$51)/Supuestos!$C$86))*(1+Supuestos!$C$39)^(J6-1) -> 45544.98 | ... BJ88: =BJ87*(Supuestos!$C$84/1000*(BJ31/Supuestos!$C$51)*Supuestos!$C$83+Supuestos!$C$85*MIN(1,(BJ31/Supuestos!$C$51)/Supuestos!$C$86))*(1+Supuestos!$C$39)^(BJ6-1) -> 0
A89: Reserva de reposición de los portátiles de los fundadores | B89: COP | C89: =Supuestos!$C$51*Supuestos!$C$87/Supuestos!$C$88*(1+Supuestos!$C$39)^(C6-1) -> 125000 | D89: =Supuestos!$C$51*Supuestos!$C$87/Supuestos!$C$88*(1+Supuestos!$C$39)^(D6-1) -> 125000 | E89: =Supuestos!$C$51*Supuestos!$C$87/Supuestos!$C$88*(1+Supuestos!$C$39)^(E6-1) -> 125000 | F89: =Supuestos!$C$51*Supuestos!$C$87/Supuestos!$C$88*(1+Supuestos!$C$39)^(F6-1) -> 125000 | G89: =Supuestos!$C$51*Supuestos!$C$87/Supuestos!$C$88*(1+Supuestos!$C$39)^(G6-1) -> 125000 | H89: =Supuestos!$C$51*Supuestos!$C$87/Supuestos!$C$88*(1+Supuestos!$C$39)^(H6-1) -> 125000 | I89: =Supuestos!$C$51*Supuestos!$C$87/Supuestos!$C$88*(1+Supuestos!$C$39)^(I6-1) -> 125000 | J89: =Supuestos!$C$51*Supuestos!$C$87/Supuestos!$C$88*(1+Supuestos!$C$39)^(J6-1) -> 125000 | ... BJ89: =Supuestos!$C$51*Supuestos!$C$87/Supuestos!$C$88*(1+Supuestos!$C$39)^(BJ6-1) -> 151938.28
A90: Portátiles para colaboradores nuevos | B90: COP | C90: =MAX(0,C32)*Supuestos!$C$87*(1+Supuestos!$C$39)^(C6-1) -> 0 | D90: =MAX(0,D32-MAX($C$32:C32))*Supuestos!$C$87*(1+Supuestos!$C$39)^(D6-1) -> 0 | E90: =MAX(0,E32-MAX($C$32:D32))*Supuestos!$C$87*(1+Supuestos!$C$39)^(E6-1) -> 0 | F90: =MAX(0,F32-MAX($C$32:E32))*Supuestos!$C$87*(1+Supuestos!$C$39)^(F6-1) -> 0 | G90: =MAX(0,G32-MAX($C$32:F32))*Supuestos!$C$87*(1+Supuestos!$C$39)^(G6-1) -> 0 | H90: =MAX(0,H32-MAX($C$32:G32))*Supuestos!$C$87*(1+Supuestos!$C$39)^(H6-1) -> 0 | I90: =MAX(0,I32-MAX($C$32:H32))*Supuestos!$C$87*(1+Supuestos!$C$39)^(I6-1) -> 0 | J90: =MAX(0,J32-MAX($C$32:I32))*Supuestos!$C$87*(1+Supuestos!$C$39)^(J6-1) -> 0 | K90: =MAX(0,K32-MAX($C$32:J32))*Supuestos!$C$87*(1+Supuestos!$C$39)^(K6-1) -> 0 | ... BJ90: =MAX(0,BJ32-MAX($C$32:BI32))*Supuestos!$C$87*(1+Supuestos!$C$39)^(BJ6-1) -> 0
A91: Total trabajo desde casa y equipos | B91: COP | C91: =SUM(C88:C90) -> 170544.98 | D91: =SUM(D88:D90) -> 170544.98 | E91: =SUM(E88:E90) -> 170544.98 | F91: =SUM(F88:F90) -> 170544.98 | G91: =SUM(G88:G90) -> 170544.98 | H91: =SUM(H88:H90) -> 170544.98 | I91: =SUM(I88:I90) -> 170544.98 | J91: =SUM(J88:J90) -> 170544.98 | ... BJ91: =SUM(BJ88:BJ90) -> 151938.28
A93: Memo: de lo anterior, trabajo desde casa y equipos (millones COP) | C93: =SUMIF($C$6:$BJ$6,1,$C$91:$BJ$91)/1000000 -> 2.0465398 | D93: =SUMIF($C$6:$BJ$6,2,$C$91:$BJ$91)/1000000 -> 2.4358001 | E93: =SUMIF($C$6:$BJ$6,3,$C$91:$BJ$91)/1000000 -> 2.8588702 | F93: =SUMIF($C$6:$BJ$6,4,$C$91:$BJ$91)/1000000 -> 1.7364375 | G93: =SUMIF($C$6:$BJ$6,5,$C$91:$BJ$91)/1000000 -> 4.862025

Sheet Base
A1: Escenario Base — proyección mensual (60 meses) y anual
A2: Índice del escenario | B2: 2
A3: Todo en esta hoja es fórmula. Para cambiar resultados, edite la hoja Supuestos.
A5: Mes | C5: 1 | D5: 2 | E5: 3 | F5: 4 | G5: 5 | H5: 6 | I5: 7 | J5: 8 | K5: 9 | L5: 10 | M5: 11 | N5: 12 | O5: 13 | P5: 14 | Q5: 15 | R5: 16 | S5: 17 | T5: 18 | U5: 19 | V5: 20 | W5: 21 | X5: 22 | Y5: 23 | Z5: 24 | AA5: 25 | AB5: 26 | AC5: 27 | AD5: 28 | AE5: 29 | AF5: 30 | AG5: 31 | AH5: 32 | AI5: 33 | AJ5: 34 | AK5: 35 | AL5: 36 | AM5: 37 | AN5: 38 | AO5: 39 | AP5: 40 | AQ5: 41 | AR5: 42 | AS5: 43 | AT5: 44 | AU5: 45 | AV5: 46 | AW5: 47 | AX5: 48 | AY5: 49 | AZ5: 50 | BA5: 51 | BB5: 52 | BC5: 53 | BD5: 54 | BE5: 55 | BF5: 56 | BG5: 57 | BH5: 58 | BI5: 59 | BJ5: 60
A6: Año | C6: =ROUNDUP(C5/12,0) -> 1 | D6: =ROUNDUP(D5/12,0) -> 1 | E6: =ROUNDUP(E5/12,0) -> 1 | F6: =ROUNDUP(F5/12,0) -> 1 | G6: =ROUNDUP(G5/12,0) -> 1 | H6: =ROUNDUP(H5/12,0) -> 1 | I6: =ROUNDUP(I5/12,0) -> 1 | J6: =ROUNDUP(J5/12,0) -> 1 | ... BJ6: =ROUNDUP(BJ5/12,0) -> 5
A7: Mes del año | C7: =C5-(C6-1)*12 -> 1 | D7: =D5-(D6-1)*12 -> 2 | E7: =E5-(E6-1)*12 -> 3 | F7: =F5-(F6-1)*12 -> 4 | G7: =G5-(G6-1)*12 -> 5 | H7: =H5-(H6-1)*12 -> 6 | I7: =I5-(I6-1)*12 -> 7 | J7: =J5-(J6-1)*12 -> 8 | ... BJ7: =BJ5-(BJ6-1)*12 -> 12
A9: Clientes
A10: Meta de clientes activos al cierre del mes | B10: clientes | C10: =IF(C6=1,INDEX(Supuestos!$C$22:$N$22,1,C7)*INDEX(Supuestos!$C$11:$E$11,1,$B$2),IF(C6=2,INDEX(Supuestos!$C$11:$E$11,1,$B$2),IF(C6=3,INDEX(Supuestos!$C$12:$E$12,1,$B$2),IF(C6=4,INDEX(Supuestos!$C$13:$E$13,1,$B$2),INDEX(Supuestos!$C$14:$E$14,1,$B$2))))+(IF(C6=2,INDEX(Supuestos!$C$12:$E$12,1,$B$2),IF(C6=3,INDEX(Supuestos!$C$13:$E$13,1,$B$2),IF(C6=4,INDEX(Supuestos!$C$14:$E$14,1,$B$2),INDEX(Supuestos!$C$15:$E$15,1,$B$2))))-IF(C6=2,INDEX(Supuestos!$C$11:$E$11,1,$B$2),IF(C6=3,INDEX(Supuestos!$C$12:$E$12,1,$B$2),IF(C6=4,INDEX(Supuestos!$C$13:$E$13,1,$B$2),INDEX(Supuestos!$C$14:$E$14,1,$B$2)))))*C7/12) -> 9.996 | D10: =IF(D6=1,INDEX(Supuestos!$C$22:$N$22,1,D7)*INDEX(Supuestos!$C$11:$E$11,1,$B$2),IF(D6=2,INDEX(Supuestos!$C$11:$E$11,1,$B$2),IF(D6=3,INDEX(Supuestos!$C$12:$E$12,1,$B$2),IF(D6=4,INDEX(Supuestos!$C$13:$E$13,1,$B$2),INDEX(Supuestos!$C$14:$E$14,1,$B$2))))+(IF(D6=2,INDEX(Supuestos!$C$12:$E$12,1,$B$2),IF(D6=3,INDEX(Supuestos!$C$13:$E$13,1,$B$2),IF(D6=4,INDEX(Supuestos!$C$14:$E$14,1,$B$2),INDEX(Supuestos!$C$15:$E$15,1,$B$2))))-IF(D6=2,INDEX(Supuestos!$C$11:$E$11,1,$B$2),IF(D6=3,INDEX(Supuestos!$C$12:$E$12,1,$B$2),IF(D6=4,INDEX(Supuestos!$C$13:$E$13,1,$B$2),INDEX(Supuestos!$C$14:$E$14,1,$B$2)))))*D7/12) -> 15 | E10: =IF(E6=1,INDEX(Supuestos!$C$22:$N$22,1,E7)*INDEX(Supuestos!$C$11:$E$11,1,$B$2),IF(E6=2,INDEX(Supuestos!$C$11:$E$11,1,$B$2),IF(E6=3,INDEX(Supuestos!$C$12:$E$12,1,$B$2),IF(E6=4,INDEX(Supuestos!$C$13:$E$13,1,$B$2),INDEX(Supuestos!$C$14:$E$14,1,$B$2))))+(IF(E6=2,INDEX(Supuestos!$C$12:$E$12,1,$B$2),IF(E6=3,INDEX(Supuestos!$C$13:$E$13,1,$B$2),IF(E6=4,INDEX(Supuestos!$C$14:$E$14,1,$B$2),INDEX(Supuestos!$C$15:$E$15,1,$B$2))))-IF(E6=2,INDEX(Supuestos!$C$11:$E$11,1,$B$2),IF(E6=3,INDEX(Supuestos!$C$12:$E$12,1,$B$2),IF(E6=4,INDEX(Supuestos!$C$13:$E$13,1,$B$2),INDEX(Supuestos!$C$14:$E$14,1,$B$2)))))*E7/12) -> 24.996 | F10: =IF(F6=1,INDEX(Supuestos!$C$22:$N$22,1,F7)*INDEX(Supuestos!$C$11:$E$11,1,$B$2),IF(F6=2,INDEX(Supuestos!$C$11:$E$11,1,$B$2),IF(F6=3,INDEX(Supuestos!$C$12:$E$12,1,$B$2),IF(F6=4,INDEX(Supuestos!$C$13:$E$13,1,$B$2),INDEX(Supuestos!$C$14:$E$14,1,$B$2))))+(IF(F6=2,INDEX(Supuestos!$C$12:$E$12,1,$B$2),IF(F6=3,INDEX(Supuestos!$C$13:$E$13,1,$B$2),IF(F6=4,INDEX(Supuestos!$C$14:$E$14,1,$B$2),INDEX(Supuestos!$C$15:$E$15,1,$B$2))))-IF(F6=2,INDEX(Supuestos!$C$11:$E$11,1,$B$2),IF(F6=3,INDEX(Supuestos!$C$12:$E$12,1,$B$2),IF(F6=4,INDEX(Supuestos!$C$13:$E$13,1,$B$2),INDEX(Supuestos!$C$14:$E$14,1,$B$2)))))*F7/12) -> 35.004 | G10: =IF(G6=1,INDEX(Supuestos!$C$22:$N$22,1,G7)*INDEX(Supuestos!$C$11:$E$11,1,$B$2),IF(G6=2,INDEX(Supuestos!$C$11:$E$11,1,$B$2),IF(G6=3,INDEX(Supuestos!$C$12:$E$12,1,$B$2),IF(G6=4,INDEX(Supuestos!$C$13:$E$13,1,$B$2),INDEX(Supuestos!$C$14:$E$14,1,$B$2))))+(IF(G6=2,INDEX(Supuestos!$C$12:$E$12,1,$B$2),IF(G6=3,INDEX(Supuestos!$C$13:$E$13,1,$B$2),IF(G6=4,INDEX(Supuestos!$C$14:$E$14,1,$B$2),INDEX(Supuestos!$C$15:$E$15,1,$B$2))))-IF(G6=2,INDEX(Supuestos!$C$11:$E$11,1,$B$2),IF(G6=3,INDEX(Supuestos!$C$12:$E$12,1,$B$2),IF(G6=4,INDEX(Supuestos!$C$13:$E$13,1,$B$2),INDEX(Supuestos!$C$14:$E$14,1,$B$2)))))*G7/12) -> 45 | H10: =IF(H6=1,INDEX(Supuestos!$C$22:$N$22,1,H7)*INDEX(Supuestos!$C$11:$E$11,1,$B$2),IF(H6=2,INDEX(Supuestos!$C$11:$E$11,1,$B$2),IF(H6=3,INDEX(Supuestos!$C$12:$E$12,1,$B$2),IF(H6=4,INDEX(Supuestos!$C$13:$E$13,1,$B$2),INDEX(Supuestos!$C$14:$E$14,1,$B$2))))+(IF(H6=2,INDEX(Supuestos!$C$12:$E$12,1,$B$2),IF(H6=3,INDEX(Supuestos!$C$13:$E$13,1,$B$2),IF(H6=4,INDEX(Supuestos!$C$14:$E$14,1,$B$2),INDEX(Supuestos!$C$15:$E$15,1,$B$2))))-IF(H6=2,INDEX(Supuestos!$C$11:$E$11,1,$B$2),IF(H6=3,INDEX(Supuestos!$C$12:$E$12,1,$B$2),IF(H6=4,INDEX(Supuestos!$C$13:$E$13,1,$B$2),INDEX(Supuestos!$C$14:$E$14,1,$B$2)))))*H7/12) -> 54.996 | I10: =IF(I6=1,INDEX(Supuestos!$C$22:$N$22,1,I7)*INDEX(Supuestos!$C$11:$E$11,1,$B$2),IF(I6=2,INDEX(Supuestos!$C$11:$E$11,1,$B$2),IF(I6=3,INDEX(Supuestos!$C$12:$E$12,1,$B$2),IF(I6=4,INDEX(Supuestos!$C$13:$E$13,1,$B$2),INDEX(Supuestos!$C$14:$E$14,1,$B$2))))+(IF(I6=2,INDEX(Supuestos!$C$12:$E$12,1,$B$2),IF(I6=3,INDEX(Supuestos!$C$13:$E$13,1,$B$2),IF(I6=4,INDEX(Supuestos!$C$14:$E$14,1,$B$2),INDEX(Supuestos!$C$15:$E$15,1,$B$2))))-IF(I6=2,INDEX(Supuestos!$C$11:$E$11,1,$B$2),IF(I6=3,INDEX(Supuestos!$C$12:$E$12,1,$B$2),IF(I6=4,INDEX(Supuestos!$C$13:$E$13,1,$B$2),INDEX(Supuestos!$C$14:$E$14,1,$B$2)))))*I7/12) -> 65.004 | J10: =IF(J6=1,INDEX(Supuestos!$C$22:$N$22,1,J7)*INDEX(Supuestos!$C$11:$E$11,1,$B$2),IF(J6=2,INDEX(Supuestos!$C$11:$E$11,1,$B$2),IF(J6=3,INDEX(Supuestos!$C$12:$E$12,1,$B$2),IF(J6=4,INDEX(Supuestos!$C$13:$E$13,1,$B$2),INDEX(Supuestos!$C$14:$E$14,1,$B$2))))+(IF(J6=2,INDEX(Supuestos!$C$12:$E$12,1,$B$2),IF(J6=3,INDEX(Supuestos!$C$13:$E$13,1,$B$2),IF(J6=4,INDEX(Supuestos!$C$14:$E$14,1,$B$2),INDEX(Supuestos!$C$15:$E$15,1,$B$2))))-IF(J6=2,INDEX(Supuestos!$C$11:$E$11,1,$B$2),IF(J6=3,INDEX(Supuestos!$C$12:$E$12,1,$B$2),IF(J6=4,INDEX(Supuestos!$C$13:$E$13,1,$B$2),INDEX(Supuestos!$C$14:$E$14,1,$B$2)))))*J7/12) -> 80.004 | ... BJ10: =IF(BJ6=1,INDEX(Supuestos!$C$22:$N$22,1,BJ7)*INDEX(Supuestos!$C$11:$E$11,1,$B$2),IF(BJ6=2,INDEX(Supuestos!$C$11:$E$11,1,$B$2),IF(BJ6=3,INDEX(Supuestos!$C$12:$E$12,1,$B$2),IF(BJ6=4,INDEX(Supuestos!$C$13:$E$13,1,$B$2),INDEX(Supuestos!$C$14:$E$14,1,$B$2))))+(IF(BJ6=2,INDEX(Supuestos!$C$12:$E$12,1,$B$2),IF(BJ6=3,INDEX(Supuestos!$C$13:$E$13,1,$B$2),IF(BJ6=4,INDEX(Supuestos!$C$14:$E$14,1,$B$2),INDEX(Supuestos!$C$15:$E$15,1,$B$2))))-IF(BJ6=2,INDEX(Supuestos!$C$11:$E$11,1,$B$2),IF(BJ6=3,INDEX(Supuestos!$C$12:$E$12,1,$B$2),IF(BJ6=4,INDEX(Supuestos!$C$13:$E$13,1,$B$2),INDEX(Supuestos!$C$14:$E$14,1,$B$2)))))*BJ7/12) -> 1200
A11: Clientes al inicio del mes | B11: clientes | C11: 0 | D11: =C14 -> 9.996 | E11: =D14 -> 15 | F11: =E14 -> 24.996 | G11: =F14 -> 35.004 | H11: =G14 -> 45 | I11: =H14 -> 54.996 | J11: =I14 -> 65.004 | K11: =J14 -> 80.004 | ... BJ11: =BI14 -> 1175
A12: Clientes que se retiran | B12: clientes | C12: =C11*INDEX(Supuestos!$C$16:$E$16,1,$B$2) -> 0 | D12: =D11*INDEX(Supuestos!$C$16:$E$16,1,$B$2) -> 0.29988 | E12: =E11*INDEX(Supuestos!$C$16:$E$16,1,$B$2) -> 0.45 | F12: =F11*INDEX(Supuestos!$C$16:$E$16,1,$B$2) -> 0.74988 | G12: =G11*INDEX(Supuestos!$C$16:$E$16,1,$B$2) -> 1.05012 | H12: =H11*INDEX(Supuestos!$C$16:$E$16,1,$B$2) -> 1.35 | I12: =I11*INDEX(Supuestos!$C$16:$E$16,1,$B$2) -> 1.64988 | J12: =J11*INDEX(Supuestos!$C$16:$E$16,1,$B$2) -> 1.95012 | ... BJ12: =BJ11*INDEX(Supuestos!$C$16:$E$16,1,$B$2) -> 35.25
A13: Clientes nuevos | B13: clientes | C13: =MAX(0,C10-(C11-C12)) -> 9.996 | D13: =MAX(0,D10-(D11-D12)) -> 5.30388 | E13: =MAX(0,E10-(E11-E12)) -> 10.446 | F13: =MAX(0,F10-(F11-F12)) -> 10.75788 | G13: =MAX(0,G10-(G11-G12)) -> 11.04612 | H13: =MAX(0,H10-(H11-H12)) -> 11.346 | I13: =MAX(0,I10-(I11-I12)) -> 11.65788 | J13: =MAX(0,J10-(J11-J12)) -> 16.95012 | ... BJ13: =MAX(0,BJ10-(BJ11-BJ12)) -> 60.25
A14: Clientes activos al cierre del mes | B14: clientes | C14: =C11-C12+C13 -> 9.996 | D14: =D11-D12+D13 -> 15 | E14: =E11-E12+E13 -> 24.996 | F14: =F11-F12+F13 -> 35.004 | G14: =G11-G12+G13 -> 45 | H14: =H11-H12+H13 -> 54.996 | I14: =I11-I12+I13 -> 65.004 | J14: =J11-J12+J13 -> 80.004 | ... BJ14: =BJ11-BJ12+BJ13 -> 1200
A16: Ingresos y costos variables
A17: Precio mensual por tienda | B17: COP | C17: =Supuestos!$C$26*(1+Supuestos!$C$27)^(C6-1) -> 39900 | D17: =Supuestos!$C$26*(1+Supuestos!$C$27)^(D6-1) -> 39900 | E17: =Supuestos!$C$26*(1+Supuestos!$C$27)^(E6-1) -> 39900 | F17: =Supuestos!$C$26*(1+Supuestos!$C$27)^(F6-1) -> 39900 | G17: =Supuestos!$C$26*(1+Supuestos!$C$27)^(G6-1) -> 39900 | H17: =Supuestos!$C$26*(1+Supuestos!$C$27)^(H6-1) -> 39900 | I17: =Supuestos!$C$26*(1+Supuestos!$C$27)^(I6-1) -> 39900 | J17: =Supuestos!$C$26*(1+Supuestos!$C$27)^(J6-1) -> 39900 | ... BJ17: =Supuestos!$C$26*(1+Supuestos!$C$27)^(BJ6-1) -> 48498.699
A18: Ingresos | B18: COP | C18: =C14*C17 -> 398840.4 | D18: =D14*D17 -> 598500 | E18: =E14*E17 -> 997340.4 | F18: =F14*F17 -> 1396659.6 | G18: =G14*G17 -> 1795500 | H18: =H14*H17 -> 2194340.4 | I18: =I14*I17 -> 2593659.6 | J18: =J14*J17 -> 3192159.6 | ... BJ18: =BJ14*BJ17 -> 58198439
A19: Costo de IA | B19: COP | C19: =C14*Supuestos!$C$29*(1+Supuestos!$C$39)^(C6-1) -> 12495 | D19: =D14*Supuestos!$C$29*(1+Supuestos!$C$39)^(D6-1) -> 18750 | E19: =E14*Supuestos!$C$29*(1+Supuestos!$C$39)^(E6-1) -> 31245 | F19: =F14*Supuestos!$C$29*(1+Supuestos!$C$39)^(F6-1) -> 43755 | G19: =G14*Supuestos!$C$29*(1+Supuestos!$C$39)^(G6-1) -> 56250 | H19: =H14*Supuestos!$C$29*(1+Supuestos!$C$39)^(H6-1) -> 68745 | I19: =I14*Supuestos!$C$29*(1+Supuestos!$C$39)^(I6-1) -> 81255 | J19: =J14*Supuestos!$C$29*(1+Supuestos!$C$39)^(J6-1) -> 100005 | ... BJ19: =BJ14*Supuestos!$C$29*(1+Supuestos!$C$39)^(BJ6-1) -> 1823259.4
A20: Comisión de pasarela de pagos | B20: COP | C20: =C18*Supuestos!$C$30 -> 11965.212 | D20: =D18*Supuestos!$C$30 -> 17955 | E20: =E18*Supuestos!$C$30 -> 29920.212 | F20: =F18*Supuestos!$C$30 -> 41899.788 | G20: =G18*Supuestos!$C$30 -> 53865 | H20: =H18*Supuestos!$C$30 -> 65830.212 | I20: =I18*Supuestos!$C$30 -> 77809.788 | J20: =J18*Supuestos!$C$30 -> 95764.788 | ... BJ20: =BJ18*Supuestos!$C$30 -> 1745953.2
A21: Infraestructura en la nube | B21: COP | C21: =IF(C14<=Supuestos!$C$32,Supuestos!$C$31,IF(C14<=Supuestos!$C$34,Supuestos!$C$33,Supuestos!$C$35)) -> 220000 | D21: =IF(D14<=Supuestos!$C$32,Supuestos!$C$31,IF(D14<=Supuestos!$C$34,Supuestos!$C$33,Supuestos!$C$35)) -> 220000 | E21: =IF(E14<=Supuestos!$C$32,Supuestos!$C$31,IF(E14<=Supuestos!$C$34,Supuestos!$C$33,Supuestos!$C$35)) -> 220000 | F21: =IF(F14<=Supuestos!$C$32,Supuestos!$C$31,IF(F14<=Supuestos!$C$34,Supuestos!$C$33,Supuestos!$C$35)) -> 220000 | G21: =IF(G14<=Supuestos!$C$32,Supuestos!$C$31,IF(G14<=Supuestos!$C$34,Supuestos!$C$33,Supuestos!$C$35)) -> 220000 | H21: =IF(H14<=Supuestos!$C$32,Supuestos!$C$31,IF(H14<=Supuestos!$C$34,Supuestos!$C$33,Supuestos!$C$35)) -> 220000 | I21: =IF(I14<=Supuestos!$C$32,Supuestos!$C$31,IF(I14<=Supuestos!$C$34,Supuestos!$C$33,Supuestos!$C$35)) -> 220000 | J21: =IF(J14<=Supuestos!$C$32,Supuestos!$C$31,IF(J14<=Supuestos!$C$34,Supuestos!$C$33,Supuestos!$C$35)) -> 220000 | ... BJ21: =IF(BJ14<=Supuestos!$C$32,Supuestos!$C$31,IF(BJ14<=Supuestos!$C$34,Supuestos!$C$33,Supuestos!$C$35)) -> 800000
A22: Total costos de operación del servicio | B22: COP | C22: =SUM(C19:C21) -> 244460.21 | D22: =SUM(D19:D21) -> 256705 | E22: =SUM(E19:E21) -> 281165.21 | F22: =SUM(F19:F21) -> 305654.79 | G22: =SUM(G19:G21) -> 330115 | H22: =SUM(H19:H21) -> 354575.21 | I22: =SUM(I19:I21) -> 379064.79 | J22: =SUM(J19:J21) -> 415769.79 | ... BJ22: =SUM(BJ19:BJ21) -> 4369212.6
A23: Margen bruto | B23: COP | C23: =C18-C22 -> 154380.19 | D23: =D18-D22 -> 341795 | E23: =E18-E22 -> 716175.19 | F23: =F18-F22 -> 1091004.8 | G23: =G18-G22 -> 1465385 | H23: =H18-H22 -> 1839765.2 | I23: =I18-I22 -> 2214594.8 | J23: =J18-J22 -> 2776389.8 | ... BJ23: =BJ18-BJ22 -> 53829227
A25: Carga de trabajo y equipo
A26: Horas de soporte | B26: horas | C26: =C14*Supuestos!$C$58/60 -> 3.332 | D26: =D14*Supuestos!$C$58/60 -> 5 | E26: =E14*Supuestos!$C$58/60 -> 8.332 | F26: =F14*Supuestos!$C$58/60 -> 11.668 | G26: =G14*Supuestos!$C$58/60 -> 15 | H26: =H14*Supuestos!$C$58/60 -> 18.332 | I26: =I14*Supuestos!$C$58/60 -> 21.668 | J26: =J14*Supuestos!$C$58/60 -> 26.668 | ... BJ26: =BJ14*Supuestos!$C$58/60 -> 400
A27: Horas de incorporación de clientes nuevos | B27: horas | C27: =C13*Supuestos!$C$59 -> 16.9932 | D27: =D13*Supuestos!$C$59 -> 9.016596 | E27: =E13*Supuestos!$C$59 -> 17.7582 | F27: =F13*Supuestos!$C$59 -> 18.288396 | G27: =G13*Supuestos!$C$59 -> 18.778404 | H27: =H13*Supuestos!$C$59 -> 19.2882 | I27: =I13*Supuestos!$C$59 -> 19.818396 | J27: =J13*Supuestos!$C$59 -> 28.815204 | ... BJ27: =BJ13*Supuestos!$C$59 -> 102.425
A28: Horas de ventas | B28: horas | C28: =C13*Supuestos!$C$60 -> 39.984 | D28: =D13*Supuestos!$C$60 -> 21.21552 | E28: =E13*Supuestos!$C$60 -> 41.784 | F28: =F13*Supuestos!$C$60 -> 43.03152 | G28: =G13*Supuestos!$C$60 -> 44.18448 | H28: =H13*Supuestos!$C$60 -> 45.384 | I28: =I13*Supuestos!$C$60 -> 46.63152 | J28: =J13*Supuestos!$C$60 -> 67.80048 | ... BJ28: =BJ13*Supuestos!$C$60 -> 241
A29: Horas de desarrollo y mantenimiento | B29: horas | C29: =Supuestos!$C$61+C14/100*Supuestos!$C$62 -> 80.4998 | D29: =Supuestos!$C$61+D14/100*Supuestos!$C$62 -> 80.75 | E29: =Supuestos!$C$61+E14/100*Supuestos!$C$62 -> 81.2498 | F29: =Supuestos!$C$61+F14/100*Supuestos!$C$62 -> 81.7502 | G29: =Supuestos!$C$61+G14/100*Supuestos!$C$62 -> 82.25 | H29: =Supuestos!$C$61+H14/100*Supuestos!$C$62 -> 82.7498 | I29: =Supuestos!$C$61+I14/100*Supuestos!$C$62 -> 83.2502 | J29: =Supuestos!$C$61+J14/100*Supuestos!$C$62 -> 84.0002 | ... BJ29: =Supuestos!$C$61+BJ14/100*Supuestos!$C$62 -> 140
A30: Horas requeridas | B30: horas | C30: =SUM(C26:C29) -> 140.809 | D30: =SUM(D26:D29) -> 115.98212 | E30: =SUM(E26:E29) -> 149.124 | F30: =SUM(F26:F29) -> 154.73812 | G30: =SUM(G26:G29) -> 160.21288 | H30: =SUM(H26:H29) -> 165.754 | I30: =SUM(I26:I29) -> 171.36812 | J30: =SUM(J26:J29) -> 207.28388 | ... BJ30: =SUM(BJ26:BJ29) -> 883.425
A31: Capacidad de los fundadores | B31: horas | C31: =Supuestos!$C$51*IF(C6=1,Supuestos!$C$54,IF(C6=2,Supuestos!$C$55,Supuestos!$C$56)) -> 240 | D31: =Supuestos!$C$51*IF(D6=1,Supuestos!$C$54,IF(D6=2,Supuestos!$C$55,Supuestos!$C$56)) -> 240 | E31: =Supuestos!$C$51*IF(E6=1,Supuestos!$C$54,IF(E6=2,Supuestos!$C$55,Supuestos!$C$56)) -> 240 | F31: =Supuestos!$C$51*IF(F6=1,Supuestos!$C$54,IF(F6=2,Supuestos!$C$55,Supuestos!$C$56)) -> 240 | G31: =Supuestos!$C$51*IF(G6=1,Supuestos!$C$54,IF(G6=2,Supuestos!$C$55,Supuestos!$C$56)) -> 240 | H31: =Supuestos!$C$51*IF(H6=1,Supuestos!$C$54,IF(H6=2,Supuestos!$C$55,Supuestos!$C$56)) -> 240 | I31: =Supuestos!$C$51*IF(I6=1,Supuestos!$C$54,IF(I6=2,Supuestos!$C$55,Supuestos!$C$56)) -> 240 | J31: =Supuestos!$C$51*IF(J6=1,Supuestos!$C$54,IF(J6=2,Supuestos!$C$55,Supuestos!$C$56)) -> 240 | ... BJ31: =Supuestos!$C$51*IF(BJ6=1,Supuestos!$C$54,IF(BJ6=2,Supuestos!$C$55,Supuestos!$C$56)) -> 480
A32: Colaboradores contratados | B32: personas | C32: =IF(Supuestos!$C$8=1,MAX(0,ROUNDUP((C30-C31)/Supuestos!$C$57,0)),IF(C5=1,1,IF(C6=1,2,IF(C6=2,3,IF(C6=3,4,5))))) -> 0 | D32: =IF(Supuestos!$C$8=1,MAX(0,ROUNDUP((D30-D31)/Supuestos!$C$57,0)),IF(D5=1,1,IF(D6=1,2,IF(D6=2,3,IF(D6=3,4,5))))) -> 0 | E32: =IF(Supuestos!$C$8=1,MAX(0,ROUNDUP((E30-E31)/Supuestos!$C$57,0)),IF(E5=1,1,IF(E6=1,2,IF(E6=2,3,IF(E6=3,4,5))))) -> 0 | F32: =IF(Supuestos!$C$8=1,MAX(0,ROUNDUP((F30-F31)/Supuestos!$C$57,0)),IF(F5=1,1,IF(F6=1,2,IF(F6=2,3,IF(F6=3,4,5))))) -> 0 | G32: =IF(Supuestos!$C$8=1,MAX(0,ROUNDUP((G30-G31)/Supuestos!$C$57,0)),IF(G5=1,1,IF(G6=1,2,IF(G6=2,3,IF(G6=3,4,5))))) -> 0 | H32: =IF(Supuestos!$C$8=1,MAX(0,ROUNDUP((H30-H31)/Supuestos!$C$57,0)),IF(H5=1,1,IF(H6=1,2,IF(H6=2,3,IF(H6=3,4,5))))) -> 0 | I32: =IF(Supuestos!$C$8=1,MAX(0,ROUNDUP((I30-I31)/Supuestos!$C$57,0)),IF(I5=1,1,IF(I6=1,2,IF(I6=2,3,IF(I6=3,4,5))))) -> 0 | J32: =IF(Supuestos!$C$8=1,MAX(0,ROUNDUP((J30-J31)/Supuestos!$C$57,0)),IF(J5=1,1,IF(J6=1,2,IF(J6=2,3,IF(J6=3,4,5))))) -> 0 | ... BJ32: =IF(Supuestos!$C$8=1,MAX(0,ROUNDUP((BJ30-BJ31)/Supuestos!$C$57,0)),IF(BJ5=1,1,IF(BJ6=1,2,IF(BJ6=2,3,IF(BJ6=3,4,5))))) -> 3
A33: Costo total mensual por colaborador | B33: COP | C33: =Supuestos!$C$50*(1+Supuestos!$C$39)^(C6-1)*(1+Supuestos!$C$48)+IF(Supuestos!$C$50*(1+Supuestos!$C$39)^(C6-1)<=2*Supuestos!$C$37*(1+Supuestos!$C$39)^(C6-1),Supuestos!$C$38*(1+Supuestos!$C$39)^(C6-1)*(1+Supuestos!$C$49),0) -> 3060125.2 | D33: =Supuestos!$C$50*(1+Supuestos!$C$39)^(D6-1)*(1+Supuestos!$C$48)+IF(Supuestos!$C$50*(1+Supuestos!$C$39)^(D6-1)<=2*Supuestos!$C$37*(1+Supuestos!$C$39)^(D6-1),Supuestos!$C$38*(1+Supuestos!$C$39)^(D6-1)*(1+Supuestos!$C$49),0) -> 3060125.2 | E33: =Supuestos!$C$50*(1+Supuestos!$C$39)^(E6-1)*(1+Supuestos!$C$48)+IF(Supuestos!$C$50*(1+Supuestos!$C$39)^(E6-1)<=2*Supuestos!$C$37*(1+Supuestos!$C$39)^(E6-1),Supuestos!$C$38*(1+Supuestos!$C$39)^(E6-1)*(1+Supuestos!$C$49),0) -> 3060125.2 | F33: =Supuestos!$C$50*(1+Supuestos!$C$39)^(F6-1)*(1+Supuestos!$C$48)+IF(Supuestos!$C$50*(1+Supuestos!$C$39)^(F6-1)<=2*Supuestos!$C$37*(1+Supuestos!$C$39)^(F6-1),Supuestos!$C$38*(1+Supuestos!$C$39)^(F6-1)*(1+Supuestos!$C$49),0) -> 3060125.2 | G33: =Supuestos!$C$50*(1+Supuestos!$C$39)^(G6-1)*(1+Supuestos!$C$48)+IF(Supuestos!$C$50*(1+Supuestos!$C$39)^(G6-1)<=2*Supuestos!$C$37*(1+Supuestos!$C$39)^(G6-1),Supuestos!$C$38*(1+Supuestos!$C$39)^(G6-1)*(1+Supuestos!$C$49),0) -> 3060125.2 | H33: =Supuestos!$C$50*(1+Supuestos!$C$39)^(H6-1)*(1+Supuestos!$C$48)+IF(Supuestos!$C$50*(1+Supuestos!$C$39)^(H6-1)<=2*Supuestos!$C$37*(1+Supuestos!$C$39)^(H6-1),Supuestos!$C$38*(1+Supuestos!$C$39)^(H6-1)*(1+Supuestos!$C$49),0) -> 3060125.2 | I33: =Supuestos!$C$50*(1+Supuestos!$C$39)^(I6-1)*(1+Supuestos!$C$48)+IF(Supuestos!$C$50*(1+Supuestos!$C$39)^(I6-1)<=2*Supuestos!$C$37*(1+Supuestos!$C$39)^(I6-1),Supuestos!$C$38*(1+Supuestos!$C$39)^(I6-1)*(1+Supuestos!$C$49),0) -> 3060125.2 | J33: =Supuestos!$C$50*(1+Supuestos!$C$39)^(J6-1)*(1+Supuestos!$C$48)+IF(Supuestos!$C$50*(1+Supuestos!$C$39)^(J6-1)<=2*Supuestos!$C$37*(1+Supuestos!$C$39)^(J6-1),Supuestos!$C$38*(1+Supuestos!$C$39)^(J6-1)*(1+Supuestos!$C$49),0) -> 3060125.2 | ... BJ33: =Supuestos!$C$50*(1+Supuestos!$C$39)^(BJ6-1)*(1+Supuestos!$C$48)+IF(Supuestos!$C$50*(1+Supuestos!$C$39)^(BJ6-1)<=2*Supuestos!$C$37*(1+Supuestos!$C$39)^(BJ6-1),Supuestos!$C$38*(1+Supuestos!$C$39)^(BJ6-1)*(1+Supuestos!$C$49),0) -> 3719601.3
A34: Nómina de colaboradores | B34: COP | C34: =C32*C33 -> 0 | D34: =D32*D33 -> 0 | E34: =E32*E33 -> 0 | F34: =F32*F33 -> 0 | G34: =G32*G33 -> 0 | H34: =H32*H33 -> 0 | I34: =I32*I33 -> 0 | J34: =J32*J33 -> 0 | ... BJ34: =BJ32*BJ33 -> 11158804
A35: Fundadores con salario | B35: personas | C35: =IF(C5>=INDEX(Supuestos!$C$18:$E$18,1,$B$2),Supuestos!$C$51,0) -> 0 | D35: =IF(D5>=INDEX(Supuestos!$C$18:$E$18,1,$B$2),Supuestos!$C$51,0) -> 0 | E35: =IF(E5>=INDEX(Supuestos!$C$18:$E$18,1,$B$2),Supuestos!$C$51,0) -> 0 | F35: =IF(F5>=INDEX(Supuestos!$C$18:$E$18,1,$B$2),Supuestos!$C$51,0) -> 0 | G35: =IF(G5>=INDEX(Supuestos!$C$18:$E$18,1,$B$2),Supuestos!$C$51,0) -> 0 | H35: =IF(H5>=INDEX(Supuestos!$C$18:$E$18,1,$B$2),Supuestos!$C$51,0) -> 0 | I35: =IF(I5>=INDEX(Supuestos!$C$18:$E$18,1,$B$2),Supuestos!$C$51,0) -> 0 | J35: =IF(J5>=INDEX(Supuestos!$C$18:$E$18,1,$B$2),Supuestos!$C$51,0) -> 0 | ... BJ35: =IF(BJ5>=INDEX(Supuestos!$C$18:$E$18,1,$B$2),Supuestos!$C$51,0) -> 3
A36: Costo total mensual por fundador | B36: COP | C36: =Supuestos!$C$52*(1+Supuestos!$C$39)^(C6-1)*(1+Supuestos!$C$48)+IF(Supuestos!$C$52*(1+Supuestos!$C$39)^(C6-1)<=2*Supuestos!$C$37*(1+Supuestos!$C$39)^(C6-1),Supuestos!$C$38*(1+Supuestos!$C$39)^(C6-1)*(1+Supuestos!$C$49),0) -> 4443645.2 | D36: =Supuestos!$C$52*(1+Supuestos!$C$39)^(D6-1)*(1+Supuestos!$C$48)+IF(Supuestos!$C$52*(1+Supuestos!$C$39)^(D6-1)<=2*Supuestos!$C$37*(1+Supuestos!$C$39)^(D6-1),Supuestos!$C$38*(1+Supuestos!$C$39)^(D6-1)*(1+Supuestos!$C$49),0) -> 4443645.2 | E36: =Supuestos!$C$52*(1+Supuestos!$C$39)^(E6-1)*(1+Supuestos!$C$48)+IF(Supuestos!$C$52*(1+Supuestos!$C$39)^(E6-1)<=2*Supuestos!$C$37*(1+Supuestos!$C$39)^(E6-1),Supuestos!$C$38*(1+Supuestos!$C$39)^(E6-1)*(1+Supuestos!$C$49),0) -> 4443645.2 | F36: =Supuestos!$C$52*(1+Supuestos!$C$39)^(F6-1)*(1+Supuestos!$C$48)+IF(Supuestos!$C$52*(1+Supuestos!$C$39)^(F6-1)<=2*Supuestos!$C$37*(1+Supuestos!$C$39)^(F6-1),Supuestos!$C$38*(1+Supuestos!$C$39)^(F6-1)*(1+Supuestos!$C$49),0) -> 4443645.2 | G36: =Supuestos!$C$52*(1+Supuestos!$C$39)^(G6-1)*(1+Supuestos!$C$48)+IF(Supuestos!$C$52*(1+Supuestos!$C$39)^(G6-1)<=2*Supuestos!$C$37*(1+Supuestos!$C$39)^(G6-1),Supuestos!$C$38*(1+Supuestos!$C$39)^(G6-1)*(1+Supuestos!$C$49),0) -> 4443645.2 | H36: =Supuestos!$C$52*(1+Supuestos!$C$39)^(H6-1)*(1+Supuestos!$C$48)+IF(Supuestos!$C$52*(1+Supuestos!$C$39)^(H6-1)<=2*Supuestos!$C$37*(1+Supuestos!$C$39)^(H6-1),Supuestos!$C$38*(1+Supuestos!$C$39)^(H6-1)*(1+Supuestos!$C$49),0) -> 4443645.2 | I36: =Supuestos!$C$52*(1+Supuestos!$C$39)^(I6-1)*(1+Supuestos!$C$48)+IF(Supuestos!$C$52*(1+Supuestos!$C$39)^(I6-1)<=2*Supuestos!$C$37*(1+Supuestos!$C$39)^(I6-1),Supuestos!$C$38*(1+Supuestos!$C$39)^(I6-1)*(1+Supuestos!$C$49),0) -> 4443645.2 | J36: =Supuestos!$C$52*(1+Supuestos!$C$39)^(J6-1)*(1+Supuestos!$C$48)+IF(Supuestos!$C$52*(1+Supuestos!$C$39)^(J6-1)<=2*Supuestos!$C$37*(1+Supuestos!$C$39)^(J6-1),Supuestos!$C$38*(1+Supuestos!$C$39)^(J6-1)*(1+Supuestos!$C$49),0) -> 4443645.2 | ... BJ36: =Supuestos!$C$52*(1+Supuestos!$C$39)^(BJ6-1)*(1+Supuestos!$C$48)+IF(Supuestos!$C$52*(1+Supuestos!$C$39)^(BJ6-1)<=2*Supuestos!$C$37*(1+Supuestos!$C$39)^(BJ6-1),Supuestos!$C$38*(1+Supuestos!$C$39)^(BJ6-1)*(1+Supuestos!$C$49),0) -> 5401278.5
A37: Nómina de fundadores | B37: COP | C37: =C35*C36 -> 0 | D37: =D35*D36 -> 0 | E37: =E35*E36 -> 0 | F37: =F35*F36 -> 0 | G37: =G35*G36 -> 0 | H37: =H35*H36 -> 0 | I37: =I35*I36 -> 0 | J37: =J35*J36 -> 0 | ... BJ37: =BJ35*BJ36 -> 16203835
A38: Personas en el equipo (fundadores + colaboradores) | B38: personas | C38: =Supuestos!$C$51+C32 -> 3 | D38: =Supuestos!$C$51+D32 -> 3 | E38: =Supuestos!$C$51+E32 -> 3 | F38: =Supuestos!$C$51+F32 -> 3 | G38: =Supuestos!$C$51+G32 -> 3 | H38: =Supuestos!$C$51+H32 -> 3 | I38: =Supuestos!$C$51+I32 -> 3 | J38: =Supuestos!$C$51+J32 -> 3 | ... BJ38: =Supuestos!$C$51+BJ32 -> 6
A40: Gastos operativos
A41: Nómina total | B41: COP | C41: =C34+C37 -> 0 | D41: =D34+D37 -> 0 | E41: =E34+E37 -> 0 | F41: =F34+F37 -> 0 | G41: =G34+G37 -> 0 | H41: =H34+H37 -> 0 | I41: =I34+I37 -> 0 | J41: =J34+J37 -> 0 | ... BJ41: =BJ34+BJ37 -> 27362639
A42: Marketing y adquisición de clientes | B42: COP | C42: =C13*INDEX(Supuestos!$C$17:$E$17,1,$B$2)*(1+Supuestos!$C$39)^(C6-1) -> 649740 | D42: =D13*INDEX(Supuestos!$C$17:$E$17,1,$B$2)*(1+Supuestos!$C$39)^(D6-1) -> 344752.2 | E42: =E13*INDEX(Supuestos!$C$17:$E$17,1,$B$2)*(1+Supuestos!$C$39)^(E6-1) -> 678990 | F42: =F13*INDEX(Supuestos!$C$17:$E$17,1,$B$2)*(1+Supuestos!$C$39)^(F6-1) -> 699262.2 | G42: =G13*INDEX(Supuestos!$C$17:$E$17,1,$B$2)*(1+Supuestos!$C$39)^(G6-1) -> 717997.8 | H42: =H13*INDEX(Supuestos!$C$17:$E$17,1,$B$2)*(1+Supuestos!$C$39)^(H6-1) -> 737490 | I42: =I13*INDEX(Supuestos!$C$17:$E$17,1,$B$2)*(1+Supuestos!$C$39)^(I6-1) -> 757762.2 | J42: =J13*INDEX(Supuestos!$C$17:$E$17,1,$B$2)*(1+Supuestos!$C$39)^(J6-1) -> 1101757.8 | ... BJ42: =BJ13*INDEX(Supuestos!$C$17:$E$17,1,$B$2)*(1+Supuestos!$C$39)^(BJ6-1) -> 4760226.4
A43: Arriendo de coworking | B43: COP | C43: =IF(C5>=Supuestos!$C$65,Supuestos!$C$64*(1+Supuestos!$C$39)^(C6-1),0) -> 0 | D43: =IF(D5>=Supuestos!$C$65,Supuestos!$C$64*(1+Supuestos!$C$39)^(D6-1),0) -> 0 | E43: =IF(E5>=Supuestos!$C$65,Supuestos!$C$64*(1+Supuestos!$C$39)^(E6-1),0) -> 0 | F43: =IF(F5>=Supuestos!$C$65,Supuestos!$C$64*(1+Supuestos!$C$39)^(F6-1),0) -> 0 | G43: =IF(G5>=Supuestos!$C$65,Supuestos!$C$64*(1+Supuestos!$C$39)^(G6-1),0) -> 0 | H43: =IF(H5>=Supuestos!$C$65,Supuestos!$C$64*(1+Supuestos!$C$39)^(H6-1),0) -> 0 | I43: =IF(I5>=Supuestos!$C$65,Supuestos!$C$64*(1+Supuestos!$C$39)^(I6-1),0) -> 0 | J43: =IF(J5>=Supuestos!$C$65,Supuestos!$C$64*(1+Supuestos!$C$39)^(J6-1),0) -> 0 | ... BJ43: =IF(BJ5>=Supuestos!$C$65,Supuestos!$C$64*(1+Supuestos!$C$39)^(BJ6-1),0) -> 607753.12
A44: Gastos administrativos y legales | B44: COP | C44: =IF(C6=1,Supuestos!$C$66,Supuestos!$C$67*(1+Supuestos!$C$39)^(C6-2)) -> 200000 | D44: =IF(D6=1,Supuestos!$C$66,Supuestos!$C$67*(1+Supuestos!$C$39)^(D6-2)) -> 200000 | E44: =IF(E6=1,Supuestos!$C$66,Supuestos!$C$67*(1+Supuestos!$C$39)^(E6-2)) -> 200000 | F44: =IF(F6=1,Supuestos!$C$66,Supuestos!$C$67*(1+Supuestos!$C$39)^(F6-2)) -> 200000 | G44: =IF(G6=1,Supuestos!$C$66,Supuestos!$C$67*(1+Supuestos!$C$39)^(G6-2)) -> 200000 | H44: =IF(H6=1,Supuestos!$C$66,Supuestos!$C$67*(1+Supuestos!$C$39)^(H6-2)) -> 200000 | I44: =IF(I6=1,Supuestos!$C$66,Supuestos!$C$67*(1+Supuestos!$C$39)^(I6-2)) -> 200000 | J44: =IF(J6=1,Supuestos!$C$66,Supuestos!$C$67*(1+Supuestos!$C$39)^(J6-2)) -> 200000 | ... BJ44: =IF(BJ6=1,Supuestos!$C$66,Supuestos!$C$67*(1+Supuestos!$C$39)^(BJ6-2)) -> 463050
A45: Software, herramientas, dominio y SSL | B45: COP | C45: =(Supuestos!$C$68+Supuestos!$C$69)*(1+Supuestos!$C$39)^(C6-1) -> 110000 | D45: =(Supuestos!$C$68+Supuestos!$C$69)*(1+Supuestos!$C$39)^(D6-1) -> 110000 | E45: =(Supuestos!$C$68+Supuestos!$C$69)*(1+Supuestos!$C$39)^(E6-1) -> 110000 | F45: =(Supuestos!$C$68+Supuestos!$C$69)*(1+Supuestos!$C$39)^(F6-1) -> 110000 | G45: =(Supuestos!$C$68+Supuestos!$C$69)*(1+Supuestos!$C$39)^(G6-1) -> 110000 | H45: =(Supuestos!$C$68+Supuestos!$C$69)*(1+Supuestos!$C$39)^(H6-1) -> 110000 | I45: =(Supuestos!$C$68+Supuestos!$C$69)*(1+Supuestos!$C$39)^(I6-1) -> 110000 | J45: =(Supuestos!$C$68+Supuestos!$C$69)*(1+Supuestos!$C$39)^(J6-1) -> 110000 | ... BJ45: =(Supuestos!$C$68+Supuestos!$C$69)*(1+Supuestos!$C$39)^(BJ6-1) -> 133705.69
A46: Total gastos operativos | B46: COP | C46: =SUM(C41:C45)+C91 -> 1130285 | D46: =SUM(D41:D45)+D91 -> 825297.18 | E46: =SUM(E41:E45)+E91 -> 1159535 | F46: =SUM(F41:F45)+F91 -> 1179807.2 | G46: =SUM(G41:G45)+G91 -> 1198542.8 | H46: =SUM(H41:H45)+H91 -> 1218035 | I46: =SUM(I41:I45)+I91 -> 1238307.2 | J46: =SUM(J41:J45)+J91 -> 1582302.8 | ... BJ46: =SUM(BJ41:BJ45)+BJ91 -> 33479313
A47: Resultado operativo (EBITDA) | B47: COP | C47: =C23-C46 -> -975904.79 | D47: =D23-D46 -> -483502.18 | E47: =E23-E46 -> -443359.79 | F47: =F23-F46 -> -88802.368 | G47: =G23-G46 -> 266842.22 | H47: =H23-H46 -> 621730.21 | I47: =I23-I46 -> 976287.63 | J47: =J23-J46 -> 1194087 | ... BJ47: =BJ23-BJ46 -> 20349914
A48: Caja acumulada antes de impuestos (incluye inversión inicial) | B48: COP | C48: =-(Supuestos!$C$71+Supuestos!$C$72+Supuestos!$C$73)+C47 -> -2475904.8 | D48: =C48+D47 -> -2959407 | E48: =D48+E47 -> -3402766.8 | F48: =E48+F47 -> -3491569.1 | G48: =F48+G47 -> -3224726.9 | H48: =G48+H47 -> -2602996.7 | I48: =H48+I47 -> -1626709.1 | J48: =I48+J47 -> -432622.04 | K48: =J48+K47 -> 1431855.2 | ... BJ48: =BI48+BJ47 -> 3.2729291e+08
A49: Memo: valor del trabajo no remunerado de los fundadores | B49: COP | C49: =(Supuestos!$C$51-C35)*C36*C31/Supuestos!$C$51/160 -> 6665467.8 | D49: =(Supuestos!$C$51-D35)*D36*D31/Supuestos!$C$51/160 -> 6665467.8 | E49: =(Supuestos!$C$51-E35)*E36*E31/Supuestos!$C$51/160 -> 6665467.8 | F49: =(Supuestos!$C$51-F35)*F36*F31/Supuestos!$C$51/160 -> 6665467.8 | G49: =(Supuestos!$C$51-G35)*G36*G31/Supuestos!$C$51/160 -> 6665467.8 | H49: =(Supuestos!$C$51-H35)*H36*H31/Supuestos!$C$51/160 -> 6665467.8 | I49: =(Supuestos!$C$51-I35)*I36*I31/Supuestos!$C$51/160 -> 6665467.8 | J49: =(Supuestos!$C$51-J35)*J36*J31/Supuestos!$C$51/160 -> 6665467.8 | ... BJ49: =(Supuestos!$C$51-BJ35)*BJ36*BJ31/Supuestos!$C$51/160 -> 0
A51: Resumen anual (millones de COP salvo indicación)
A52: Concepto | B52: Año 0 | C52: Año 1 | D52: Año 2 | E52: Año 3 | F52: Año 4 | G52: Año 5
A53: Clientes activos al cierre (número) | C53: =INDEX($C$14:$BJ$14,1,12) -> 120 | D53: =INDEX($C$14:$BJ$14,1,24) -> 300 | E53: =INDEX($C$14:$BJ$14,1,36) -> 600 | F53: =INDEX($C$14:$BJ$14,1,48) -> 900 | G53: =INDEX($C$14:$BJ$14,1,60) -> 1200
A54: Clientes nuevos en el año (número) | C54: =SUMIF($C$6:$BJ$6,1,$C$13:$BJ$13) -> 138.9 | D54: =SUMIF($C$6:$BJ$6,2,$C$13:$BJ$13) -> 252.9 | E54: =SUMIF($C$6:$BJ$6,3,$C$13:$BJ$13) -> 457.5 | F54: =SUMIF($C$6:$BJ$6,4,$C$13:$BJ$13) -> 565.5 | G54: =SUMIF($C$6:$BJ$6,5,$C$13:$BJ$13) -> 673.5
A55: Clientes retirados en el año (número) | C55: =SUMIF($C$6:$BJ$6,1,$C$12:$BJ$12) -> 18.9 | D55: =SUMIF($C$6:$BJ$6,2,$C$12:$BJ$12) -> 72.9 | E55: =SUMIF($C$6:$BJ$6,3,$C$12:$BJ$12) -> 157.5 | F55: =SUMIF($C$6:$BJ$6,4,$C$12:$BJ$12) -> 265.5 | G55: =SUMIF($C$6:$BJ$6,5,$C$12:$BJ$12) -> 373.5
A56: Precio mensual (COP) | C56: =INDEX($C$17:$BJ$17,1,12) -> 39900 | D56: =INDEX($C$17:$BJ$17,1,24) -> 41895 | E56: =INDEX($C$17:$BJ$17,1,36) -> 43989.75 | F56: =INDEX($C$17:$BJ$17,1,48) -> 46189.238 | G56: =INDEX($C$17:$BJ$17,1,60) -> 48498.699
A57: Ingresos | C57: =SUMIF($C$6:$BJ$6,1,$C$18:$BJ$18)/1000000 -> 29.925 | D57: =SUMIF($C$6:$BJ$6,2,$C$18:$BJ$18)/1000000 -> 109.34595 | E57: =SUMIF($C$6:$BJ$6,3,$C$18:$BJ$18)/1000000 -> 244.14311 | F57: =SUMIF($C$6:$BJ$6,4,$C$18:$BJ$18)/1000000 -> 422.63152 | G57: =SUMIF($C$6:$BJ$6,5,$C$18:$BJ$18)/1000000 -> 618.35842
A58: Costos de operación del servicio (IA, pasarela, nube) | C58: =SUMIF($C$6:$BJ$6,1,$C$22:$BJ$22)/1000000 -> 4.47525 | D58: =SUMIF($C$6:$BJ$6,2,$C$22:$BJ$22)/1000000 -> 9.3460035 | E58: =SUMIF($C$6:$BJ$6,3,$C$22:$BJ$22)/1000000 -> 20.372887 | F58: =SUMIF($C$6:$BJ$6,4,$C$22:$BJ$22)/1000000 -> 34.119282 | G58: =SUMIF($C$6:$BJ$6,5,$C$22:$BJ$22)/1000000 -> 47.522883
A59: Margen bruto | C59: =C57-C58 -> 25.44975 | D59: =D57-D58 -> 99.999946 | E59: =E57-E58 -> 223.77023 | F59: =F57-F58 -> 388.51224 | G59: =G57-G58 -> 570.83553
A60: Margen bruto (%) | C60: =IF(C57=0,0,C59/C57) -> 0.85045113 | D60: =IF(D57=0,0,D59/D57) -> 0.91452812 | E60: =IF(E57=0,0,E59/E57) -> 0.9165535 | F60: =IF(F57=0,0,F59/F57) -> 0.91926944 | G60: =IF(G57=0,0,G59/G57) -> 0.9231467
A61: Nómina de colaboradores | C61: =SUMIF($C$6:$BJ$6,1,$C$34:$BJ$34)/1000000 -> 0 | D61: =SUMIF($C$6:$BJ$6,2,$C$34:$BJ$34)/1000000 -> 0 | E61: =SUMIF($C$6:$BJ$6,3,$C$34:$BJ$34)/1000000 -> 20.242728 | F61: =SUMIF($C$6:$BJ$6,4,$C$34:$BJ$34)/1000000 -> 63.764593 | G61: =SUMIF($C$6:$BJ$6,5,$C$34:$BJ$34)/1000000 -> 115.30764
A62: Nómina de fundadores | C62: =SUMIF($C$6:$BJ$6,1,$C$37:$BJ$37)/1000000 -> 0 | D62: =SUMIF($C$6:$BJ$6,2,$C$37:$BJ$37)/1000000 -> 0 | E62: =SUMIF($C$6:$BJ$6,3,$C$37:$BJ$37)/1000000 -> 176.36828 | F62: =SUMIF($C$6:$BJ$6,4,$C$37:$BJ$37)/1000000 -> 185.18669 | G62: =SUMIF($C$6:$BJ$6,5,$C$37:$BJ$37)/1000000 -> 194.44603
A63: Marketing y adquisición | C63: =SUMIF($C$6:$BJ$6,1,$C$42:$BJ$42)/1000000 -> 9.0285 | D63: =SUMIF($C$6:$BJ$6,2,$C$42:$BJ$42)/1000000 -> 17.260425 | E63: =SUMIF($C$6:$BJ$6,3,$C$42:$BJ$42)/1000000 -> 32.785594 | F63: =SUMIF($C$6:$BJ$6,4,$C$42:$BJ$42)/1000000 -> 42.551401 | G63: =SUMIF($C$6:$BJ$6,5,$C$42:$BJ$42)/1000000 -> 53.211825
A64: Arriendo, administración, software, equipos y trabajo desde casa | C64: =(SUMIF($C$6:$BJ$6,1,$C$43:$BJ$43)+SUMIF($C$6:$BJ$6,1,$C$44:$BJ$44)+SUMIF($C$6:$BJ$6,1,$C$45:$BJ$45)+SUMIF($C$6:$BJ$6,1,$C$91:$BJ$91))/1000000 -> 5.7665398 | D64: =(SUMIF($C$6:$BJ$6,2,$C$43:$BJ$43)+SUMIF($C$6:$BJ$6,2,$C$44:$BJ$44)+SUMIF($C$6:$BJ$6,2,$C$45:$BJ$45)+SUMIF($C$6:$BJ$6,2,$C$91:$BJ$91))/1000000 -> 8.6218001 | E64: =(SUMIF($C$6:$BJ$6,3,$C$43:$BJ$43)+SUMIF($C$6:$BJ$6,3,$C$44:$BJ$44)+SUMIF($C$6:$BJ$6,3,$C$45:$BJ$45)+SUMIF($C$6:$BJ$6,3,$C$91:$BJ$91))/1000000 -> 17.5203 | F64: =(SUMIF($C$6:$BJ$6,4,$C$43:$BJ$43)+SUMIF($C$6:$BJ$6,4,$C$44:$BJ$44)+SUMIF($C$6:$BJ$6,4,$C$45:$BJ$45)+SUMIF($C$6:$BJ$6,4,$C$91:$BJ$91))/1000000 -> 18.396315 | G64: =(SUMIF($C$6:$BJ$6,5,$C$43:$BJ$43)+SUMIF($C$6:$BJ$6,5,$C$44:$BJ$44)+SUMIF($C$6:$BJ$6,5,$C$45:$BJ$45)+SUMIF($C$6:$BJ$6,5,$C$91:$BJ$91))/1000000 -> 19.316131
A65: Total gastos operativos | C65: =SUMIF($C$6:$BJ$6,1,$C$46:$BJ$46)/1000000 -> 14.79504 | D65: =SUMIF($C$6:$BJ$6,2,$C$46:$BJ$46)/1000000 -> 25.882225 | E65: =SUMIF($C$6:$BJ$6,3,$C$46:$BJ$46)/1000000 -> 246.9169 | F65: =SUMIF($C$6:$BJ$6,4,$C$46:$BJ$46)/1000000 -> 309.899 | G65: =SUMIF($C$6:$BJ$6,5,$C$46:$BJ$46)/1000000 -> 382.28162
A66: Resultado operativo (EBITDA) | C66: =C59-C65 -> 10.65471 | D66: =D59-D65 -> 74.117721 | E66: =E59-E65 -> -23.146673 | F66: =F59-F65 -> 78.613241 | G66: =G59-G65 -> 188.55391
A67: Pérdidas acumuladas por compensar al inicio | C67: =0 -> 0 | D67: =MIN(0,C67+C66) -> 0 | E67: =MIN(0,D67+D66) -> 0 | F67: =MIN(0,E67+E66) -> -23.146673 | G67: =MIN(0,F67+F66) -> 0
A68: Base gravable | C68: =MAX(0,C66+C67) -> 10.65471 | D68: =MAX(0,D66+D67) -> 74.117721 | E68: =MAX(0,E66+E67) -> 0 | F68: =MAX(0,F66+F67) -> 55.466568 | G68: =MAX(0,G66+G67) -> 188.55391
A69: Impuesto de renta | C69: =C68*Supuestos!$C$74 -> 3.7291486 | D69: =D68*Supuestos!$C$74 -> 25.941202 | E69: =E68*Supuestos!$C$74 -> 0 | F69: =F68*Supuestos!$C$74 -> 19.413299 | G69: =G68*Supuestos!$C$74 -> 65.99387
A70: Utilidad neta | C70: =C66-C69 -> 6.9255617 | D70: =D66-D69 -> 48.176519 | E70: =E66-E69 -> -23.146673 | F70: =F66-F69 -> 59.199943 | G70: =G66-G69 -> 122.56004
A71: Flujo de caja neto | B71: =-(Supuestos!$C$71+Supuestos!$C$72+Supuestos!$C$73)/1000000 -> -1.5 | C71: =C70 -> 6.9255617 | D71: =D70 -> 48.176519 | E71: =E70 -> -23.146673 | F71: =F70 -> 59.199943 | G71: =G70 -> 122.56004
A72: Flujo de caja acumulado | B72: =B71 -> -1.5 | C72: =B72+C71 -> 5.4255617 | D72: =C72+D71 -> 53.602081 | E72: =D72+E71 -> 30.455407 | F72: =E72+F71 -> 89.65535 | G72: =F72+G71 -> 212.21539
A73: ¿Recuperó la inversión? (1 = sí) | C73: =IF(C72>=0,1,0) -> 1 | D73: =IF(D72>=0,1,0) -> 1 | E73: =IF(E72>=0,1,0) -> 1 | F73: =IF(F72>=0,1,0) -> 1 | G73: =IF(G72>=0,1,0) -> 1
A74: Memo: trabajo no remunerado de los fundadores (aporte en especie) | C74: =SUMIF($C$6:$BJ$6,1,$C$49:$BJ$49)/1000000 -> 79.985613 | D74: =SUMIF($C$6:$BJ$6,2,$C$49:$BJ$49)/1000000 -> 125.97734 | E74: =SUMIF($C$6:$BJ$6,3,$C$49:$BJ$49)/1000000 -> 0 | F74: =SUMIF($C$6:$BJ$6,4,$C$49:$BJ$49)/1000000 -> 0 | G74: =SUMIF($C$6:$BJ$6,5,$C$49:$BJ$49)/1000000 -> 0
A75: Personas en el equipo al cierre | C75: =INDEX($C$38:$BJ$38,1,12) -> 3 | D75: =INDEX($C$38:$BJ$38,1,24) -> 3 | E75: =INDEX($C$38:$BJ$38,1,36) -> 4 | F75: =INDEX($C$38:$BJ$38,1,48) -> 5 | G75: =INDEX($C$38:$BJ$38,1,60) -> 6
A76: Ingreso anual por persona del equipo | C76: =IF(C75=0,0,C57/C75) -> 9.975 | D76: =IF(D75=0,0,D57/D75) -> 36.44865 | E76: =IF(E75=0,0,E57/E75) -> 61.035778 | F76: =IF(F75=0,0,F57/F75) -> 84.526305 | G76: =IF(G75=0,0,G57/G75) -> 103.05974
A77: Punto de equilibrio (clientes activos necesarios, promedio mensual del año) | C77: =ROUNDUP((SUMIF($C$6:$BJ$6,1,$C$46:$BJ$46)+SUMIF($C$6:$BJ$6,1,$C$21:$BJ$21))/12/(INDEX($C$17:$BJ$17,1,12)*(1-Supuestos!$C$30)-Supuestos!$C$29*(1+Supuestos!$C$39)^(1-1)),0) -> 39 | D77: =ROUNDUP((SUMIF($C$6:$BJ$6,2,$C$46:$BJ$46)+SUMIF($C$6:$BJ$6,2,$C$21:$BJ$21))/12/(INDEX($C$17:$BJ$17,1,24)*(1-Supuestos!$C$30)-Supuestos!$C$29*(1+Supuestos!$C$39)^(2-1)),0) -> 61 | E77: =ROUNDUP((SUMIF($C$6:$BJ$6,3,$C$46:$BJ$46)+SUMIF($C$6:$BJ$6,3,$C$21:$BJ$21))/12/(INDEX($C$17:$BJ$17,1,36)*(1-Supuestos!$C$30)-Supuestos!$C$29*(1+Supuestos!$C$39)^(3-1)),0) -> 510 | F77: =ROUNDUP((SUMIF($C$6:$BJ$6,4,$C$46:$BJ$46)+SUMIF($C$6:$BJ$6,4,$C$21:$BJ$21))/12/(INDEX($C$17:$BJ$17,1,48)*(1-Supuestos!$C$30)-Supuestos!$C$29*(1+Supuestos!$C$39)^(4-1)),0) -> 612 | G77: =ROUNDUP((SUMIF($C$6:$BJ$6,5,$C$46:$BJ$46)+SUMIF($C$6:$BJ$6,5,$C$21:$BJ$21))/12/(INDEX($C$17:$BJ$17,1,60)*(1-Supuestos!$C$30)-Supuestos!$C$29*(1+Supuestos!$C$39)^(5-1)),0) -> 718
A79: Indicadores de evaluación
A80: VPN a la TIO (millones COP) | C80: =B71+NPV(Supuestos!$C$75,C71:G71) -> 102.13564
A81: TIR | C81: =IFERROR(IRR(B71:G71),"No existe") -> 7.333862
A82: Año de recuperación de la inversión | C82: =IFERROR(MATCH(1,C73:G73,0),"Más de 5 años") -> 1
A83: Necesidad máxima de caja (millones COP) | C83: =-MIN(0,MIN($C$48:$BJ$48))/1000000 -> 3.4915691
A84: Primer mes con resultado operativo positivo | C84: =IFERROR(MATCH(TRUE(),INDEX($C$47:$BJ$47>0,0),0),"No ocurre en 5 años") -> 5
A86: Trabajo desde casa y equipos
A87: Fundadores trabajando sin salario desde casa | B87: personas | C87: =Supuestos!$C$51-C35 -> 3 | D87: =Supuestos!$C$51-D35 -> 3 | E87: =Supuestos!$C$51-E35 -> 3 | F87: =Supuestos!$C$51-F35 -> 3 | G87: =Supuestos!$C$51-G35 -> 3 | H87: =Supuestos!$C$51-H35 -> 3 | I87: =Supuestos!$C$51-I35 -> 3 | J87: =Supuestos!$C$51-J35 -> 3 | ... BJ87: =Supuestos!$C$51-BJ35 -> 0
A88: Energía e internet del hogar (se reembolsan mientras no hay salario) | B88: COP | C88: =C87*(Supuestos!$C$84/1000*(C31/Supuestos!$C$51)*Supuestos!$C$83+Supuestos!$C$85*MIN(1,(C31/Supuestos!$C$51)/Supuestos!$C$86))*(1+Supuestos!$C$39)^(C6-1) -> 45544.98 | D88: =D87*(Supuestos!$C$84/1000*(D31/Supuestos!$C$51)*Supuestos!$C$83+Supuestos!$C$85*MIN(1,(D31/Supuestos!$C$51)/Supuestos!$C$86))*(1+Supuestos!$C$39)^(D6-1) -> 45544.98 | E88: =E87*(Supuestos!$C$84/1000*(E31/Supuestos!$C$51)*Supuestos!$C$83+Supuestos!$C$85*MIN(1,(E31/Supuestos!$C$51)/Supuestos!$C$86))*(1+Supuestos!$C$39)^(E6-1) -> 45544.98 | F88: =F87*(Supuestos!$C$84/1000*(F31/Supuestos!$C$51)*Supuestos!$C$83+Supuestos!$C$85*MIN(1,(F31/Supuestos!$C$51)/Supuestos!$C$86))*(1+Supuestos!$C$39)^(F6-1) -> 45544.98 | G88: =G87*(Supuestos!$C$84/1000*(G31/Supuestos!$C$51)*Supuestos!$C$83+Supuestos!$C$85*MIN(1,(G31/Supuestos!$C$51)/Supuestos!$C$86))*(1+Supuestos!$C$39)^(G6-1) -> 45544.98 | H88: =H87*(Supuestos!$C$84/1000*(H31/Supuestos!$C$51)*Supuestos!$C$83+Supuestos!$C$85*MIN(1,(H31/Supuestos!$C$51)/Supuestos!$C$86))*(1+Supuestos!$C$39)^(H6-1) -> 45544.98 | I88: =I87*(Supuestos!$C$84/1000*(I31/Supuestos!$C$51)*Supuestos!$C$83+Supuestos!$C$85*MIN(1,(I31/Supuestos!$C$51)/Supuestos!$C$86))*(1+Supuestos!$C$39)^(I6-1) -> 45544.98 | J88: =J87*(Supuestos!$C$84/1000*(J31/Supuestos!$C$51)*Supuestos!$C$83+Supuestos!$C$85*MIN(1,(J31/Supuestos!$C$51)/Supuestos!$C$86))*(1+Supuestos!$C$39)^(J6-1) -> 45544.98 | ... BJ88: =BJ87*(Supuestos!$C$84/1000*(BJ31/Supuestos!$C$51)*Supuestos!$C$83+Supuestos!$C$85*MIN(1,(BJ31/Supuestos!$C$51)/Supuestos!$C$86))*(1+Supuestos!$C$39)^(BJ6-1) -> 0
A89: Reserva de reposición de los portátiles de los fundadores | B89: COP | C89: =Supuestos!$C$51*Supuestos!$C$87/Supuestos!$C$88*(1+Supuestos!$C$39)^(C6-1) -> 125000 | D89: =Supuestos!$C$51*Supuestos!$C$87/Supuestos!$C$88*(1+Supuestos!$C$39)^(D6-1) -> 125000 | E89: =Supuestos!$C$51*Supuestos!$C$87/Supuestos!$C$88*(1+Supuestos!$C$39)^(E6-1) -> 125000 | F89: =Supuestos!$C$51*Supuestos!$C$87/Supuestos!$C$88*(1+Supuestos!$C$39)^(F6-1) -> 125000 | G89: =Supuestos!$C$51*Supuestos!$C$87/Supuestos!$C$88*(1+Supuestos!$C$39)^(G6-1) -> 125000 | H89: =Supuestos!$C$51*Supuestos!$C$87/Supuestos!$C$88*(1+Supuestos!$C$39)^(H6-1) -> 125000 | I89: =Supuestos!$C$51*Supuestos!$C$87/Supuestos!$C$88*(1+Supuestos!$C$39)^(I6-1) -> 125000 | J89: =Supuestos!$C$51*Supuestos!$C$87/Supuestos!$C$88*(1+Supuestos!$C$39)^(J6-1) -> 125000 | ... BJ89: =Supuestos!$C$51*Supuestos!$C$87/Supuestos!$C$88*(1+Supuestos!$C$39)^(BJ6-1) -> 151938.28
A90: Portátiles para colaboradores nuevos | B90: COP | C90: =MAX(0,C32)*Supuestos!$C$87*(1+Supuestos!$C$39)^(C6-1) -> 0 | D90: =MAX(0,D32-MAX($C$32:C32))*Supuestos!$C$87*(1+Supuestos!$C$39)^(D6-1) -> 0 | E90: =MAX(0,E32-MAX($C$32:D32))*Supuestos!$C$87*(1+Supuestos!$C$39)^(E6-1) -> 0 | F90: =MAX(0,F32-MAX($C$32:E32))*Supuestos!$C$87*(1+Supuestos!$C$39)^(F6-1) -> 0 | G90: =MAX(0,G32-MAX($C$32:F32))*Supuestos!$C$87*(1+Supuestos!$C$39)^(G6-1) -> 0 | H90: =MAX(0,H32-MAX($C$32:G32))*Supuestos!$C$87*(1+Supuestos!$C$39)^(H6-1) -> 0 | I90: =MAX(0,I32-MAX($C$32:H32))*Supuestos!$C$87*(1+Supuestos!$C$39)^(I6-1) -> 0 | J90: =MAX(0,J32-MAX($C$32:I32))*Supuestos!$C$87*(1+Supuestos!$C$39)^(J6-1) -> 0 | K90: =MAX(0,K32-MAX($C$32:J32))*Supuestos!$C$87*(1+Supuestos!$C$39)^(K6-1) -> 0 | ... BJ90: =MAX(0,BJ32-MAX($C$32:BI32))*Supuestos!$C$87*(1+Supuestos!$C$39)^(BJ6-1) -> 0
A91: Total trabajo desde casa y equipos | B91: COP | C91: =SUM(C88:C90) -> 170544.98 | D91: =SUM(D88:D90) -> 170544.98 | E91: =SUM(E88:E90) -> 170544.98 | F91: =SUM(F88:F90) -> 170544.98 | G91: =SUM(G88:G90) -> 170544.98 | H91: =SUM(H88:H90) -> 170544.98 | I91: =SUM(I88:I90) -> 170544.98 | J91: =SUM(J88:J90) -> 170544.98 | ... BJ91: =SUM(BJ88:BJ90) -> 151938.28
A93: Memo: de lo anterior, trabajo desde casa y equipos (millones COP) | C93: =SUMIF($C$6:$BJ$6,1,$C$91:$BJ$91)/1000000 -> 2.0465398 | D93: =SUMIF($C$6:$BJ$6,2,$C$91:$BJ$91)/1000000 -> 2.4358001 | E93: =SUMIF($C$6:$BJ$6,3,$C$91:$BJ$91)/1000000 -> 4.41 | F93: =SUMIF($C$6:$BJ$6,4,$C$91:$BJ$91)/1000000 -> 4.6305 | G93: =SUMIF($C$6:$BJ$6,5,$C$91:$BJ$91)/1000000 -> 4.862025

Sheet Optimista
A1: Escenario Optimista — proyección mensual (60 meses) y anual
A2: Índice del escenario | B2: 3
A3: Todo en esta hoja es fórmula. Para cambiar resultados, edite la hoja Supuestos.
A5: Mes | C5: 1 | D5: 2 | E5: 3 | F5: 4 | G5: 5 | H5: 6 | I5: 7 | J5: 8 | K5: 9 | L5: 10 | M5: 11 | N5: 12 | O5: 13 | P5: 14 | Q5: 15 | R5: 16 | S5: 17 | T5: 18 | U5: 19 | V5: 20 | W5: 21 | X5: 22 | Y5: 23 | Z5: 24 | AA5: 25 | AB5: 26 | AC5: 27 | AD5: 28 | AE5: 29 | AF5: 30 | AG5: 31 | AH5: 32 | AI5: 33 | AJ5: 34 | AK5: 35 | AL5: 36 | AM5: 37 | AN5: 38 | AO5: 39 | AP5: 40 | AQ5: 41 | AR5: 42 | AS5: 43 | AT5: 44 | AU5: 45 | AV5: 46 | AW5: 47 | AX5: 48 | AY5: 49 | AZ5: 50 | BA5: 51 | BB5: 52 | BC5: 53 | BD5: 54 | BE5: 55 | BF5: 56 | BG5: 57 | BH5: 58 | BI5: 59 | BJ5: 60
A6: Año | C6: =ROUNDUP(C5/12,0) -> 1 | D6: =ROUNDUP(D5/12,0) -> 1 | E6: =ROUNDUP(E5/12,0) -> 1 | F6: =ROUNDUP(F5/12,0) -> 1 | G6: =ROUNDUP(G5/12,0) -> 1 | H6: =ROUNDUP(H5/12,0) -> 1 | I6: =ROUNDUP(I5/12,0) -> 1 | J6: =ROUNDUP(J5/12,0) -> 1 | ... BJ6: =ROUNDUP(BJ5/12,0) -> 5
A7: Mes del año | C7: =C5-(C6-1)*12 -> 1 | D7: =D5-(D6-1)*12 -> 2 | E7: =E5-(E6-1)*12 -> 3 | F7: =F5-(F6-1)*12 -> 4 | G7: =G5-(G6-1)*12 -> 5 | H7: =H5-(H6-1)*12 -> 6 | I7: =I5-(I6-1)*12 -> 7 | J7: =J5-(J6-1)*12 -> 8 | ... BJ7: =BJ5-(BJ6-1)*12 -> 12
A9: Clientes
A10: Meta de clientes activos al cierre del mes | B10: clientes | C10: =IF(C6=1,INDEX(Supuestos!$C$22:$N$22,1,C7)*INDEX(Supuestos!$C$11:$E$11,1,$B$2),IF(C6=2,INDEX(Supuestos!$C$11:$E$11,1,$B$2),IF(C6=3,INDEX(Supuestos!$C$12:$E$12,1,$B$2),IF(C6=4,INDEX(Supuestos!$C$13:$E$13,1,$B$2),INDEX(Supuestos!$C$14:$E$14,1,$B$2))))+(IF(C6=2,INDEX(Supuestos!$C$12:$E$12,1,$B$2),IF(C6=3,INDEX(Supuestos!$C$13:$E$13,1,$B$2),IF(C6=4,INDEX(Supuestos!$C$14:$E$14,1,$B$2),INDEX(Supuestos!$C$15:$E$15,1,$B$2))))-IF(C6=2,INDEX(Supuestos!$C$11:$E$11,1,$B$2),IF(C6=3,INDEX(Supuestos!$C$12:$E$12,1,$B$2),IF(C6=4,INDEX(Supuestos!$C$13:$E$13,1,$B$2),INDEX(Supuestos!$C$14:$E$14,1,$B$2)))))*C7/12) -> 12.495 | D10: =IF(D6=1,INDEX(Supuestos!$C$22:$N$22,1,D7)*INDEX(Supuestos!$C$11:$E$11,1,$B$2),IF(D6=2,INDEX(Supuestos!$C$11:$E$11,1,$B$2),IF(D6=3,INDEX(Supuestos!$C$12:$E$12,1,$B$2),IF(D6=4,INDEX(Supuestos!$C$13:$E$13,1,$B$2),INDEX(Supuestos!$C$14:$E$14,1,$B$2))))+(IF(D6=2,INDEX(Supuestos!$C$12:$E$12,1,$B$2),IF(D6=3,INDEX(Supuestos!$C$13:$E$13,1,$B$2),IF(D6=4,INDEX(Supuestos!$C$14:$E$14,1,$B$2),INDEX(Supuestos!$C$15:$E$15,1,$B$2))))-IF(D6=2,INDEX(Supuestos!$C$11:$E$11,1,$B$2),IF(D6=3,INDEX(Supuestos!$C$12:$E$12,1,$B$2),IF(D6=4,INDEX(Supuestos!$C$13:$E$13,1,$B$2),INDEX(Supuestos!$C$14:$E$14,1,$B$2)))))*D7/12) -> 18.75 | E10: =IF(E6=1,INDEX(Supuestos!$C$22:$N$22,1,E7)*INDEX(Supuestos!$C$11:$E$11,1,$B$2),IF(E6=2,INDEX(Supuestos!$C$11:$E$11,1,$B$2),IF(E6=3,INDEX(Supuestos!$C$12:$E$12,1,$B$2),IF(E6=4,INDEX(Supuestos!$C$13:$E$13,1,$B$2),INDEX(Supuestos!$C$14:$E$14,1,$B$2))))+(IF(E6=2,INDEX(Supuestos!$C$12:$E$12,1,$B$2),IF(E6=3,INDEX(Supuestos!$C$13:$E$13,1,$B$2),IF(E6=4,INDEX(Supuestos!$C$14:$E$14,1,$B$2),INDEX(Supuestos!$C$15:$E$15,1,$B$2))))-IF(E6=2,INDEX(Supuestos!$C$11:$E$11,1,$B$2),IF(E6=3,INDEX(Supuestos!$C$12:$E$12,1,$B$2),IF(E6=4,INDEX(Supuestos!$C$13:$E$13,1,$B$2),INDEX(Supuestos!$C$14:$E$14,1,$B$2)))))*E7/12) -> 31.245 | F10: =IF(F6=1,INDEX(Supuestos!$C$22:$N$22,1,F7)*INDEX(Supuestos!$C$11:$E$11,1,$B$2),IF(F6=2,INDEX(Supuestos!$C$11:$E$11,1,$B$2),IF(F6=3,INDEX(Supuestos!$C$12:$E$12,1,$B$2),IF(F6=4,INDEX(Supuestos!$C$13:$E$13,1,$B$2),INDEX(Supuestos!$C$14:$E$14,1,$B$2))))+(IF(F6=2,INDEX(Supuestos!$C$12:$E$12,1,$B$2),IF(F6=3,INDEX(Supuestos!$C$13:$E$13,1,$B$2),IF(F6=4,INDEX(Supuestos!$C$14:$E$14,1,$B$2),INDEX(Supuestos!$C$15:$E$15,1,$B$2))))-IF(F6=2,INDEX(Supuestos!$C$11:$E$11,1,$B$2),IF(F6=3,INDEX(Supuestos!$C$12:$E$12,1,$B$2),IF(F6=4,INDEX(Supuestos!$C$13:$E$13,1,$B$2),INDEX(Supuestos!$C$14:$E$14,1,$B$2)))))*F7/12) -> 43.755 | G10: =IF(G6=1,INDEX(Supuestos!$C$22:$N$22,1,G7)*INDEX(Supuestos!$C$11:$E$11,1,$B$2),IF(G6=2,INDEX(Supuestos!$C$11:$E$11,1,$B$2),IF(G6=3,INDEX(Supuestos!$C$12:$E$12,1,$B$2),IF(G6=4,INDEX(Supuestos!$C$13:$E$13,1,$B$2),INDEX(Supuestos!$C$14:$E$14,1,$B$2))))+(IF(G6=2,INDEX(Supuestos!$C$12:$E$12,1,$B$2),IF(G6=3,INDEX(Supuestos!$C$13:$E$13,1,$B$2),IF(G6=4,INDEX(Supuestos!$C$14:$E$14,1,$B$2),INDEX(Supuestos!$C$15:$E$15,1,$B$2))))-IF(G6=2,INDEX(Supuestos!$C$11:$E$11,1,$B$2),IF(G6=3,INDEX(Supuestos!$C$12:$E$12,1,$B$2),IF(G6=4,INDEX(Supuestos!$C$13:$E$13,1,$B$2),INDEX(Supuestos!$C$14:$E$14,1,$B$2)))))*G7/12) -> 56.25 | H10: =IF(H6=1,INDEX(Supuestos!$C$22:$N$22,1,H7)*INDEX(Supuestos!$C$11:$E$11,1,$B$2),IF(H6=2,INDEX(Supuestos!$C$11:$E$11,1,$B$2),IF(H6=3,INDEX(Supuestos!$C$12:$E$12,1,$B$2),IF(H6=4,INDEX(Supuestos!$C$13:$E$13,1,$B$2),INDEX(Supuestos!$C$14:$E$14,1,$B$2))))+(IF(H6=2,INDEX(Supuestos!$C$12:$E$12,1,$B$2),IF(H6=3,INDEX(Supuestos!$C$13:$E$13,1,$B$2),IF(H6=4,INDEX(Supuestos!$C$14:$E$14,1,$B$2),INDEX(Supuestos!$C$15:$E$15,1,$B$2))))-IF(H6=2,INDEX(Supuestos!$C$11:$E$11,1,$B$2),IF(H6=3,INDEX(Supuestos!$C$12:$E$12,1,$B$2),IF(H6=4,INDEX(Supuestos!$C$13:$E$13,1,$B$2),INDEX(Supuestos!$C$14:$E$14,1,$B$2)))))*H7/12) -> 68.745 | I10: =IF(I6=1,INDEX(Supuestos!$C$22:$N$22,1,I7)*INDEX(Supuestos!$C$11:$E$11,1,$B$2),IF(I6=2,INDEX(Supuestos!$C$11:$E$11,1,$B$2),IF(I6=3,INDEX(Supuestos!$C$12:$E$12,1,$B$2),IF(I6=4,INDEX(Supuestos!$C$13:$E$13,1,$B$2),INDEX(Supuestos!$C$14:$E$14,1,$B$2))))+(IF(I6=2,INDEX(Supuestos!$C$12:$E$12,1,$B$2),IF(I6=3,INDEX(Supuestos!$C$13:$E$13,1,$B$2),IF(I6=4,INDEX(Supuestos!$C$14:$E$14,1,$B$2),INDEX(Supuestos!$C$15:$E$15,1,$B$2))))-IF(I6=2,INDEX(Supuestos!$C$11:$E$11,1,$B$2),IF(I6=3,INDEX(Supuestos!$C$12:$E$12,1,$B$2),IF(I6=4,INDEX(Supuestos!$C$13:$E$13,1,$B$2),INDEX(Supuestos!$C$14:$E$14,1,$B$2)))))*I7/12) -> 81.255 | J10: =IF(J6=1,INDEX(Supuestos!$C$22:$N$22,1,J7)*INDEX(Supuestos!$C$11:$E$11,1,$B$2),IF(J6=2,INDEX(Supuestos!$C$11:$E$11,1,$B$2),IF(J6=3,INDEX(Supuestos!$C$12:$E$12,1,$B$2),IF(J6=4,INDEX(Supuestos!$C$13:$E$13,1,$B$2),INDEX(Supuestos!$C$14:$E$14,1,$B$2))))+(IF(J6=2,INDEX(Supuestos!$C$12:$E$12,1,$B$2),IF(J6=3,INDEX(Supuestos!$C$13:$E$13,1,$B$2),IF(J6=4,INDEX(Supuestos!$C$14:$E$14,1,$B$2),INDEX(Supuestos!$C$15:$E$15,1,$B$2))))-IF(J6=2,INDEX(Supuestos!$C$11:$E$11,1,$B$2),IF(J6=3,INDEX(Supuestos!$C$12:$E$12,1,$B$2),IF(J6=4,INDEX(Supuestos!$C$13:$E$13,1,$B$2),INDEX(Supuestos!$C$14:$E$14,1,$B$2)))))*J7/12) -> 100.005 | ... BJ10: =IF(BJ6=1,INDEX(Supuestos!$C$22:$N$22,1,BJ7)*INDEX(Supuestos!$C$11:$E$11,1,$B$2),IF(BJ6=2,INDEX(Supuestos!$C$11:$E$11,1,$B$2),IF(BJ6=3,INDEX(Supuestos!$C$12:$E$12,1,$B$2),IF(BJ6=4,INDEX(Supuestos!$C$13:$E$13,1,$B$2),INDEX(Supuestos!$C$14:$E$14,1,$B$2))))+(IF(BJ6=2,INDEX(Supuestos!$C$12:$E$12,1,$B$2),IF(BJ6=3,INDEX(Supuestos!$C$13:$E$13,1,$B$2),IF(BJ6=4,INDEX(Supuestos!$C$14:$E$14,1,$B$2),INDEX(Supuestos!$C$15:$E$15,1,$B$2))))-IF(BJ6=2,INDEX(Supuestos!$C$11:$E$11,1,$B$2),IF(BJ6=3,INDEX(Supuestos!$C$12:$E$12,1,$B$2),IF(BJ6=4,INDEX(Supuestos!$C$13:$E$13,1,$B$2),INDEX(Supuestos!$C$14:$E$14,1,$B$2)))))*BJ7/12) -> 1600
A11: Clientes al inicio del mes | B11: clientes | C11: 0 | D11: =C14 -> 12.495 | E11: =D14 -> 18.75 | F11: =E14 -> 31.245 | G11: =F14 -> 43.755 | H11: =G14 -> 56.25 | I11: =H14 -> 68.745 | J11: =I14 -> 81.255 | K11: =J14 -> 100.005 | ... BJ11: =BI14 -> 1566.6667
A12: Clientes que se retiran | B12: clientes | C12: =C11*INDEX(Supuestos!$C$16:$E$16,1,$B$2) -> 0 | D12: =D11*INDEX(Supuestos!$C$16:$E$16,1,$B$2) -> 0.2499 | E12: =E11*INDEX(Supuestos!$C$16:$E$16,1,$B$2) -> 0.375 | F12: =F11*INDEX(Supuestos!$C$16:$E$16,1,$B$2) -> 0.6249 | G12: =G11*INDEX(Supuestos!$C$16:$E$16,1,$B$2) -> 0.8751 | H12: =H11*INDEX(Supuestos!$C$16:$E$16,1,$B$2) -> 1.125 | I12: =I11*INDEX(Supuestos!$C$16:$E$16,1,$B$2) -> 1.3749 | J12: =J11*INDEX(Supuestos!$C$16:$E$16,1,$B$2) -> 1.6251 | ... BJ12: =BJ11*INDEX(Supuestos!$C$16:$E$16,1,$B$2) -> 31.333333
A13: Clientes nuevos | B13: clientes | C13: =MAX(0,C10-(C11-C12)) -> 12.495 | D13: =MAX(0,D10-(D11-D12)) -> 6.5049 | E13: =MAX(0,E10-(E11-E12)) -> 12.87 | F13: =MAX(0,F10-(F11-F12)) -> 13.1349 | G13: =MAX(0,G10-(G11-G12)) -> 13.3701 | H13: =MAX(0,H10-(H11-H12)) -> 13.62 | I13: =MAX(0,I10-(I11-I12)) -> 13.8849 | J13: =MAX(0,J10-(J11-J12)) -> 20.3751 | ... BJ13: =MAX(0,BJ10-(BJ11-BJ12)) -> 64.666667
A14: Clientes activos al cierre del mes | B14: clientes | C14: =C11-C12+C13 -> 12.495 | D14: =D11-D12+D13 -> 18.75 | E14: =E11-E12+E13 -> 31.245 | F14: =F11-F12+F13 -> 43.755 | G14: =G11-G12+G13 -> 56.25 | H14: =H11-H12+H13 -> 68.745 | I14: =I11-I12+I13 -> 81.255 | J14: =J11-J12+J13 -> 100.005 | ... BJ14: =BJ11-BJ12+BJ13 -> 1600
A16: Ingresos y costos variables
A17: Precio mensual por tienda | B17: COP | C17: =Supuestos!$C$26*(1+Supuestos!$C$27)^(C6-1) -> 39900 | D17: =Supuestos!$C$26*(1+Supuestos!$C$27)^(D6-1) -> 39900 | E17: =Supuestos!$C$26*(1+Supuestos!$C$27)^(E6-1) -> 39900 | F17: =Supuestos!$C$26*(1+Supuestos!$C$27)^(F6-1) -> 39900 | G17: =Supuestos!$C$26*(1+Supuestos!$C$27)^(G6-1) -> 39900 | H17: =Supuestos!$C$26*(1+Supuestos!$C$27)^(H6-1) -> 39900 | I17: =Supuestos!$C$26*(1+Supuestos!$C$27)^(I6-1) -> 39900 | J17: =Supuestos!$C$26*(1+Supuestos!$C$27)^(J6-1) -> 39900 | ... BJ17: =Supuestos!$C$26*(1+Supuestos!$C$27)^(BJ6-1) -> 48498.699
A18: Ingresos | B18: COP | C18: =C14*C17 -> 498550.5 | D18: =D14*D17 -> 748125 | E18: =E14*E17 -> 1246675.5 | F18: =F14*F17 -> 1745824.5 | G18: =G14*G17 -> 2244375 | H18: =H14*H17 -> 2742925.5 | I18: =I14*I17 -> 3242074.5 | J18: =J14*J17 -> 3990199.5 | ... BJ18: =BJ14*BJ17 -> 77597919
A19: Costo de IA | B19: COP | C19: =C14*Supuestos!$C$29*(1+Supuestos!$C$39)^(C6-1) -> 15618.75 | D19: =D14*Supuestos!$C$29*(1+Supuestos!$C$39)^(D6-1) -> 23437.5 | E19: =E14*Supuestos!$C$29*(1+Supuestos!$C$39)^(E6-1) -> 39056.25 | F19: =F14*Supuestos!$C$29*(1+Supuestos!$C$39)^(F6-1) -> 54693.75 | G19: =G14*Supuestos!$C$29*(1+Supuestos!$C$39)^(G6-1) -> 70312.5 | H19: =H14*Supuestos!$C$29*(1+Supuestos!$C$39)^(H6-1) -> 85931.25 | I19: =I14*Supuestos!$C$29*(1+Supuestos!$C$39)^(I6-1) -> 101568.75 | J19: =J14*Supuestos!$C$29*(1+Supuestos!$C$39)^(J6-1) -> 125006.25 | ... BJ19: =BJ14*Supuestos!$C$29*(1+Supuestos!$C$39)^(BJ6-1) -> 2431012.5
A20: Comisión de pasarela de pagos | B20: COP | C20: =C18*Supuestos!$C$30 -> 14956.515 | D20: =D18*Supuestos!$C$30 -> 22443.75 | E20: =E18*Supuestos!$C$30 -> 37400.265 | F20: =F18*Supuestos!$C$30 -> 52374.735 | G20: =G18*Supuestos!$C$30 -> 67331.25 | H20: =H18*Supuestos!$C$30 -> 82287.765 | I20: =I18*Supuestos!$C$30 -> 97262.235 | J20: =J18*Supuestos!$C$30 -> 119705.99 | ... BJ20: =BJ18*Supuestos!$C$30 -> 2327937.6
A21: Infraestructura en la nube | B21: COP | C21: =IF(C14<=Supuestos!$C$32,Supuestos!$C$31,IF(C14<=Supuestos!$C$34,Supuestos!$C$33,Supuestos!$C$35)) -> 220000 | D21: =IF(D14<=Supuestos!$C$32,Supuestos!$C$31,IF(D14<=Supuestos!$C$34,Supuestos!$C$33,Supuestos!$C$35)) -> 220000 | E21: =IF(E14<=Supuestos!$C$32,Supuestos!$C$31,IF(E14<=Supuestos!$C$34,Supuestos!$C$33,Supuestos!$C$35)) -> 220000 | F21: =IF(F14<=Supuestos!$C$32,Supuestos!$C$31,IF(F14<=Supuestos!$C$34,Supuestos!$C$33,Supuestos!$C$35)) -> 220000 | G21: =IF(G14<=Supuestos!$C$32,Supuestos!$C$31,IF(G14<=Supuestos!$C$34,Supuestos!$C$33,Supuestos!$C$35)) -> 220000 | H21: =IF(H14<=Supuestos!$C$32,Supuestos!$C$31,IF(H14<=Supuestos!$C$34,Supuestos!$C$33,Supuestos!$C$35)) -> 220000 | I21: =IF(I14<=Supuestos!$C$32,Supuestos!$C$31,IF(I14<=Supuestos!$C$34,Supuestos!$C$33,Supuestos!$C$35)) -> 220000 | J21: =IF(J14<=Supuestos!$C$32,Supuestos!$C$31,IF(J14<=Supuestos!$C$34,Supuestos!$C$33,Supuestos!$C$35)) -> 220000 | ... BJ21: =IF(BJ14<=Supuestos!$C$32,Supuestos!$C$31,IF(BJ14<=Supuestos!$C$34,Supuestos!$C$33,Supuestos!$C$35)) -> 800000
A22: Total costos de operación del servicio | B22: COP | C22: =SUM(C19:C21) -> 250575.27 | D22: =SUM(D19:D21) -> 265881.25 | E22: =SUM(E19:E21) -> 296456.52 | F22: =SUM(F19:F21) -> 327068.48 | G22: =SUM(G19:G21) -> 357643.75 | H22: =SUM(H19:H21) -> 388219.02 | I22: =SUM(I19:I21) -> 418830.98 | J22: =SUM(J19:J21) -> 464712.23 | ... BJ22: =SUM(BJ19:BJ21) -> 5558950.1
A23: Margen bruto | B23: COP | C23: =C18-C22 -> 247975.23 | D23: =D18-D22 -> 482243.75 | E23: =E18-E22 -> 950218.98 | F23: =F18-F22 -> 1418756 | G23: =G18-G22 -> 1886731.2 | H23: =H18-H22 -> 2354706.5 | I23: =I18-I22 -> 2823243.5 | J23: =J18-J22 -> 3525487.3 | ... BJ23: =BJ18-BJ22 -> 72038969
A25: Carga de trabajo y equipo
A26: Horas de soporte | B26: horas | C26: =C14*Supuestos!$C$58/60 -> 4.165 | D26: =D14*Supuestos!$C$58/60 -> 6.25 | E26: =E14*Supuestos!$C$58/60 -> 10.415 | F26: =F14*Supuestos!$C$58/60 -> 14.585 | G26: =G14*Supuestos!$C$58/60 -> 18.75 | H26: =H14*Supuestos!$C$58/60 -> 22.915 | I26: =I14*Supuestos!$C$58/60 -> 27.085 | J26: =J14*Supuestos!$C$58/60 -> 33.335 | ... BJ26: =BJ14*Supuestos!$C$58/60 -> 533.33333
A27: Horas de incorporación de clientes nuevos | B27: horas | C27: =C13*Supuestos!$C$59 -> 21.2415 | D27: =D13*Supuestos!$C$59 -> 11.05833 | E27: =E13*Supuestos!$C$59 -> 21.879 | F27: =F13*Supuestos!$C$59 -> 22.32933 | G27: =G13*Supuestos!$C$59 -> 22.72917 | H27: =H13*Supuestos!$C$59 -> 23.154 | I27: =I13*Supuestos!$C$59 -> 23.60433 | J27: =J13*Supuestos!$C$59 -> 34.63767 | ... BJ27: =BJ13*Supuestos!$C$59 -> 109.93333
A28: Horas de ventas | B28: horas | C28: =C13*Supuestos!$C$60 -> 49.98 | D28: =D13*Supuestos!$C$60 -> 26.0196 | E28: =E13*Supuestos!$C$60 -> 51.48 | F28: =F13*Supuestos!$C$60 -> 52.5396 | G28: =G13*Supuestos!$C$60 -> 53.4804 | H28: =H13*Supuestos!$C$60 -> 54.48 | I28: =I13*Supuestos!$C$60 -> 55.5396 | J28: =J13*Supuestos!$C$60 -> 81.5004 | ... BJ28: =BJ13*Supuestos!$C$60 -> 258.66667
A29: Horas de desarrollo y mantenimiento | B29: horas | C29: =Supuestos!$C$61+C14/100*Supuestos!$C$62 -> 80.62475 | D29: =Supuestos!$C$61+D14/100*Supuestos!$C$62 -> 80.9375 | E29: =Supuestos!$C$61+E14/100*Supuestos!$C$62 -> 81.56225 | F29: =Supuestos!$C$61+F14/100*Supuestos!$C$62 -> 82.18775 | G29: =Supuestos!$C$61+G14/100*Supuestos!$C$62 -> 82.8125 | H29: =Supuestos!$C$61+H14/100*Supuestos!$C$62 -> 83.43725 | I29: =Supuestos!$C$61+I14/100*Supuestos!$C$62 -> 84.06275 | J29: =Supuestos!$C$61+J14/100*Supuestos!$C$62 -> 85.00025 | ... BJ29: =Supuestos!$C$61+BJ14/100*Supuestos!$C$62 -> 160
A30: Horas requeridas | B30: horas | C30: =SUM(C26:C29) -> 156.01125 | D30: =SUM(D26:D29) -> 124.26543 | E30: =SUM(E26:E29) -> 165.33625 | F30: =SUM(F26:F29) -> 171.64168 | G30: =SUM(G26:G29) -> 177.77207 | H30: =SUM(H26:H29) -> 183.98625 | I30: =SUM(I26:I29) -> 190.29168 | J30: =SUM(J26:J29) -> 234.47332 | ... BJ30: =SUM(BJ26:BJ29) -> 1061.9333
A31: Capacidad de los fundadores | B31: horas | C31: =Supuestos!$C$51*IF(C6=1,Supuestos!$C$54,IF(C6=2,Supuestos!$C$55,Supuestos!$C$56)) -> 240 | D31: =Supuestos!$C$51*IF(D6=1,Supuestos!$C$54,IF(D6=2,Supuestos!$C$55,Supuestos!$C$56)) -> 240 | E31: =Supuestos!$C$51*IF(E6=1,Supuestos!$C$54,IF(E6=2,Supuestos!$C$55,Supuestos!$C$56)) -> 240 | F31: =Supuestos!$C$51*IF(F6=1,Supuestos!$C$54,IF(F6=2,Supuestos!$C$55,Supuestos!$C$56)) -> 240 | G31: =Supuestos!$C$51*IF(G6=1,Supuestos!$C$54,IF(G6=2,Supuestos!$C$55,Supuestos!$C$56)) -> 240 | H31: =Supuestos!$C$51*IF(H6=1,Supuestos!$C$54,IF(H6=2,Supuestos!$C$55,Supuestos!$C$56)) -> 240 | I31: =Supuestos!$C$51*IF(I6=1,Supuestos!$C$54,IF(I6=2,Supuestos!$C$55,Supuestos!$C$56)) -> 240 | J31: =Supuestos!$C$51*IF(J6=1,Supuestos!$C$54,IF(J6=2,Supuestos!$C$55,Supuestos!$C$56)) -> 240 | ... BJ31: =Supuestos!$C$51*IF(BJ6=1,Supuestos!$C$54,IF(BJ6=2,Supuestos!$C$55,Supuestos!$C$56)) -> 480
A32: Colaboradores contratados | B32: personas | C32: =IF(Supuestos!$C$8=1,MAX(0,ROUNDUP((C30-C31)/Supuestos!$C$57,0)),IF(C5=1,1,IF(C6=1,2,IF(C6=2,3,IF(C6=3,4,5))))) -> 0 | D32: =IF(Supuestos!$C$8=1,MAX(0,ROUNDUP((D30-D31)/Supuestos!$C$57,0)),IF(D5=1,1,IF(D6=1,2,IF(D6=2,3,IF(D6=3,4,5))))) -> 0 | E32: =IF(Supuestos!$C$8=1,MAX(0,ROUNDUP((E30-E31)/Supuestos!$C$57,0)),IF(E5=1,1,IF(E6=1,2,IF(E6=2,3,IF(E6=3,4,5))))) -> 0 | F32: =IF(Supuestos!$C$8=1,MAX(0,ROUNDUP((F30-F31)/Supuestos!$C$57,0)),IF(F5=1,1,IF(F6=1,2,IF(F6=2,3,IF(F6=3,4,5))))) -> 0 | G32: =IF(Supuestos!$C$8=1,MAX(0,ROUNDUP((G30-G31)/Supuestos!$C$57,0)),IF(G5=1,1,IF(G6=1,2,IF(G6=2,3,IF(G6=3,4,5))))) -> 0 | H32: =IF(Supuestos!$C$8=1,MAX(0,ROUNDUP((H30-H31)/Supuestos!$C$57,0)),IF(H5=1,1,IF(H6=1,2,IF(H6=2,3,IF(H6=3,4,5))))) -> 0 | I32: =IF(Supuestos!$C$8=1,MAX(0,ROUNDUP((I30-I31)/Supuestos!$C$57,0)),IF(I5=1,1,IF(I6=1,2,IF(I6=2,3,IF(I6=3,4,5))))) -> 0 | J32: =IF(Supuestos!$C$8=1,MAX(0,ROUNDUP((J30-J31)/Supuestos!$C$57,0)),IF(J5=1,1,IF(J6=1,2,IF(J6=2,3,IF(J6=3,4,5))))) -> 0 | ... BJ32: =IF(Supuestos!$C$8=1,MAX(0,ROUNDUP((BJ30-BJ31)/Supuestos!$C$57,0)),IF(BJ5=1,1,IF(BJ6=1,2,IF(BJ6=2,3,IF(BJ6=3,4,5))))) -> 4
A33: Costo total mensual por colaborador | B33: COP | C33: =Supuestos!$C$50*(1+Supuestos!$C$39)^(C6-1)*(1+Supuestos!$C$48)+IF(Supuestos!$C$50*(1+Supuestos!$C$39)^(C6-1)<=2*Supuestos!$C$37*(1+Supuestos!$C$39)^(C6-1),Supuestos!$C$38*(1+Supuestos!$C$39)^(C6-1)*(1+Supuestos!$C$49),0) -> 3060125.2 | D33: =Supuestos!$C$50*(1+Supuestos!$C$39)^(D6-1)*(1+Supuestos!$C$48)+IF(Supuestos!$C$50*(1+Supuestos!$C$39)^(D6-1)<=2*Supuestos!$C$37*(1+Supuestos!$C$39)^(D6-1),Supuestos!$C$38*(1+Supuestos!$C$39)^(D6-1)*(1+Supuestos!$C$49),0) -> 3060125.2 | E33: =Supuestos!$C$50*(1+Supuestos!$C$39)^(E6-1)*(1+Supuestos!$C$48)+IF(Supuestos!$C$50*(1+Supuestos!$C$39)^(E6-1)<=2*Supuestos!$C$37*(1+Supuestos!$C$39)^(E6-1),Supuestos!$C$38*(1+Supuestos!$C$39)^(E6-1)*(1+Supuestos!$C$49),0) -> 3060125.2 | F33: =Supuestos!$C$50*(1+Supuestos!$C$39)^(F6-1)*(1+Supuestos!$C$48)+IF(Supuestos!$C$50*(1+Supuestos!$C$39)^(F6-1)<=2*Supuestos!$C$37*(1+Supuestos!$C$39)^(F6-1),Supuestos!$C$38*(1+Supuestos!$C$39)^(F6-1)*(1+Supuestos!$C$49),0) -> 3060125.2 | G33: =Supuestos!$C$50*(1+Supuestos!$C$39)^(G6-1)*(1+Supuestos!$C$48)+IF(Supuestos!$C$50*(1+Supuestos!$C$39)^(G6-1)<=2*Supuestos!$C$37*(1+Supuestos!$C$39)^(G6-1),Supuestos!$C$38*(1+Supuestos!$C$39)^(G6-1)*(1+Supuestos!$C$49),0) -> 3060125.2 | H33: =Supuestos!$C$50*(1+Supuestos!$C$39)^(H6-1)*(1+Supuestos!$C$48)+IF(Supuestos!$C$50*(1+Supuestos!$C$39)^(H6-1)<=2*Supuestos!$C$37*(1+Supuestos!$C$39)^(H6-1),Supuestos!$C$38*(1+Supuestos!$C$39)^(H6-1)*(1+Supuestos!$C$49),0) -> 3060125.2 | I33: =Supuestos!$C$50*(1+Supuestos!$C$39)^(I6-1)*(1+Supuestos!$C$48)+IF(Supuestos!$C$50*(1+Supuestos!$C$39)^(I6-1)<=2*Supuestos!$C$37*(1+Supuestos!$C$39)^(I6-1),Supuestos!$C$38*(1+Supuestos!$C$39)^(I6-1)*(1+Supuestos!$C$49),0) -> 3060125.2 | J33: =Supuestos!$C$50*(1+Supuestos!$C$39)^(J6-1)*(1+Supuestos!$C$48)+IF(Supuestos!$C$50*(1+Supuestos!$C$39)^(J6-1)<=2*Supuestos!$C$37*(1+Supuestos!$C$39)^(J6-1),Supuestos!$C$38*(1+Supuestos!$C$39)^(J6-1)*(1+Supuestos!$C$49),0) -> 3060125.2 | ... BJ33: =Supuestos!$C$50*(1+Supuestos!$C$39)^(BJ6-1)*(1+Supuestos!$C$48)+IF(Supuestos!$C$50*(1+Supuestos!$C$39)^(BJ6-1)<=2*Supuestos!$C$37*(1+Supuestos!$C$39)^(BJ6-1),Supuestos!$C$38*(1+Supuestos!$C$39)^(BJ6-1)*(1+Supuestos!$C$49),0) -> 3719601.3
A34: Nómina de colaboradores | B34: COP | C34: =C32*C33 -> 0 | D34: =D32*D33 -> 0 | E34: =E32*E33 -> 0 | F34: =F32*F33 -> 0 | G34: =G32*G33 -> 0 | H34: =H32*H33 -> 0 | I34: =I32*I33 -> 0 | J34: =J32*J33 -> 0 | ... BJ34: =BJ32*BJ33 -> 14878405
A35: Fundadores con salario | B35: personas | C35: =IF(C5>=INDEX(Supuestos!$C$18:$E$18,1,$B$2),Supuestos!$C$51,0) -> 0 | D35: =IF(D5>=INDEX(Supuestos!$C$18:$E$18,1,$B$2),Supuestos!$C$51,0) -> 0 | E35: =IF(E5>=INDEX(Supuestos!$C$18:$E$18,1,$B$2),Supuestos!$C$51,0) -> 0 | F35: =IF(F5>=INDEX(Supuestos!$C$18:$E$18,1,$B$2),Supuestos!$C$51,0) -> 0 | G35: =IF(G5>=INDEX(Supuestos!$C$18:$E$18,1,$B$2),Supuestos!$C$51,0) -> 0 | H35: =IF(H5>=INDEX(Supuestos!$C$18:$E$18,1,$B$2),Supuestos!$C$51,0) -> 0 | I35: =IF(I5>=INDEX(Supuestos!$C$18:$E$18,1,$B$2),Supuestos!$C$51,0) -> 0 | J35: =IF(J5>=INDEX(Supuestos!$C$18:$E$18,1,$B$2),Supuestos!$C$51,0) -> 0 | ... BJ35: =IF(BJ5>=INDEX(Supuestos!$C$18:$E$18,1,$B$2),Supuestos!$C$51,0) -> 3
A36: Costo total mensual por fundador | B36: COP | C36: =Supuestos!$C$52*(1+Supuestos!$C$39)^(C6-1)*(1+Supuestos!$C$48)+IF(Supuestos!$C$52*(1+Supuestos!$C$39)^(C6-1)<=2*Supuestos!$C$37*(1+Supuestos!$C$39)^(C6-1),Supuestos!$C$38*(1+Supuestos!$C$39)^(C6-1)*(1+Supuestos!$C$49),0) -> 4443645.2 | D36: =Supuestos!$C$52*(1+Supuestos!$C$39)^(D6-1)*(1+Supuestos!$C$48)+IF(Supuestos!$C$52*(1+Supuestos!$C$39)^(D6-1)<=2*Supuestos!$C$37*(1+Supuestos!$C$39)^(D6-1),Supuestos!$C$38*(1+Supuestos!$C$39)^(D6-1)*(1+Supuestos!$C$49),0) -> 4443645.2 | E36: =Supuestos!$C$52*(1+Supuestos!$C$39)^(E6-1)*(1+Supuestos!$C$48)+IF(Supuestos!$C$52*(1+Supuestos!$C$39)^(E6-1)<=2*Supuestos!$C$37*(1+Supuestos!$C$39)^(E6-1),Supuestos!$C$38*(1+Supuestos!$C$39)^(E6-1)*(1+Supuestos!$C$49),0) -> 4443645.2 | F36: =Supuestos!$C$52*(1+Supuestos!$C$39)^(F6-1)*(1+Supuestos!$C$48)+IF(Supuestos!$C$52*(1+Supuestos!$C$39)^(F6-1)<=2*Supuestos!$C$37*(1+Supuestos!$C$39)^(F6-1),Supuestos!$C$38*(1+Supuestos!$C$39)^(F6-1)*(1+Supuestos!$C$49),0) -> 4443645.2 | G36: =Supuestos!$C$52*(1+Supuestos!$C$39)^(G6-1)*(1+Supuestos!$C$48)+IF(Supuestos!$C$52*(1+Supuestos!$C$39)^(G6-1)<=2*Supuestos!$C$37*(1+Supuestos!$C$39)^(G6-1),Supuestos!$C$38*(1+Supuestos!$C$39)^(G6-1)*(1+Supuestos!$C$49),0) -> 4443645.2 | H36: =Supuestos!$C$52*(1+Supuestos!$C$39)^(H6-1)*(1+Supuestos!$C$48)+IF(Supuestos!$C$52*(1+Supuestos!$C$39)^(H6-1)<=2*Supuestos!$C$37*(1+Supuestos!$C$39)^(H6-1),Supuestos!$C$38*(1+Supuestos!$C$39)^(H6-1)*(1+Supuestos!$C$49),0) -> 4443645.2 | I36: =Supuestos!$C$52*(1+Supuestos!$C$39)^(I6-1)*(1+Supuestos!$C$48)+IF(Supuestos!$C$52*(1+Supuestos!$C$39)^(I6-1)<=2*Supuestos!$C$37*(1+Supuestos!$C$39)^(I6-1),Supuestos!$C$38*(1+Supuestos!$C$39)^(I6-1)*(1+Supuestos!$C$49),0) -> 4443645.2 | J36: =Supuestos!$C$52*(1+Supuestos!$C$39)^(J6-1)*(1+Supuestos!$C$48)+IF(Supuestos!$C$52*(1+Supuestos!$C$39)^(J6-1)<=2*Supuestos!$C$37*(1+Supuestos!$C$39)^(J6-1),Supuestos!$C$38*(1+Supuestos!$C$39)^(J6-1)*(1+Supuestos!$C$49),0) -> 4443645.2 | ... BJ36: =Supuestos!$C$52*(1+Supuestos!$C$39)^(BJ6-1)*(1+Supuestos!$C$48)+IF(Supuestos!$C$52*(1+Supuestos!$C$39)^(BJ6-1)<=2*Supuestos!$C$37*(1+Supuestos!$C$39)^(BJ6-1),Supuestos!$C$38*(1+Supuestos!$C$39)^(BJ6-1)*(1+Supuestos!$C$49),0) -> 5401278.5
A37: Nómina de fundadores | B37: COP | C37: =C35*C36 -> 0 | D37: =D35*D36 -> 0 | E37: =E35*E36 -> 0 | F37: =F35*F36 -> 0 | G37: =G35*G36 -> 0 | H37: =H35*H36 -> 0 | I37: =I35*I36 -> 0 | J37: =J35*J36 -> 0 | ... BJ37: =BJ35*BJ36 -> 16203835
A38: Personas en el equipo (fundadores + colaboradores) | B38: personas | C38: =Supuestos!$C$51+C32 -> 3 | D38: =Supuestos!$C$51+D32 -> 3 | E38: =Supuestos!$C$51+E32 -> 3 | F38: =Supuestos!$C$51+F32 -> 3 | G38: =Supuestos!$C$51+G32 -> 3 | H38: =Supuestos!$C$51+H32 -> 3 | I38: =Supuestos!$C$51+I32 -> 3 | J38: =Supuestos!$C$51+J32 -> 3 | ... BJ38: =Supuestos!$C$51+BJ32 -> 7
A40: Gastos operativos
A41: Nómina total | B41: COP | C41: =C34+C37 -> 0 | D41: =D34+D37 -> 0 | E41: =E34+E37 -> 0 | F41: =F34+F37 -> 0 | G41: =G34+G37 -> 0 | H41: =H34+H37 -> 0 | I41: =I34+I37 -> 0 | J41: =J34+J37 -> 0 | ... BJ41: =BJ34+BJ37 -> 31082241
A42: Marketing y adquisición de clientes | B42: COP | C42: =C13*INDEX(Supuestos!$C$17:$E$17,1,$B$2)*(1+Supuestos!$C$39)^(C6-1) -> 624750 | D42: =D13*INDEX(Supuestos!$C$17:$E$17,1,$B$2)*(1+Supuestos!$C$39)^(D6-1) -> 325245 | E42: =E13*INDEX(Supuestos!$C$17:$E$17,1,$B$2)*(1+Supuestos!$C$39)^(E6-1) -> 643500 | F42: =F13*INDEX(Supuestos!$C$17:$E$17,1,$B$2)*(1+Supuestos!$C$39)^(F6-1) -> 656745 | G42: =G13*INDEX(Supuestos!$C$17:$E$17,1,$B$2)*(1+Supuestos!$C$39)^(G6-1) -> 668505 | H42: =H13*INDEX(Supuestos!$C$17:$E$17,1,$B$2)*(1+Supuestos!$C$39)^(H6-1) -> 681000 | I42: =I13*INDEX(Supuestos!$C$17:$E$17,1,$B$2)*(1+Supuestos!$C$39)^(I6-1) -> 694245 | J42: =J13*INDEX(Supuestos!$C$17:$E$17,1,$B$2)*(1+Supuestos!$C$39)^(J6-1) -> 1018755 | ... BJ42: =BJ13*INDEX(Supuestos!$C$17:$E$17,1,$B$2)*(1+Supuestos!$C$39)^(BJ6-1) -> 3930136.9
A43: Arriendo de coworking | B43: COP | C43: =IF(C5>=Supuestos!$C$65,Supuestos!$C$64*(1+Supuestos!$C$39)^(C6-1),0) -> 0 | D43: =IF(D5>=Supuestos!$C$65,Supuestos!$C$64*(1+Supuestos!$C$39)^(D6-1),0) -> 0 | E43: =IF(E5>=Supuestos!$C$65,Supuestos!$C$64*(1+Supuestos!$C$39)^(E6-1),0) -> 0 | F43: =IF(F5>=Supuestos!$C$65,Supuestos!$C$64*(1+Supuestos!$C$39)^(F6-1),0) -> 0 | G43: =IF(G5>=Supuestos!$C$65,Supuestos!$C$64*(1+Supuestos!$C$39)^(G6-1),0) -> 0 | H43: =IF(H5>=Supuestos!$C$65,Supuestos!$C$64*(1+Supuestos!$C$39)^(H6-1),0) -> 0 | I43: =IF(I5>=Supuestos!$C$65,Supuestos!$C$64*(1+Supuestos!$C$39)^(I6-1),0) -> 0 | J43: =IF(J5>=Supuestos!$C$65,Supuestos!$C$64*(1+Supuestos!$C$39)^(J6-1),0) -> 0 | ... BJ43: =IF(BJ5>=Supuestos!$C$65,Supuestos!$C$64*(1+Supuestos!$C$39)^(BJ6-1),0) -> 607753.12
A44: Gastos administrativos y legales | B44: COP | C44: =IF(C6=1,Supuestos!$C$66,Supuestos!$C$67*(1+Supuestos!$C$39)^(C6-2)) -> 200000 | D44: =IF(D6=1,Supuestos!$C$66,Supuestos!$C$67*(1+Supuestos!$C$39)^(D6-2)) -> 200000 | E44: =IF(E6=1,Supuestos!$C$66,Supuestos!$C$67*(1+Supuestos!$C$39)^(E6-2)) -> 200000 | F44: =IF(F6=1,Supuestos!$C$66,Supuestos!$C$67*(1+Supuestos!$C$39)^(F6-2)) -> 200000 | G44: =IF(G6=1,Supuestos!$C$66,Supuestos!$C$67*(1+Supuestos!$C$39)^(G6-2)) -> 200000 | H44: =IF(H6=1,Supuestos!$C$66,Supuestos!$C$67*(1+Supuestos!$C$39)^(H6-2)) -> 200000 | I44: =IF(I6=1,Supuestos!$C$66,Supuestos!$C$67*(1+Supuestos!$C$39)^(I6-2)) -> 200000 | J44: =IF(J6=1,Supuestos!$C$66,Supuestos!$C$67*(1+Supuestos!$C$39)^(J6-2)) -> 200000 | ... BJ44: =IF(BJ6=1,Supuestos!$C$66,Supuestos!$C$67*(1+Supuestos!$C$39)^(BJ6-2)) -> 463050
A45: Software, herramientas, dominio y SSL | B45: COP | C45: =(Supuestos!$C$68+Supuestos!$C$69)*(1+Supuestos!$C$39)^(C6-1) -> 110000 | D45: =(Supuestos!$C$68+Supuestos!$C$69)*(1+Supuestos!$C$39)^(D6-1) -> 110000 | E45: =(Supuestos!$C$68+Supuestos!$C$69)*(1+Supuestos!$C$39)^(E6-1) -> 110000 | F45: =(Supuestos!$C$68+Supuestos!$C$69)*(1+Supuestos!$C$39)^(F6-1) -> 110000 | G45: =(Supuestos!$C$68+Supuestos!$C$69)*(1+Supuestos!$C$39)^(G6-1) -> 110000 | H45: =(Supuestos!$C$68+Supuestos!$C$69)*(1+Supuestos!$C$39)^(H6-1) -> 110000 | I45: =(Supuestos!$C$68+Supuestos!$C$69)*(1+Supuestos!$C$39)^(I6-1) -> 110000 | J45: =(Supuestos!$C$68+Supuestos!$C$69)*(1+Supuestos!$C$39)^(J6-1) -> 110000 | ... BJ45: =(Supuestos!$C$68+Supuestos!$C$69)*(1+Supuestos!$C$39)^(BJ6-1) -> 133705.69
A46: Total gastos operativos | B46: COP | C46: =SUM(C41:C45)+C91 -> 1105295 | D46: =SUM(D41:D45)+D91 -> 805789.98 | E46: =SUM(E41:E45)+E91 -> 1124045 | F46: =SUM(F41:F45)+F91 -> 1137290 | G46: =SUM(G41:G45)+G91 -> 1149050 | H46: =SUM(H41:H45)+H91 -> 1161545 | I46: =SUM(I41:I45)+I91 -> 1174790 | J46: =SUM(J41:J45)+J91 -> 1499300 | ... BJ46: =SUM(BJ41:BJ45)+BJ91 -> 36368825
A47: Resultado operativo (EBITDA) | B47: COP | C47: =C23-C46 -> -857319.74 | D47: =D23-D46 -> -323546.23 | E47: =E23-E46 -> -173825.99 | F47: =F23-F46 -> 281466.03 | G47: =G23-G46 -> 737681.27 | H47: =H23-H46 -> 1193161.5 | I47: =I23-I46 -> 1648453.5 | J47: =J23-J46 -> 2026187.3 | ... BJ47: =BJ23-BJ46 -> 35670144
A48: Caja acumulada antes de impuestos (incluye inversión inicial) | B48: COP | C48: =-(Supuestos!$C$71+Supuestos!$C$72+Supuestos!$C$73)+C47 -> -2357319.7 | D48: =C48+D47 -> -2680866 | E48: =D48+E47 -> -2854692 | F48: =E48+F47 -> -2573225.9 | G48: =F48+G47 -> -1835544.7 | H48: =G48+H47 -> -642383.16 | I48: =H48+I47 -> 1006070.4 | J48: =I48+J47 -> 3032257.7 | K48: =J48+K47 -> 5820420.2 | ... BJ48: =BI48+BJ47 -> 6.6136793e+08
A49: Memo: valor del trabajo no remunerado de los fundadores | B49: COP | C49: =(Supuestos!$C$51-C35)*C36*C31/Supuestos!$C$51/160 -> 6665467.8 | D49: =(Supuestos!$C$51-D35)*D36*D31/Supuestos!$C$51/160 -> 6665467.8 | E49: =(Supuestos!$C$51-E35)*E36*E31/Supuestos!$C$51/160 -> 6665467.8 | F49: =(Supuestos!$C$51-F35)*F36*F31/Supuestos!$C$51/160 -> 6665467.8 | G49: =(Supuestos!$C$51-G35)*G36*G31/Supuestos!$C$51/160 -> 6665467.8 | H49: =(Supuestos!$C$51-H35)*H36*H31/Supuestos!$C$51/160 -> 6665467.8 | I49: =(Supuestos!$C$51-I35)*I36*I31/Supuestos!$C$51/160 -> 6665467.8 | J49: =(Supuestos!$C$51-J35)*J36*J31/Supuestos!$C$51/160 -> 6665467.8 | ... BJ49: =(Supuestos!$C$51-BJ35)*BJ36*BJ31/Supuestos!$C$51/160 -> 0
A51: Resumen anual (millones de COP salvo indicación)
A52: Concepto | B52: Año 0 | C52: Año 1 | D52: Año 2 | E52: Año 3 | F52: Año 4 | G52: Año 5
A53: Clientes activos al cierre (número) | C53: =INDEX($C$14:$BJ$14,1,12) -> 150 | D53: =INDEX($C$14:$BJ$14,1,24) -> 400 | E53: =INDEX($C$14:$BJ$14,1,36) -> 800 | F53: =INDEX($C$14:$BJ$14,1,48) -> 1200 | G53: =INDEX($C$14:$BJ$14,1,60) -> 1600
A54: Clientes nuevos en el año (número) | C54: =SUMIF($C$6:$BJ$6,1,$C$13:$BJ$13) -> 165.75 | D54: =SUMIF($C$6:$BJ$6,2,$C$13:$BJ$13) -> 313.5 | E54: =SUMIF($C$6:$BJ$6,3,$C$13:$BJ$13) -> 540 | F54: =SUMIF($C$6:$BJ$6,4,$C$13:$BJ$13) -> 636 | G54: =SUMIF($C$6:$BJ$6,5,$C$13:$BJ$13) -> 732
A55: Clientes retirados en el año (número) | C55: =SUMIF($C$6:$BJ$6,1,$C$12:$BJ$12) -> 15.75 | D55: =SUMIF($C$6:$BJ$6,2,$C$12:$BJ$12) -> 63.5 | E55: =SUMIF($C$6:$BJ$6,3,$C$12:$BJ$12) -> 140 | F55: =SUMIF($C$6:$BJ$6,4,$C$12:$BJ$12) -> 236 | G55: =SUMIF($C$6:$BJ$6,5,$C$12:$BJ$12) -> 332
A56: Precio mensual (COP) | C56: =INDEX($C$17:$BJ$17,1,12) -> 39900 | D56: =INDEX($C$17:$BJ$17,1,24) -> 41895 | E56: =INDEX($C$17:$BJ$17,1,36) -> 43989.75 | F56: =INDEX($C$17:$BJ$17,1,48) -> 46189.238 | G56: =INDEX($C$17:$BJ$17,1,60) -> 48498.699
A57: Ingresos | C57: =SUMIF($C$6:$BJ$6,1,$C$18:$BJ$18)/1000000 -> 37.40625 | D57: =SUMIF($C$6:$BJ$6,2,$C$18:$BJ$18)/1000000 -> 143.49038 | E57: =SUMIF($C$6:$BJ$6,3,$C$18:$BJ$18)/1000000 -> 325.52415 | F57: =SUMIF($C$6:$BJ$6,4,$C$18:$BJ$18)/1000000 -> 563.5087 | G57: =SUMIF($C$6:$BJ$6,5,$C$18:$BJ$18)/1000000 -> 824.47789
A58: Costos de operación del servicio (IA, pasarela, nube) | C58: =SUMIF($C$6:$BJ$6,1,$C$22:$BJ$22)/1000000 -> 4.9340625 | D58: =SUMIF($C$6:$BJ$6,2,$C$22:$BJ$22)/1000000 -> 12.590024 | E58: =SUMIF($C$6:$BJ$6,3,$C$22:$BJ$22)/1000000 -> 26.41385 | F58: =SUMIF($C$6:$BJ$6,4,$C$22:$BJ$22)/1000000 -> 44.159042 | G58: =SUMIF($C$6:$BJ$6,5,$C$22:$BJ$22)/1000000 -> 60.163844
A59: Margen bruto | C59: =C57-C58 -> 32.472187 | D59: =D57-D58 -> 130.90035 | E59: =E57-E58 -> 299.1103 | F59: =F57-F58 -> 519.34966 | G59: =G57-G58 -> 764.31404
A60: Margen bruto (%) | C60: =IF(C57=0,0,C59/C57) -> 0.86809524 | D60: =IF(D57=0,0,D59/D57) -> 0.91225876 | E60: =IF(E57=0,0,E59/E57) -> 0.91885748 | F60: =IF(F57=0,0,F59/F57) -> 0.92163556 | G60: =IF(G57=0,0,G59/G57) -> 0.92702795
A61: Nómina de colaboradores | C61: =SUMIF($C$6:$BJ$6,1,$C$34:$BJ$34)/1000000 -> 0 | D61: =SUMIF($C$6:$BJ$6,2,$C$34:$BJ$34)/1000000 -> 12.852526 | E61: =SUMIF($C$6:$BJ$6,3,$C$34:$BJ$34)/1000000 -> 47.233032 | F61: =SUMIF($C$6:$BJ$6,4,$C$34:$BJ$34)/1000000 -> 99.189367 | G61: =SUMIF($C$6:$BJ$6,5,$C$34:$BJ$34)/1000000 -> 159.94285
A62: Nómina de fundadores | C62: =SUMIF($C$6:$BJ$6,1,$C$37:$BJ$37)/1000000 -> 0 | D62: =SUMIF($C$6:$BJ$6,2,$C$37:$BJ$37)/1000000 -> 0 | E62: =SUMIF($C$6:$BJ$6,3,$C$37:$BJ$37)/1000000 -> 176.36828 | F62: =SUMIF($C$6:$BJ$6,4,$C$37:$BJ$37)/1000000 -> 185.18669 | G62: =SUMIF($C$6:$BJ$6,5,$C$37:$BJ$37)/1000000 -> 194.44603
A63: Marketing y adquisición | C63: =SUMIF($C$6:$BJ$6,1,$C$42:$BJ$42)/1000000 -> 8.2875 | D63: =SUMIF($C$6:$BJ$6,2,$C$42:$BJ$42)/1000000 -> 16.45875 | E63: =SUMIF($C$6:$BJ$6,3,$C$42:$BJ$42)/1000000 -> 29.7675 | F63: =SUMIF($C$6:$BJ$6,4,$C$42:$BJ$42)/1000000 -> 36.812475 | G63: =SUMIF($C$6:$BJ$6,5,$C$42:$BJ$42)/1000000 -> 44.487529
A64: Arriendo, administración, software, equipos y trabajo desde casa | C64: =(SUMIF($C$6:$BJ$6,1,$C$43:$BJ$43)+SUMIF($C$6:$BJ$6,1,$C$44:$BJ$44)+SUMIF($C$6:$BJ$6,1,$C$45:$BJ$45)+SUMIF($C$6:$BJ$6,1,$C$91:$BJ$91))/1000000 -> 5.7665398 | D64: =(SUMIF($C$6:$BJ$6,2,$C$43:$BJ$43)+SUMIF($C$6:$BJ$6,2,$C$44:$BJ$44)+SUMIF($C$6:$BJ$6,2,$C$45:$BJ$45)+SUMIF($C$6:$BJ$6,2,$C$91:$BJ$91))/1000000 -> 11.2468 | E64: =(SUMIF($C$6:$BJ$6,3,$C$43:$BJ$43)+SUMIF($C$6:$BJ$6,3,$C$44:$BJ$44)+SUMIF($C$6:$BJ$6,3,$C$45:$BJ$45)+SUMIF($C$6:$BJ$6,3,$C$91:$BJ$91))/1000000 -> 17.5203 | F64: =(SUMIF($C$6:$BJ$6,4,$C$43:$BJ$43)+SUMIF($C$6:$BJ$6,4,$C$44:$BJ$44)+SUMIF($C$6:$BJ$6,4,$C$45:$BJ$45)+SUMIF($C$6:$BJ$6,4,$C$91:$BJ$91))/1000000 -> 18.396315 | G64: =(SUMIF($C$6:$BJ$6,5,$C$43:$BJ$43)+SUMIF($C$6:$BJ$6,5,$C$44:$BJ$44)+SUMIF($C$6:$BJ$6,5,$C$45:$BJ$45)+SUMIF($C$6:$BJ$6,5,$C$91:$BJ$91))/1000000 -> 19.316131
A65: Total gastos operativos | C65: =SUMIF($C$6:$BJ$6,1,$C$46:$BJ$46)/1000000 -> 14.05404 | D65: =SUMIF($C$6:$BJ$6,2,$C$46:$BJ$46)/1000000 -> 40.558076 | E65: =SUMIF($C$6:$BJ$6,3,$C$46:$BJ$46)/1000000 -> 270.88911 | F65: =SUMIF($C$6:$BJ$6,4,$C$46:$BJ$46)/1000000 -> 339.58485 | G65: =SUMIF($C$6:$BJ$6,5,$C$46:$BJ$46)/1000000 -> 418.19254
A66: Resultado operativo (EBITDA) | C66: =C59-C65 -> 18.418148 | D66: =D59-D65 -> 90.342275 | E66: =E59-E65 -> 28.221191 | F66: =F59-F65 -> 179.76481 | G66: =G59-G65 -> 346.1215
A67: Pérdidas acumuladas por compensar al inicio | C67: =0 -> 0 | D67: =MIN(0,C67+C66) -> 0 | E67: =MIN(0,D67+D66) -> 0 | F67: =MIN(0,E67+E66) -> 0 | G67: =MIN(0,F67+F66) -> 0
A68: Base gravable | C68: =MAX(0,C66+C67) -> 18.418148 | D68: =MAX(0,D66+D67) -> 90.342275 | E68: =MAX(0,E66+E67) -> 28.221191 | F68: =MAX(0,F66+F67) -> 179.76481 | G68: =MAX(0,G66+G67) -> 346.1215
A69: Impuesto de renta | C69: =C68*Supuestos!$C$74 -> 6.4463517 | D69: =D68*Supuestos!$C$74 -> 31.619796 | E69: =E68*Supuestos!$C$74 -> 9.877417 | F69: =F68*Supuestos!$C$74 -> 62.917682 | G69: =G68*Supuestos!$C$74 -> 121.14253
A70: Utilidad neta | C70: =C66-C69 -> 11.971796 | D70: =D66-D69 -> 58.722479 | E70: =E66-E69 -> 18.343774 | F70: =F66-F69 -> 116.84712 | G70: =G66-G69 -> 224.97898
A71: Flujo de caja neto | B71: =-(Supuestos!$C$71+Supuestos!$C$72+Supuestos!$C$73)/1000000 -> -1.5 | C71: =C70 -> 11.971796 | D71: =D70 -> 58.722479 | E71: =E70 -> 18.343774 | F71: =F70 -> 116.84712 | G71: =G70 -> 224.97898
A72: Flujo de caja acumulado | B72: =B71 -> -1.5 | C72: =B72+C71 -> 10.471796 | D72: =C72+D71 -> 69.194275 | E72: =D72+E71 -> 87.538049 | F72: =E72+F71 -> 204.38517 | G72: =F72+G71 -> 429.36415
A73: ¿Recuperó la inversión? (1 = sí) | C73: =IF(C72>=0,1,0) -> 1 | D73: =IF(D72>=0,1,0) -> 1 | E73: =IF(E72>=0,1,0) -> 1 | F73: =IF(F72>=0,1,0) -> 1 | G73: =IF(G72>=0,1,0) -> 1
A74: Memo: trabajo no remunerado de los fundadores (aporte en especie) | C74: =SUMIF($C$6:$BJ$6,1,$C$49:$BJ$49)/1000000 -> 79.985613 | D74: =SUMIF($C$6:$BJ$6,2,$C$49:$BJ$49)/1000000 -> 125.97734 | E74: =SUMIF($C$6:$BJ$6,3,$C$49:$BJ$49)/1000000 -> 0 | F74: =SUMIF($C$6:$BJ$6,4,$C$49:$BJ$49)/1000000 -> 0 | G74: =SUMIF($C$6:$BJ$6,5,$C$49:$BJ$49)/1000000 -> 0
A75: Personas en el equipo al cierre | C75: =INDEX($C$38:$BJ$38,1,12) -> 3 | D75: =INDEX($C$38:$BJ$38,1,24) -> 4 | E75: =INDEX($C$38:$BJ$38,1,36) -> 5 | F75: =INDEX($C$38:$BJ$38,1,48) -> 6 | G75: =INDEX($C$38:$BJ$38,1,60) -> 7
A76: Ingreso anual por persona del equipo | C76: =IF(C75=0,0,C57/C75) -> 12.46875 | D76: =IF(D75=0,0,D57/D75) -> 35.872594 | E76: =IF(E75=0,0,E57/E75) -> 65.10483 | F76: =IF(F75=0,0,F57/F75) -> 93.918116 | G76: =IF(G75=0,0,G57/G75) -> 117.78256
A77: Punto de equilibrio (clientes activos necesarios, promedio mensual del año) | C77: =ROUNDUP((SUMIF($C$6:$BJ$6,1,$C$46:$BJ$46)+SUMIF($C$6:$BJ$6,1,$C$21:$BJ$21))/12/(INDEX($C$17:$BJ$17,1,12)*(1-Supuestos!$C$30)-Supuestos!$C$29*(1+Supuestos!$C$39)^(1-1)),0) -> 38 | D77: =ROUNDUP((SUMIF($C$6:$BJ$6,2,$C$46:$BJ$46)+SUMIF($C$6:$BJ$6,2,$C$21:$BJ$21))/12/(INDEX($C$17:$BJ$17,1,24)*(1-Supuestos!$C$30)-Supuestos!$C$29*(1+Supuestos!$C$39)^(2-1)),0) -> 94 | E77: =ROUNDUP((SUMIF($C$6:$BJ$6,3,$C$46:$BJ$46)+SUMIF($C$6:$BJ$6,3,$C$21:$BJ$21))/12/(INDEX($C$17:$BJ$17,1,36)*(1-Supuestos!$C$30)-Supuestos!$C$29*(1+Supuestos!$C$39)^(3-1)),0) -> 560 | F77: =ROUNDUP((SUMIF($C$6:$BJ$6,4,$C$46:$BJ$46)+SUMIF($C$6:$BJ$6,4,$C$21:$BJ$21))/12/(INDEX($C$17:$BJ$17,1,48)*(1-Supuestos!$C$30)-Supuestos!$C$29*(1+Supuestos!$C$39)^(4-1)),0) -> 672 | G77: =ROUNDUP((SUMIF($C$6:$BJ$6,5,$C$46:$BJ$46)+SUMIF($C$6:$BJ$6,5,$C$21:$BJ$21))/12/(INDEX($C$17:$BJ$17,1,60)*(1-Supuestos!$C$30)-Supuestos!$C$29*(1+Supuestos!$C$39)^(5-1)),0) -> 784
A79: Indicadores de evaluación
A80: VPN a la TIO (millones COP) | C80: =B71+NPV(Supuestos!$C$75,C71:G71) -> 206.6355
A81: TIR | C81: =IFERROR(IRR(B71:G71),"No existe") -> 10.528371
A82: Año de recuperación de la inversión | C82: =IFERROR(MATCH(1,C73:G73,0),"Más de 5 años") -> 1
A83: Necesidad máxima de caja (millones COP) | C83: =-MIN(0,MIN($C$48:$BJ$48))/1000000 -> 2.854692
A84: Primer mes con resultado operativo positivo | C84: =IFERROR(MATCH(TRUE(),INDEX($C$47:$BJ$47>0,0),0),"No ocurre en 5 años") -> 4
A86: Trabajo desde casa y equipos
A87: Fundadores trabajando sin salario desde casa | B87: personas | C87: =Supuestos!$C$51-C35 -> 3 | D87: =Supuestos!$C$51-D35 -> 3 | E87: =Supuestos!$C$51-E35 -> 3 | F87: =Supuestos!$C$51-F35 -> 3 | G87: =Supuestos!$C$51-G35 -> 3 | H87: =Supuestos!$C$51-H35 -> 3 | I87: =Supuestos!$C$51-I35 -> 3 | J87: =Supuestos!$C$51-J35 -> 3 | ... BJ87: =Supuestos!$C$51-BJ35 -> 0
A88: Energía e internet del hogar (se reembolsan mientras no hay salario) | B88: COP | C88: =C87*(Supuestos!$C$84/1000*(C31/Supuestos!$C$51)*Supuestos!$C$83+Supuestos!$C$85*MIN(1,(C31/Supuestos!$C$51)/Supuestos!$C$86))*(1+Supuestos!$C$39)^(C6-1) -> 45544.98 | D88: =D87*(Supuestos!$C$84/1000*(D31/Supuestos!$C$51)*Supuestos!$C$83+Supuestos!$C$85*MIN(1,(D31/Supuestos!$C$51)/Supuestos!$C$86))*(1+Supuestos!$C$39)^(D6-1) -> 45544.98 | E88: =E87*(Supuestos!$C$84/1000*(E31/Supuestos!$C$51)*Supuestos!$C$83+Supuestos!$C$85*MIN(1,(E31/Supuestos!$C$51)/Supuestos!$C$86))*(1+Supuestos!$C$39)^(E6-1) -> 45544.98 | F88: =F87*(Supuestos!$C$84/1000*(F31/Supuestos!$C$51)*Supuestos!$C$83+Supuestos!$C$85*MIN(1,(F31/Supuestos!$C$51)/Supuestos!$C$86))*(1+Supuestos!$C$39)^(F6-1) -> 45544.98 | G88: =G87*(Supuestos!$C$84/1000*(G31/Supuestos!$C$51)*Supuestos!$C$83+Supuestos!$C$85*MIN(1,(G31/Supuestos!$C$51)/Supuestos!$C$86))*(1+Supuestos!$C$39)^(G6-1) -> 45544.98 | H88: =H87*(Supuestos!$C$84/1000*(H31/Supuestos!$C$51)*Supuestos!$C$83+Supuestos!$C$85*MIN(1,(H31/Supuestos!$C$51)/Supuestos!$C$86))*(1+Supuestos!$C$39)^(H6-1) -> 45544.98 | I88: =I87*(Supuestos!$C$84/1000*(I31/Supuestos!$C$51)*Supuestos!$C$83+Supuestos!$C$85*MIN(1,(I31/Supuestos!$C$51)/Supuestos!$C$86))*(1+Supuestos!$C$39)^(I6-1) -> 45544.98 | J88: =J87*(Supuestos!$C$84/1000*(J31/Supuestos!$C$51)*Supuestos!$C$83+Supuestos!$C$85*MIN(1,(J31/Supuestos!$C$51)/Supuestos!$C$86))*(1+Supuestos!$C$39)^(J6-1) -> 45544.98 | ... BJ88: =BJ87*(Supuestos!$C$84/1000*(BJ31/Supuestos!$C$51)*Supuestos!$C$83+Supuestos!$C$85*MIN(1,(BJ31/Supuestos!$C$51)/Supuestos!$C$86))*(1+Supuestos!$C$39)^(BJ6-1) -> 0
A89: Reserva de reposición de los portátiles de los fundadores | B89: COP | C89: =Supuestos!$C$51*Supuestos!$C$87/Supuestos!$C$88*(1+Supuestos!$C$39)^(C6-1) -> 125000 | D89: =Supuestos!$C$51*Supuestos!$C$87/Supuestos!$C$88*(1+Supuestos!$C$39)^(D6-1) -> 125000 | E89: =Supuestos!$C$51*Supuestos!$C$87/Supuestos!$C$88*(1+Supuestos!$C$39)^(E6-1) -> 125000 | F89: =Supuestos!$C$51*Supuestos!$C$87/Supuestos!$C$88*(1+Supuestos!$C$39)^(F6-1) -> 125000 | G89: =Supuestos!$C$51*Supuestos!$C$87/Supuestos!$C$88*(1+Supuestos!$C$39)^(G6-1) -> 125000 | H89: =Supuestos!$C$51*Supuestos!$C$87/Supuestos!$C$88*(1+Supuestos!$C$39)^(H6-1) -> 125000 | I89: =Supuestos!$C$51*Supuestos!$C$87/Supuestos!$C$88*(1+Supuestos!$C$39)^(I6-1) -> 125000 | J89: =Supuestos!$C$51*Supuestos!$C$87/Supuestos!$C$88*(1+Supuestos!$C$39)^(J6-1) -> 125000 | ... BJ89: =Supuestos!$C$51*Supuestos!$C$87/Supuestos!$C$88*(1+Supuestos!$C$39)^(BJ6-1) -> 151938.28
A90: Portátiles para colaboradores nuevos | B90: COP | C90: =MAX(0,C32)*Supuestos!$C$87*(1+Supuestos!$C$39)^(C6-1) -> 0 | D90: =MAX(0,D32-MAX($C$32:C32))*Supuestos!$C$87*(1+Supuestos!$C$39)^(D6-1) -> 0 | E90: =MAX(0,E32-MAX($C$32:D32))*Supuestos!$C$87*(1+Supuestos!$C$39)^(E6-1) -> 0 | F90: =MAX(0,F32-MAX($C$32:E32))*Supuestos!$C$87*(1+Supuestos!$C$39)^(F6-1) -> 0 | G90: =MAX(0,G32-MAX($C$32:F32))*Supuestos!$C$87*(1+Supuestos!$C$39)^(G6-1) -> 0 | H90: =MAX(0,H32-MAX($C$32:G32))*Supuestos!$C$87*(1+Supuestos!$C$39)^(H6-1) -> 0 | I90: =MAX(0,I32-MAX($C$32:H32))*Supuestos!$C$87*(1+Supuestos!$C$39)^(I6-1) -> 0 | J90: =MAX(0,J32-MAX($C$32:I32))*Supuestos!$C$87*(1+Supuestos!$C$39)^(J6-1) -> 0 | K90: =MAX(0,K32-MAX($C$32:J32))*Supuestos!$C$87*(1+Supuestos!$C$39)^(K6-1) -> 0 | ... BJ90: =MAX(0,BJ32-MAX($C$32:BI32))*Supuestos!$C$87*(1+Supuestos!$C$39)^(BJ6-1) -> 0
A91: Total trabajo desde casa y equipos | B91: COP | C91: =SUM(C88:C90) -> 170544.98 | D91: =SUM(D88:D90) -> 170544.98 | E91: =SUM(E88:E90) -> 170544.98 | F91: =SUM(F88:F90) -> 170544.98 | G91: =SUM(G88:G90) -> 170544.98 | H91: =SUM(H88:H90) -> 170544.98 | I91: =SUM(I88:I90) -> 170544.98 | J91: =SUM(J88:J90) -> 170544.98 | ... BJ91: =SUM(BJ88:BJ90) -> 151938.28
A93: Memo: de lo anterior, trabajo desde casa y equipos (millones COP) | C93: =SUMIF($C$6:$BJ$6,1,$C$91:$BJ$91)/1000000 -> 2.0465398 | D93: =SUMIF($C$6:$BJ$6,2,$C$91:$BJ$91)/1000000 -> 5.0608001 | E93: =SUMIF($C$6:$BJ$6,3,$C$91:$BJ$91)/1000000 -> 4.41 | F93: =SUMIF($C$6:$BJ$6,4,$C$91:$BJ$91)/1000000 -> 4.6305 | G93: =SUMIF($C$6:$BJ$6,5,$C$91:$BJ$91)/1000000 -> 4.862025
